Workbook

Sheet Go-Karts pricelist 2026
D3: Valid as per 1 January 2026
D5: Dealerprice
A6: Art. nr. | B6: Description | C6: EAN-code | D6: excl. VAT
B7: BERG Buzzy
A8: 24.30.08.00 | B8: BERG Buzzy Orange | C8: 8715839100372 | D8: 72.666667
A9: 24.30.15.00 | B9: BERG Buzzy Retro Green | C9: 8715839091182 | D9: 92.666667
A10: 24.30.01.00 | B10: BERG Buzzy Nitro | C10: 8715839059427 | D10: 92.666667
A11: 24.30.02.00 | B11: BERG Buzzy Bloom | C11: 8715839059434 | D11: 92.666667
A12: 24.32.00.00 | B12: BERG Buzzy Nitro 2-in-1 | C12: 8715839068320 | D12: 112.66667
A13: 24.32.02.00 | B13: BERG Buzzy Retro 2-in-1 Green | C13: 8715839075991 | D13: 112.66667
A14: 24.30.12.00 | B14: JEEP Buzzy Sahara | C14: 8715839066661 | D14: 112.66667
A15: 24.30.16.00 | B15: BERG Buzzy Green | C15: 8715839105063 | D15: 79.333333
A16: 24.30.17.00 | B16: BERG Buzzy Pink | C16: 8715839105100 | D16: 92.666667
A17: 24.30.22.00 | B17: BERG Buzzy Police | C17: 8715839086102 | D17: 119.33333
A18: 24.30.11.00 | B18: BERG Buzzy John Deere | C18: 8715839057744 | D18: 119.33333
B19: BERG Reppy
A20: 24.60.07.00 | B20: BERG Reppy Blue | C20: 8715839101522 | D20: 132.66667
A21: 24.60.04.00 | B21: BERG Reppy Roadster | C21: 8715839075328 | D21: 139.33333
A22: 24.60.02.00 | B22: BERG Reppy Rebel | C22: 8715839066630 | D22: 146
A23: 24.61.01.00 | B23: BERG Reppy GP | C23: 8715839081893 | D23: 172.66667
A24: 24.61.00.00 | B24: BERG Reppy BMW | C24: 8715839068993 | D24: 179.33333
A25: 24.60.09.00 | B25: BERG Reppy Volt Black | C25: 8715839105087 | D25: 172.66667
B26: BERG Buddy
A27: 24.20.60.03 | B27: BERG Buddy B-Orange | C27: 8715839067705 | D27: 199.33333
A28: 24.20.64.01 | B28: BERG Buddy Lua | C28: 8715839068207 | D28: 212.66667
A29: 24.20.65.01 | B29: BERG Buddy Cross | C29: 8715839062472 | D29: 219.33333
A30: 24.20.68.00 | B30: BERG Buddy Retro Green | C30: 8715839101799 | D30: 212.66667
A31: 24.20.69.00 | B31: BERG Buddy Trail Green | C31: 8715839105070 | D31: 212.66667
A32: 24.20.70.00 | B32: BERG Buddy Cross Black | C32: 8715839105377 | D32: 219.33333
A33: 24.20.71.00 | B33: BERG Buddy Purple | C33: 8715839105414 | D33: 212.66667
A34: 24.21.24.03 | B34: BERG Buddy John Deere | C34: 8715839100419 | D34: 266
A35: 24.21.34.03 | B35: Jeep® Buddy Wrangler | C35: 8715839100044 | D35: 266
A36: 24.21.54.02 | B36: BERG Buddy Fendt | C36: 8715839100426 | D36: 266
A37: 24.15.01.01 | B37: BERG Choppy Neo | C37: 8715839070187 | D37: 186
A38: 24.20.66.00 | B38: BERG Buddy PRO | C38: 8715839053692 | D38: 322
B39: BERG Rally
A40: 24.40.01.00 | B40: BERG Rally NRG Orange | C40: 8715839082012 | D40: 306
A41: 24.40.02.00 | B41: BERG Rally APX Blue | C41: 8715839081992 | D41: 352.66667
A42: 24.40.03.00 | B42: BERG Rally DRT Green | C42: 8715839086072 | D42: 332.66667
A43: 24.40.11.00 | B43: Jeep® Rally Cherokee | C43: 8715839086096 | D43: 379.33333
A44: 24.41.02.00 | B44: BERG Rally APX Red 3 Gears | C44: 8715839082005 | D44: 519.33333
A45: 24.41.03.00 | B45: BERG Rally DRT Yellow 3 Gears | C45: 8715839086089 | D45: 506
A46: 24.41.04.00 | B46: BERG Rally DRT Black 3 Gears | C46: 8715839103526 | D46: 506
B47: BERG Street-X
A48: 24.10.01.00 | B48: BERG Street-X Venom | C48: 8715839076387 | D48: 256.66667
A49: 24.10.02.00 | B49: BERG Street-X Vibes | C49: 8715839076394 | D49: 256.66667
B50: BERG Specials
A51: 07.12.01.00 | B51: BERG XL Chopper BFR | C51: 8715839064377 | D51: 490
A52: 07.12.00.00 | B52: BERG XL Duo Chopper BF | C52: 8715839058598 | D52: 656.66667
A53: 07.17.00.00 | B53: BERG Duo Coaster BFR | C53: 8715839070668 | D53: 1259.3333
A54: 07.47.00.00 | B54: BERG Duo Coaster E-BFR | C54: 8715839073409 | D54: 2286
A55: 29.07.30.01 | B55: BERG Gran Tour Off-Road | C55: 8715839070255 | D55: 2026
A56: 29.07.40.01 | B56: BERG Gran Tour Racer | C56: 8715839070262 | D56: 2106
A57: 29.41.25.00 | B57: BERG Sunroof Gran Tour | C57: 8715839053685 | D57: 266
B58: XL BFR
A59: 07.10.20.00 | B59: BERG XL B.Pure Blue BFR | C59: 8715839050998 | D59: 370
A60: 07.10.21.00 | B60: BERG XL B.Rapid Blue BFR | C60: 8715839050936 | D60: 399.33333
A61: 07.10.22.00 | B61: BERG XL B.Super Blue BFR | C61: 8715839050943 | D61: 439.33333
A62: 07.10.23.00 | B62: BERG XL B.Super Red BFR | C62: 8715839063486 | D62: 439.33333
A63: 07.10.24.00 | B63: BERG XL B.Super Yellow BFR | C63: 8715839078992 | D63: 439.33333
A64: 07.10.05.00 | B64: BERG XL Black Edition BFR | C64: 8715839050981 | D64: 503.33333
A65: 07.10.14.00 | B65: BERG XL Race GTS BFR | C65: 8715839067651 | D65: 539.33333
A66: 07.10.15.00 | B66: BERG XL Race GTS BFR - Full spec | C66: 8715839068801 | D66: 643.33333
A67: 07.10.17.00 | B67: BERG XL X-ite BFR | C67: 8715839072761 | D67: 470
A68: 07.10.08.01 | B68: BERG XL X-Cross BFR | C68: 8715839070101 | D68: 510
A69: 07.10.03.00 | B69: BERG XL X-Plore BFR | C69: 8715839050967 | D69: 546
A70: 07.11.06.00 | B70: Jeep® Revolution pedal go-kart XL BFR | C70: 8715839051087 | D70: 586
... A77: 07.11.03.00 | B77: BERG XL New Holland BFR | C77: 8715839051056 | D77: 610
B78: BERG XXL-BFR
A79: 07.15.22.00 | B79: BERG XXL B.Super Blue BFR | C79: 8715839063189 | D79: 579.33333
A80: 07.15.23.00 | B80: BERG XXL B.Super Red BFR | C80: 8715839063455 | D80: 579.33333
A81: 07.15.24.00 | B81: BERG XXL B.Super Yellow BFR | C81: 8715839079111 | D81: 579.33333
A82: 07.15.05.00 | B82: BERG XXL Black Edition BFR | C82: 8715839063219 | D82: 643.33333
A83: 07.15.14.00 | B83: BERG XXL Race GTS BFR | C83: 8715839067675 | D83: 679.33333
A84: 07.15.17.00 | B84: BERG XXL X-ite BFR | C84: 8715839072778 | D84: 610
A85: 07.15.08.01 | B85: BERG XXL X-Cross BFR | C85: 8715839070118 | D85: 650
A86: 07.15.03.00 | B86: BERG XXL X-Plore BFR | C86: 8715839063202 | D86: 686
A87: 07.16.06.00 | B87: Jeep® Revolution pedal go-kart XXL BFR | C87: 8715839063301 | D87: 726
A88: 07.15.09.00 | B88: BERG XXL X-Treme BFR | C88: 8715839064599 | D88: 806
A89: 07.16.02.00 | B89: BERG XXL Case IH BFR | C89: 8715839063264 | D89: 750
A90: 07.16.01.00 | B90: BERG XXL CLAAS BFR | C90: 8715839063257 | D90: 750
... A94: 07.16.03.00 | B94: BERG XXL New Holland BFR | C94: 8715839063271 | D94: 750
B95: XL BFR-3
A96: 07.20.22.00 | B96: BERG XL B.Super Blue BFR-3 | C96: 8715839051094 | D96: 612.66667
A97: 07.20.23.00 | B97: BERG XL B.Super Red BFR-3 | C97: 8715839063493 | D97: 612.66667
A98: 07.20.24.00 | B98: BERG XL B.Super Yellow BFR-3 | C98: 8715839079029 | D98: 612.66667
A99: 07.20.05.00 | B99: BERG XL Black Edition BFR-3 | C99: 8715839051124 | D99: 676.66667
A100: 07.20.14.00 | B100: BERG XL Race GTS BFR-3 | C100: 8715839067668 | D100: 712.66667
A101: 07.20.15.00 | B101: BERG XL Race GTS BFR-3 - Full spec | C101: 8715839068818 | D101: 816.66667
A102: 07.20.17.00 | B102: BERG XL X-ite BFR-3 | C102: 8715839072785 | D102: 643.33333
A103: 07.20.08.01 | B103: BERG XL X-Cross BFR-3 | C103: 8715839070125 | D103: 683.33333
A104: 07.20.03.00 | B104: BERG XL X-Plore BFR-3 | C104: 8715839051117 | D104: 719.33333
A105: 07.21.06.00 | B105: Jeep® Revolution pedal go-kart XL BFR-3 | C105: 8715839051216 | D105: 759.33333
A106: 07.20.19.00 | B106: BERG XL X-Treme BFR-3 | C106: 8715839075281 | D106: 839.33333
A107: 07.21.02.00 | B107: BERG XL Case IH BFR-3 | C107: 8715839051179 | D107: 783.33333
... A112: 07.21.03.00 | B112: BERG XL New Holland BFR-3 | C112: 8715839051186 | D112: 783.33333
B113: BERG E-BFR
A114: 07.45.22.00 | B114: BERG XXL B.Super Blue E-BFR | C114: 8715839063318 | D114: 1466
A115: 07.45.23.00 | B115: BERG XXL B.Super Red E-BFR | C115: 8715839063448 | D115: 1466
A116: 07.45.24.00 | B116: BERG XXL B.Super Yellow E-BFR | C116: 8715839079081 | D116: 1466
...

Sheet Ride-Ons pricelist 2026
D3: Valid as per 1 January 2026
D5: inkoopprijs
D6: Dealerprice
A7: Art. nr. | B7: Description | C7: EAN-code | D7: excl. VAT
B8: BERG GO
A9: 24.52.00.00 | B9: BERG GO Twirl Turquoise | C9: 8715839085334 | D9: 39.333333
A10: 24.52.01.00 | B10: BERG GO Twirl Multicolor | C10: 8715839085341 | D10: 39.333333
B11: BERG GO²
A12: 24.50.00.00 | B12: BERG GO² Blue | C12: 8715839065404 | D12: 46
A13: 24.50.01.00 | B13: BERG GO² Pink | C13: 8715839064322 | D13: 46
A14: 24.50.04.00 | B14: BERG GO² SparX Yellow | C14: 8715839070460 | D14: 66
A15: 24.50.07.00 | B15: BERG GO² Retro Pink | C15: 8715839076028 | D15: 66
A16: 24.50.08.00 | B16: BERG GO² Retro Green | C16: 8715839076035 | D16: 66
B17: BERG Moov
A18: 24.81.00.00 | B18: BERG MOOV 10 Blue | C18: 8715839102475 | D18: 39.333333
A19: 24.81.01.00 | B19: BERG MOOV 10 Green | C19: 8715839102482 | D19: 39.333333
A20: 24.81.02.00 | B20: BERG MOOV 10 Pink | C20: 8715839102499 | D20: 39.333333
A21: 24.81.03.00 | B21: BERG MOOV 10 Sand Beige | C21: 8715839105223 | D21: 39.333333
A22: 24.82.00.00 | B22: BERG MOOV 12 Sage Green | C22: 8715839105865 | D22: 52.666667
A23: 24.82.01.00 | B23: BERG MOOV 12 Lavender Purple | C23: 8715839105872 | D23: 52.666667
A24: 24.82.02.00 | B24: BERG MOOV 12 Sand Beige | C24: 8715839105889 | D24: 52.666667
A25: 24.82.03.00 | B25: BERG MOOV 12 Retro Black | C25: 8715839105896 | D25: 59.333333
A26: 24.82.04.00 | B26: BERG MOOV 12 Retro Pink | C26: 8715839105902 | D26: 59.333333
B27: BERG Biky
A28: 24.75.72.00 | B28: BERG Biky Cross Grey | C28: 8715839077810 | D28: 96.666667
A29: 24.75.50.00 | B29: BERG Biky Retro Green | C29: 8715839077773 | D29: 90
A30: 24.75.51.00 | B30: BERG Biky Retro Pink | C30: 8715839077780 | D30: 90
A31: 24.74.70.00 | B31: BERG Biky Cross Blue Handbrake | C31: 8715839085358 | D31: 110
A32: 24.74.71.00 | B32: BERG Biky Cross Grey Handbrake | C32: 8715839085365 | D32: 110
A33: 24.74.72.00 | B33: BERG Biky Trail Green Handbrake | C33: 8715839090819 | D33: 123.33333
A34: 24.74.73.00 | B34: BERG Biky Cross Black Handbrake | C34: 8715839100310 | D34: 110
A35: 24.74.74.00 | B35: BERG Biky Cross White Handbrake | C35: 8715839100655 | D35: 110
A36: 24.74.75.00 | B36: BERG Biky Cross Purple Handbrake | C36: 8715839100662 | D36: 110
A37: 24.74.76.00 | B37: BERG Biky Cross Green Handbrake | C37: 8715839103366 | D37: 110
A38: 24.74.77.00 | B38: BERG Biky Trail Sand Handbrake | C38: 8715839103373 | D38: 123.33333
A39: 24.74.78.00 | B39: BERG Biky Cross Red Handbrake | C39: 8715839105216 | D39: 110
B40: BERG Nexo
A41: 24.77.00.00 | B41: BERG Nexo Foldable Lime | C41: 8715839090529 | D41: 52.666667
A42: 24.77.01.00 | B42: BERG Nexo Foldable Blue | C42: 8715839090536 | D42: 52.666667
A43: 24.77.02.00 | B43: BERG Nexo Foldable Red | C43: 8715839090543 | D43: 52.666667
A44: 24.77.03.00 | B44: BERG Nexo Foldable Mint | C44: 8715839090550 | D44: 52.666667
A45: 24.77.04.00 | B45: BERG Nexo Foldable Lights Lime | C45: 8715839090567 | D45: 63.333333
A46: 24.77.05.00 | B46: BERG Nexo Foldable Lights Blue | C46: 8715839090574 | D46: 63.333333
A47: 24.77.06.00 | B47: BERG Nexo Foldable Lights Red | C47: 8715839090581 | D47: 63.333333
A48: 24.77.07.00 | B48: BERG Nexo Foldable Lights Mint | C48: 8715839090598 | D48: 63.333333
A49: 24.77.08.00 | B49: BERG Nexo Foldable Lights LED-deck Lime | C49: 8715839090604 | D49: 72.666667
A50: 24.77.09.00 | B50: BERG Nexo Foldable Lights LED-deck Blue | C50: 8715839090611 | D50: 72.666667
A51: 24.77.10.00 | B51: BERG Nexo Foldable Lights LED-deck Red | C51: 8715839090628 | D51: 72.666667
A52: 24.77.11.00 | B52: BERG Nexo Foldable Lights LED-deck Mint | C52: 8715839090635 | D52: 72.666667
... A56: 24.77.15.00 | B56: BERG Nexo Foldable Lights Magnet-deck Mint | C56: 8715839090673 | D56: 72.666667
B57: BERG Dash
A58: 24.90.00.00 | B58: BERG Dash 14 Sage Green | C58: 8715839103533 | D58: 219.33333
A59: 24.90.01.00 | B59: BERG Dash 14 Sand Beige | C59: 8715839103557 | D59: 219.33333
A60: 24.90.02.00 | B60: BERG Dash 14 Terracotta Red | C60: 8715839103564 | D60: 219.33333
A61: 24.90.03.00 | B61: BERG Dash 14 Lavender Purple | C61: 8715839103571 | D61: 219.33333
A62: 24.91.00.00 | B62: BERG Dash 16 Sage Green | C62: 8715839103588 | D62: 246
A63: 24.91.01.00 | B63: BERG Dash 16 Sand Beige | C63: 8715839103595 | D63: 246
A64: 24.91.02.00 | B64: BERG Dash 16 Terracotta Red | C64: 8715839103601 | D64: 246
A65: 24.91.03.00 | B65: BERG Dash 16 Lavender Purple | C65: 8715839103618 | D65: 246
B66: BERG Proxus
A67: 24.80.00.00 | B67: BERG Proxus X1 Blue/Lime | C67: 8715839091953 | D67: 79.333333
A68: 24.80.01.00 | B68: BERG Proxus X1 Green/Orange | C68: 8715839091960 | D68: 79.333333
A69: 24.80.02.00 | B69: BERG Proxus X1 Grey/Pink | C69: 8715839091977 | D69: 79.333333
A70: 24.80.03.00 | B70: BERG Proxus X1 Neochrome/Black | C70: 8715839091984 | D70: 92.666667
B71: BERG Beach Wagon
A72: 18.07.10.01 | B72: BERG Beach Wagon L | C72: 8715839045222 | D72: 219.33333
A73: 18.07.17.01 | B73: BERG Beach Wagon XL | C73: 8715839045208 | D73: 246
A74: 18.07.12.00 | B74: BERG Beach Wagon L Black | C74: 8715839092028 | D74: 219.33333
A75: 18.07.18.00 | B75: BERG Beach Wagon XL Black | C75: 8715839092035 | D75: 246
B76: BERG Dempy
A77: 25.17.00.02 | B77: BERG Dempy | C77: 8715839045413 | D77: 50
B78: BERG Accessoires
A79: 16.00.00.00 | B79: BERG Safety Flag XS (BERG GO²) | C79: 8715839065732 | D79: 6.6666667
A80: 16.00.01.00 | B80: BERG Carrying Strap | C80: 8715839065749 | D80: 6.6666667
A81: 16.50.00.00 | B81: BERG Push Handle XS | C81: 8715839065725 | D81: 19.333333
A82: 16.00.04.00 | B82: BERG Helmet S | C82: 8715839078909 | D82: 19.333333
A83: 16.00.17.00 | B83: BERG Helmet M | C83: 8715839091885 | D83: 19.333333
A84: 16.00.05.00 | B84: BERG Biky Protection Cushion | C84: 8715839078916 | D84: 6.6666667
A85: 16.00.06.00 | B85: BERG Biky Kickstand | C85: 8715839078923 | D85: 10
A86: 16.00.07.01 | B86: BERG Biky Safety Flag | C86: 8715839104721 | D86: 10
A87: 16.00.18.00 | B87: BERG Protection Set S | C87: 8715839091892 | D87: 19.333333
A88: 16.00.19.00 | B88: BERG Protection Set M | C88: 8715839091908 | D88: 19.333333
A89: 16.00.20.00 | B89: BERG Biky Mudguard set | C89: 8715839091915 | D89: 10
A90: 16.00.23.00 | B90: BERG Biky Number Plate | C90: 8715839100174 | D90: 6.6666667
A91: 16.00.10.00 | B91: BERG Nexo LED Add-On | C91: 8715839090000 | D91: 16.666667
A92: 16.00.12.00 | B92: BERG Nexo Magnet Add-On | C92: 8715839090680 | D92: 16.666667
A93: 16.00.13.00 | B93: BERG Nexo Wheels 120x40mm Lights Blue | C93: 8715839090697 | D93: 16.666667
A94: 16.00.14.00 | B94: BERG Nexo Wheels 120x40mm Lights Orange | C94: 8715839090703 | D94: 16.666667
A95: 16.00.15.00 | B95: BERG Nexo Wheels 120x40mm Lights Mint | C95: 8715839090710 | D95: 16.666667
A96: 16.00.16.00 | B96: BERG Nexo Wheels 120x40mm Lights Pink | C96: 8715839090727 | D96: 16.666667
A97: 16.00.24.00 | B97: BERG MOOV 10 Kickstand | C97: 8715839103465 | D97: 10
A98: 16.00.35.00 | B98: BERG MOOV 12 Kickstand | C98: 8715839105919 | D98: 10
... A107: 16.00.33.00 | B107: BERG MOOV Safety Flag | C107: 8715839104776 | D107: 10
B109: Selective distrubution
B110: Ending product
B111: New product
A114: All product information and prices subject to change without notice
A115: General terms and conditions BERG Toys apply. These can be found at www.bergtoys.com. A copy can be supplied on request.
A116: WWW.DEALERZONE.NET

Sheet Trampoline pricelist 2026
A1: Pricelist Trampolines
D2: Valid as per 1 January 2026
A4: Art. nr. | B4: Description | C4: EAN-code | D4: Dealerprice
B5: Trampoline Regular + Safety net | D5: excl. VAT
B6: BERG Favorit - Regular + Safety Net Comfort
A7: 35.07.33.02 | B7: BERG Favorit Regular 200 Grey + Safety Net Comfort | C7: 8715839102512 | D7: 272.66667
A8: 35.09.33.02 | B8: BERG Favorit Regular 270 Grey + Safety Net Comfort | C8: 8715839102543 | D8: 359.33333
A9: 35.11.33.02 | B9: BERG Favorit Regular 330 Grey + Safety Net Comfort | C9: 8715839102581 | D9: 439.33333
A10: 35.11.37.02 | B10: BERG Favorit Regular 330 Green + Safety Net Comfort | C10: 8715839102598 | D10: 439.33333
A11: 35.12.94.03 | B11: BERG Favorit Regular 380 Grey + Safety Net Comfort | C11: 8715839102680 | D11: 512.66667
A12: 35.12.95.04 | B12: BERG Favorit Regular 380 Black + Safety Net Comfort | C12: 8715839102697 | D12: 526
A13: 35.12.01.05 | B13: BERG Favorit Regular 380 Green + Safety Net Comfort | C13: 8715839102703 | D13: 512.66667
A14: 35.14.94.03 | B14: BERG Favorit Regular 430 Grey + Safety Net Comfort | C14: 8715839102802 | D14: 579.33333
A15: 35.14.95.04 | B15: BERG Favorit Regular 430 Black + Safety Net Comfort | C15: 8715839102826 | D15: 592.66667
A16: 35.14.02.05 | B16: BERG Favorit Regular 430 Green + Safety Net Comfort | C16: 8715839102833 | D16: 579.33333
A17: 35.14.99.03 | B17: BERG Favorit Regular 430 Grey Levels + Safety Net Comfort | C17: 8715839102840 | D17: 612.66667
B18: BERG Champion - Regular + Safety Net Deluxe
A19: 35.41.93.04 | B19: BERG Champion Regular 330 Grey + Safety Net Deluxe | C19: 8715839101065 | D19: 746
A20: 35.42.93.04 | B20: BERG Champion Regular 380 Grey + Safety Net Deluxe | C20: 8715839101072 | D20: 839.33333
A21: 35.44.93.04 | B21: BERG Champion Regular 430 Grey + Safety Net Deluxe | C21: 8715839101089 | D21: 926
A22: 35.44.99.04 | B22: BERG Champion Regular 430 Grey Levels + Safety Net Deluxe | C22: 8715839101096 | D22: 952.66667
A23: 35.44.88.02 | B23: BERG Champion Regular 430 Grey + Safety Net DLX XL | C23: 8715839101492 | D23: 986
A24: 35.44.89.02 | B24: BERG Champion Regular 430 Grey Levels + Safety Net DLX XL | C24: 8715839101102 | D24: 1026
B25: BERG Elite - Regular + Safety Net Deluxe
A26: 37.81.03.03 | B26: BERG Elite Regular 330 Grey + Safety Net Deluxe | C26: 8715839101119 | D26: 966
A27: 37.82.03.03 | B27: BERG Elite Regular 380 Grey + Safety Net Deluxe | C27: 8715839101126 | D27: 1092.6667
A28: 37.84.03.03 | B28: BERG Elite Regular 430 Grey + Safety Net Deluxe | C28: 8715839101133 | D28: 1172.6667
A29: 37.84.13.04 | B29: BERG Elite Regular 430 Grey Levels + Safety Net Deluxe | C29: 8715839101140 | D29: 1212.6667
A30: 37.84.23.02 | B30: BERG Elite Regular 430 Grey + Safety Net DLX XL | C30: 8715839101157 | D30: 1232.6667
A31: 37.84.33.02 | B31: BERG Elite Regular 430 Grey Levels + Safety Net DLX XL | C31: 8715839101164 | D31: 1279.3333
B32: BERG Grand Favorit - Regular + Safety Net Comfort
A33: 30.25.65.33 | B33: BERG Grand Favorit Regular 520 Grey + Safety Net Comfort | C33: 8715839102963 | D33: 719.33333
A34: 30.25.65.42 | B34: BERG Grand Favorit Regular 520 Black + Safety Net Comfort | C34: 8715839102970 | D34: 732.66667
A35: 30.25.65.73 | B35: BERG Grand Favorit Regular 520 Green + Safety Net Comfort | C35: 8715839102987 | D35: 719.33333
B36: BERG Grand Champion - Regular + Safety Net Deluxe
A37: 30.35.73.32 | B37: BERG Grand Champion Regular 350 Grey + Safety Net Deluxe | C37: 8715839101171 | D37: 852.66667
A38: 30.35.74.32 | B38: BERG Grand Champion Regular 470 Grey + Safety Net Deluxe | C38: 8715839101188 | D38: 932.66667
A39: 30.35.75.33 | B39: BERG Grand Champion Regular 520 Grey + Safety Net Deluxe | C39: 8715839101195 | D39: 1012.6667
A40: 30.35.95.32 | B40: BERG Grand Champion Regular 520 Grey + Safety Net DLX XL | C40: 8715839101201 | D40: 1092.6667
B41: BERG Grand Elite - Regular + Safety Net Deluxe
A42: 30.45.75.33 | B42: BERG Grand Elite Regular 520 Grey + Safety Net Deluxe | C42: 8715839101218 | D42: 1299.3333
A43: 30.45.95.32 | B43: BERG Grand Elite Regular 520 Grey + Safety Net DLX XL | C43: 8715839101485 | D43: 1379.3333
B44: BERG Ultim Favorit - Regular + Safety Net Comfort
A45: 32.25.62.33 | B45: BERG Ultim Favorit Regular 280 Grey + Safety Net Comfort | C45: 8715839103045 | D45: 446
A46: 32.25.62.43 | B46: BERG Ultim Favorit Regular 280 Black + Safety Net Comfort | C46: 8715839103052 | D46: 459.33333
A47: 32.25.62.73 | B47: BERG Ultim Favorit Regular 280 Green + Safety Net Comfort | C47: 8715839103069 | D47: 446
A48: 32.25.63.32 | B48: BERG Ultim Favorit Regular 330 Grey + Safety Net Comfort | C48: 8715839103137 | D48: 552.66667
A49: 32.25.63.42 | B49: BERG Ultim Favorit Regular 330 Black + Safety Net Comfort | C49: 8715839103144 | D49: 566
A50: 32.25.64.32 | B50: BERG Ultim Favorit Regular 410 Grey + Safety Net Comfort | C50: 8715839103212 | D50: 639.33333
A51: 32.25.64.42 | B51: BERG Ultim Favorit Regular 410 Black + Safety Net Comfort | C51: 8715839103229 | D51: 652.66667
B52: BERG Ultim Champion - Regular + Safety Net Deluxe
A53: 32.35.73.32 | B53: BERG Ultim Champion Regular 330 Grey + Safety Net Deluxe | C53: 8715839084740 | D53: 792.66667
A54: 32.35.94.31 | B54: BERG Ultim Champion Regular 410 Grey + Safety Net DLX XL | C54: 8715839077490 | D54: 1306
A55: 32.35.94.71 | B55: BERG Ultim Champion Regular 410 Green + Safety Net DLX XL | C55: 8715839077506 | D55: 1306
A56: 32.35.94.10 | B56: BERG Ultim Champion ECO Regular 410 + Safety Net DLX XL | C56: 8715839090864 | D56: 1306
A57: 32.35.95.30 | B57: BERG Ultim Champion Regular 500 Grey + Safety Net DLX XL | C57: 8715839084887 | D57: 1612.6667
B58: BERG Ultim Elite - Regular + Safety Net Deluxe
A59: 32.45.95.31 | B59: BERG Ultim Elite Regular 500 Grey + Safety Net DLX XL | C59: 8715839077582 | D59: 1879.3333
B60: BERG Ultim Pro Bouncer - Regular + Safety Net Deluxe
A61: 32.55.95.30 | B61: BERG SPORTS Ultim Pro Bouncer Regular 500 + Safety Net XL | C61: 8715839086294 | D61: 2439.3333
A62: 32.55.96.30 | B62: BERG SPORTS Ultim Pro Bouncer Regular 5x5 + Safety Net XL | C62: 8715839090802 | D62: 3332.6667
B64: Trampoline InGround + Safety net
B65: BERG Favorit - InGround + Safety Net Comfort
A66: 35.07.23.02 | B66: BERG Favorit InGround 200 Grey + Safety Net Comfort | C66: 8715839102505 | D66: 312.66667
A67: 35.09.23.02 | B67: BERG Favorit InGround 270 Grey + Safety Net Comfort | C67: 8715839102536 | D67: 406
A68: 35.11.23.02 | B68: BERG Favorit InGround 330 Grey + Safety Net Comfort | C68: 8715839102567 | D68: 492.66667
A69: 35.11.27.02 | B69: BERG Favorit InGround 330 Green + Safety Net Comfort | C69: 8715839102574 | D69: 492.66667
A70: 35.12.92.03 | B70: BERG Favorit InGround 380 Grey + Safety Net Comfort | C70: 8715839102710 | D70: 566
A71: 35.12.96.04 | B71: BERG Favorit InGround 380 Black + Safety Net Comfort | C71: 8715839102727 | D71: 579.33333
A72: 35.12.04.04 | B72: BERG Favorit InGround 380 Green + Safety Net Comfort | C72: 8715839102734 | D72: 566
A73: 35.14.92.03 | B73: BERG Favorit InGround 430 Grey + Safety Net Comfort | C73: 8715839102857 | D73: 639.33333
A74: 35.14.96.04 | B74: BERG Favorit InGround 430 Black + Safety Net Comfort | C74: 8715839102864 | D74: 652.66667
A75: 35.14.09.04 | B75: BERG Favorit InGround 430 Green + Safety Net Comfort | C75: 8715839102871 | D75: 639.33333
B76: BERG Champion - InGround + Safety Net Deluxe
A77: 35.41.91.04 | B77: BERG Champion InGround 330 Grey + Safety Net Deluxe | C77: 8715839101263 | D77: 746
A78: 35.42.91.04 | B78: BERG Champion InGround 380 Grey + Safety Net Deluxe | C78: 8715839101270 | D78: 839.33333
A79: 35.44.91.04 | B79: BERG Champion InGround 430 Grey + Safety Net Deluxe | C79: 8715839101294 | D79: 926
A80: 35.44.87.02 | B80: BERG Champion InGround 430 Grey + Safety Net DLX XL | C80: 8715839101287 | D80: 986
B81: BERG Elite - InGround + Safety Net Deluxe
A82: 37.91.03.03 | B82: BERG Elite InGround 330 Grey + Safety Net Deluxe | C82: 8715839101300 | D82: 966
A83: 37.92.03.03 | B83: BERG Elite InGround 380 Grey + Safety Net Deluxe | C83: 8715839101317 | D83: 1092.6667
A84: 37.94.03.03 | B84: BERG Elite InGround 430 Grey + Safety Net Deluxe | C84: 8715839101478 | D84: 1172.6667
A85: 37.94.13.04 | B85: BERG Elite InGround 430 Grey Levels + Safety Net Deluxe | C85: 8715839101324 | D85: 1212.6667
A86: 37.94.23.02 | B86: BERG Elite InGround 430 Grey + Safety Net DLX XL | C86: 8715839101331 | D86: 1232.6667
A87: 37.94.33.02 | B87: BERG Elite InGround 430 Grey Levels + Safety Net DLX XL | C87: 8715839101348 | D87: 1279.3333
B88: BERG Grand Favorit - InGround + Safety Net Comfort
A89: 30.23.65.33 | B89: BERG Grand Favorit InGround 520 Grey + Safety Net Comfort | C89: 8715839102901 | D89: 759.33333
A90: 30.23.65.42 | B90: BERG Grand Favorit InGround 520 Black + Safety Net Comfort | C90: 8715839102918 | D90: 772.66667
A91: 30.23.65.73 | B91: BERG Grand Favorit InGround 520 Green + Safety Net Comfort | C91: 8715839102925 | D91: 759.33333
B92: BERG Grand Champion - InGround + Safety Net Deluxe
A93: 30.33.73.32 | B93: BERG Grand Champion InGround 350 Grey + Safety Net Deluxe | C93: 8715839101355 | D93: 852.66667
A94: 30.33.74.32 | B94: BERG Grand Champion InGround 470 Grey + Safety Net Deluxe | C94: 8715839101362 | D94: 932.66667
A95: 30.33.75.33 | B95: BERG Grand Champion InGround 520 Grey + Safety Net Deluxe | C95: 8715839101379 | D95: 1012.6667
A96: 30.33.95.32 | B96: BERG Grand Champion InGround 520 Grey + Safety Net DLX XL | C96: 8715839101386 | D96: 1092.6667
B97: BERG Grand Elite - InGround + Safety Net Deluxe
A98: 30.43.75.33 | B98: BERG Grand Elite InGround 520 Grey + Safety Net Deluxe | C98: 8715839101416 | D98: 1299.3333
A99: 30.43.95.32 | B99: BERG Grand Elite InGround 520 Grey + Safety Net DLX XL | C99: 8715839101409 | D99: 1379.3333
B100: BERG Ultim Favorit - InGround + Safety Net Comfort
A101: 32.23.62.32 | B101: BERG Ultim Favorit InGround 280 Grey + Safety Net Comfort | C101: 8715839103021 | D101: 499.33333
A102: 32.23.62.43 | B102: BERG Ultim Favorit InGround 280 Black + Safety Net Comfort | C102: 8715839103342 | D102: 512.66667
...

Sheet Play pricelist 2026
A1: PLAY
A3: Selective distrubution | D3: Valid as per 1 January 2026
D6: Dealerprice
A7: Art. nr. | B7: Description | C7: EAN-code | D7: excl. VAT
B8: BERG PlayBase Wall
A9: 22.00.01.00 | B9: BERG PlayBase Wall | C9: 8715839102345 | D9: 666
A10: 22.00.02.00 | B10: BERG PlayBase Wall Green | C10: 8715839105131 | D10: 666
A11: 22.01.02.00 | B11: BERG PlayBase Wall + Swing set | C11: 8715839104417 | D11: 692
A12: 22.01.03.00 | B12: BERG PlayBase Wall + Family set | C12: 8715839104424 | D12: 752
A13: 22.01.04.00 | B13: BERG PlayBase Wall + Peak set | C13: 8715839104431 | D13: 951.33
A14: 22.01.05.00 | B14: BERG PlayBase Wall + Sports set | C14: 8715839104448 | D14: 818
B15: BERG Playbase Medium
A16: 22.20.01.00 | B16: BERG PlayBase Medium | C16: 8715839081824 | D16: 999.33
A17: 22.20.04.00 | B17: BERG PlayBase Medium Green | C17: 8715839105148 | D17: 999.33
A18: 22.22.00.00 | B18: BERG PlayBase Medium TL (Climbing net M+Boxing bag) | C18: 8715839081749 | D18: 1231.33
A19: 22.21.05.00 | B19: BERG PlayBase Medium + Swing set | C19: 8715839104455 | D19: 1051.33
A20: 22.21.06.00 | B20: BERG PlayBase Medium + Active set | C20: 8715839104462 | D20: 1044.67
A21: 22.21.07.00 | B21: BERG PlayBase Medium + Toddler set | C21: 8715839104479 | D21: 1091.33
A22: 22.21.08.00 | B22: BERG PlayBase Medium + Ultimate set | C22: 8715839104486 | D22: 1443.33
A23: 22.21.09.00 | B23: BERG PlayBase Medium + Play set | C23: 8715839104493 | D23: 1350.67
A24: 22.22.01.00 | B24: BERG PlayBase Medium + Sports set | C24: 8715839104509 | D24: 1250
B25: BERG Playbase Large
A26: 22.40.01.00 | B26: BERG PlayBase Large | C26: 8715839081855 | D26: 1166
A27: 22.40.05.00 | B27: BERG PlayBase Large Green | C27: 8715839103731 | D27: 1166
A28: 22.42.00.00 | B28: BERG PlayBase Large TL (Climbing net L+Boxing bag) | C28: 8715839081800 | D28: 1464.67
A29: 22.43.00.00 | B29: BERG PlayBase Large TT (Hammock) | C29: 8715839081763 | D29: 1152
A30: 22.41.04.00 | B30: BERG PlayBase Large + Toddler set | C30: 8715839104516 | D30: 1277.33
A31: 22.41.05.00 | B31: BERG PlayBase Large + Family set | C31: 8715839104523 | D31: 1318
A32: 22.41.06.00 | B32: BERG PlayBase Large + Peak set | C32: 8715839104530 | D32: 1477.33
A33: 22.41.07.00 | B33: BERG PlayBase Large + Ultimate set | C33: 8715839104547 | D33: 1670
A34: 22.41.08.00 | B34: BERG PlayBase Large + Play set | C34: 8715839104554 | D34: 1477.33
A35: 22.42.01.00 | B35: BERG PlayBase Large + Sports set | C35: 8715839104561 | D35: 1449.33
B36: BERG PlayBase Extra Large
A37: 22.60.00.00 | B37: BERG PlayBase Extra Large | C37: 8715839102338 | D37: 1332.67
A38: 22.60.01.00 | B38: BERG PlayBase Extra Large Green | C38: 8715839105155 | D38: 1332.67
A39: 22.61.00.00 | B39: BERG PlayBase Extra Large + Active set | C39: 8715839104578 | D39: 1423.33
A40: 22.61.01.00 | B40: BERG PlayBase Extra Large + Family set | C40: 8715839104585 | D40: 1457.33
A41: 22.61.02.00 | B41: BERG PlayBase Extra Large + Ultimate set | C41: 8715839104592 | D41: 1843.33
A42: 22.61.03.00 | B42: BERG PlayBase Extra Large + Play set | C42: 8715839104608 | D42: 1995.33
A43: 22.62.00.00 | B43: BERG PlayBase Extra Large + Sports set | C43: 8715839104615 | D43: 1616
B44: BERG PlayBase accessories
A45: 22.00.00.00 | B45: BERG PlayBase Platform + Slide | C45: 8715839100549 | D45: 266
A46: 20.20.00.00 | B46: BERG PlayBase Baby seat | C46: 8715839077919 | D46: 34.67
A47: 20.21.11.00 | B47: BERG Baby swing | C47: 8715839103816 | D47: 52.67
A48: 20.20.01.00 | B48: BERG PlayBase Basketball hoop | C48: 8715839086119 | D48: 132.67
A49: 20.20.03.00 | B49: BERG PlayBase Soccer target net M | C49: 8715839102161 | D49: 66
A50: 20.20.02.00 | B50: BERG PlayBase Soccer target net L | C50: 8715839086164 | D50: 99.33
A51: 20.20.04.00 | B51: BERG PlayBase Soccer target net XL | C51: 8715839102178 | D51: 132.67
A52: 20.21.09.00 | B52: BERG Seat swing | C52: 8715839103427 | D52: 26
A53: 20.21.02.00 | B53: BERG PlayBase Wooden disc swing | C53: 8715839077940 | D53: 14.67
A54: 20.21.08.00 | B54: BERG Disc swing | C54: 8715839103434 | D54: 26
A55: 20.21.07.00 | B55: BERG Nest swing | C55: 8715839103700 | D55: 86
A56: 20.21.06.00 | B56: BERG Gym rings | C56: 8715839103458 | D56: 19.33
... A68: 20.24.00.00 | B68: BERG PlayBase Hammock | C68: 8715839078022 | D68: 86
B70: Selective distribution
B71: Ending product
B72: New product
A74: All product information and prices subject to change without notice
A75: General terms and conditions BERG Toys apply. These can be found at www.bergtoys.com. A copy can be supplied on request.
A76: WWW.DEALERZONE.NET

Sheet Sports pricelist 2026
A1: SPORTS
D3: Valid as per 1 January 2026
D5: inkoopprijs
D6: Dealerprice
A7: Art. nr. | B7: Omschrijving | C7: EAN-code | D7: excl. VAT
B8: BERG SportsGoal
A9: 20.30.01.00 | B9: BERG SportsGoal S | C9: 8715839090741 | D9: 112.67
A10: 20.30.02.00 | B10: BERG SportsGoal M | C10: 8715839090758 | D10: 146
A11: 20.30.03.00 | B11: BERG SportsGoal L | C11: 8715839091823 | D11: 199.33
A12: 20.31.01.00 | B12: BERG SportsGoal Target Net S | C12: 8715839091830 | D12: 26
A13: 20.31.02.00 | B13: BERG SportsGoal Target Net M | C13: 8715839091847 | D13: 32.67
A14: 20.31.03.00 | B14: BERG SportsGoal Target Net L | C14: 8715839091854 | D14: 39.33
A15: 20.31.10.00 | B15: BERG Soccer Ball Size 5 | C15: 8715839091861 | D15: 19.33
B16: BERG SportsGoal Kits
A17: 22.70.00.00 | B17: BERG SportsGoal S + Target Net | C17: 8715839105032 | D17: 132.67
A18: 22.70.01.00 | B18: BERG SportsGoal M + Target Net | C18: 8715839105049 | D18: 172.67
A19: 22.70.02.00 | B19: BERG SportsGoal L + Target Net | C19: 8715839105056 | D19: 232.67
B21: BERG AirTrack
A22: 36.01.14.01 | B22: BERG AirTrack Home 300 | C22: 8715839103489 | D22: 199.33333
A23: 36.01.24.01 | B23: BERG AirTrack Home 500 | C23: 8715839103496 | D23: 232.66667
A24: 36.02.24.01 | B24: BERG AirTrack Sport 500 | C24: 8715839103502 | D24: 366
B26: BERG Infinity Pods
A27: 35.82.01.00 | B27: BERG Infinity Pods - Set 3 | C27: 8715839090482 | D27: 86
A28: 35.82.02.00 | B28: BERG Infinity Pods - Set 6 | C28: 8715839090499 | D28: 166
A29: 35.82.03.00 | B29: BERG Infinity Pods - Single Pod | C29: 8715839090505 | D29: 39.333333
B32: Selective distrubution
B33: New product
A37: All product information and prices subject to change without notice
A38: General terms and conditions BERG Toys apply. These can be found at www.bergtoys.com. A copy can be supplied on request.
A39: WWW.DEALERZONE.NET

Sheet Pricelist Spareparts 2026
A1: Pricelist Spare parts
A2: Valid as per 1 January 2026
A4: Product number | B4: Product name EN-US | C4: EAN code | D4: EP
A5: 51.07.00.82 | B5: XL Frame - Steering rod secure spring (20x) | C5: 8715839066029 | D5: 8.46
A6: 51.07.00.83 | B6: XL Frame - U-bracket plastic for chair frame (10x) | C6: 8715839066111 | D6: 11.26
A7: 51.07.00.52 | B7: XL Frame - Plastic parts | C7: 8715839056884 | D7: 37.99
A8: 51.07.00.84 | B8: XXL Frame - Chain guard front part | C8: 8715839066036 | D8: 49.33
A9: 51.07.00.85 | B9: XXL Frame - Crank shaft with crank set 140, 36T + pedals | C9: 8715839066128 | D9: 86.67
A10: 51.08.00.00 | B10: E-Frame - Battery 10Ah/24V | C10: 8715839066135 | D10: 366
A11: 51.08.00.01 | B11: E-Frame - Charger 24V | C11: 8715839066142 | D11: 83.33
A12: 51.08.00.02 | B12: E-Frame - Central motor 24V/250W incl. crank set | C12: 8715839066159 | D12: 859.33
A13: 51.08.00.03 | B13: E-Frame - Battery connector | C13: 8715839066166 | D13: 93.33
A14: 51.08.00.04 | B14: E-Frame - Sensor and magnet (set) | C14: 8715839066173 | D14: 55.33
A15: 51.08.00.05 | B15: E-Frame - Display with bracing rod (296mm) | C15: 8715839066180 | D15: 130
A16: 51.08.00.06 | B16: E-Frame - Chain 136s + chain 44s | C16: 8715839066197 | D16: 45.33
... A1822: 51.75.00.70 | B1822: Biky - Sticker Set Cross Red Handbrake | C1822: 8715839105841 | D1822: 19.33

Sheet $13.000 Container
O1: Aangepaste prijs | Q1: Geel gemarkeerd prijzen nog niet 100% final
A2: Pagina 1/1 | E2: 2021 | J2: 2017 | N2: 2022 | W2: 2018 | Z2: $13.000 container price
E5: Dealerprijs | F5: Verkoopadviesprijs | N5: inkoopprijs | O5: verkoopprijs | P5: Verschil in kostprijs % | Q5: Nieuwe kostprijs RMB | R5: Nieuwe kostprijs € | S5: Verschil in prijs | T5: Bruto TF | U5: Diff | Z5: Totaal verhoging MRSP | AA5: Upcharge vrachtkosten | AB5: QTY per container | AC5: Container waarde | AD5: Benodigde upcharge | AE5: Resultaat
A6: Art. nr. | B6: Omschrijving | C6: EAN-code | E6: excl. Btw | F6: incl. Btw | G6: Kostp. RMB | H6: Kostprijs | I6: Bruto TF | N6: excl. BTW | O6: incl. BTW
E7: EP | F7: Consument | J7: EP USD | K7: EP Ireland | L7: EP UK | N7: EP | O7: Consument | S7: Consument | W7: EP USD | X7: EP Ireland | Y7: EP UK
B8: BERG GO
A9: 24.52.00.00 | B9: BERG GO Twirl Turquoise | C9: 8715839085334 | E9: NVT | F9: NVT | G9: NVT | H9: NVT | I9: NVT | N9: =O9/1.5 -> 56.666667 | O9: 85 | P9: NVT | Q9: 168 | R9: =Q9/7.6 -> 22.105263 | S9: NVT | T9: =N9/R9 -> 2.5634921 | U9: NVT | W9: 0 | X9: 0 | Y9: 0 | Z9: NVT | AA9: NVT | AB9: 1032 | AC9: =N9*AB9 -> 58480 | AD9: NVT | AE9: NVT
A10: 24.52.01.00 | B10: BERG GO Twirl Multicolor | C10: 8715839085341 | E10: NVT | F10: NVT | G10: NVT | H10: NVT | I10: NVT | N10: =O10/1.5 -> 56.666667 | O10: 85 | P10: NVT | Q10: 168 | R10: =Q10/7.6 -> 22.105263 | S10: NVT | T10: =N10/R10 -> 2.5634921 | U10: NVT | W10: 0 | X10: 0 | Y10: 0 | Z10: NVT | AA10: NVT | AB10: 1032 | AC10: =N10*AB10 -> 58480 | AD10: NVT | AE10: NVT
B11: BERG GO²
A12: 24.50.00.00 | B12: BERG GO² Blue | C12: 8715839065404 | E12: =F12/1.5 -> 59.333333 | F12: 89 | G12: 194.56 | H12: =G12/7.85 -> 24.784713 | I12: =E12/H12 -> 2.3939487 | J12: 0 | K12: 0 | L12: 0 | N12: =O12/1.5 -> 70 | O12: 105 | P12: =(Q12-G12)/(G12) -> 0.030016447 | Q12: 200.4 | R12: =Q12/7.6 -> 26.368421 | S12: =O12-F12 -> 16 | T12: =N12/R12 -> 2.6546906 | U12: =T12-I12 -> 0.26074188 | W12: 0 | X12: 0 | Y12: 0 | Z12: =S12/F12 -> 0.17977528 | AA12: =11200/AC12 -> 0.13559322 | AB12: 1180 | AC12: =N12*AB12 -> 82600 | AD12: =AA12+P12 -> 0.16560967 | AE12: =AD12-Z12 -> -0.014165613
A13: 24.50.01.00 | B13: BERG GO² Pink | C13: =VLOOKUP(A13,EAN!$A:$C,3,0) -> 8715839064322 | E13: =F13/1.5 -> 59.333333 | F13: 89 | G13: 194.56 | H13: =G13/7.85 -> 24.784713 | I13: =E13/H13 -> 2.3939487 | J13: 0 | K13: 0 | L13: 0 | N13: =O13/1.5 -> 70 | O13: 105 | P13: =(Q13-G13)/(G13) -> 0.030016447 | Q13: 200.4 | R13: =Q13/7.6 -> 26.368421 | S13: =O13-F13 -> 16 | T13: =N13/R13 -> 2.6546906 | U13: =T13-I13 -> 0.26074188 | W13: 0 | X13: 0 | Y13: 0 | Z13: =S13/F13 -> 0.17977528 | AA13: =11200/AC13 -> 0.13559322 | AB13: 1180 | AC13: =N13*AB13 -> 82600 | AD13: =AA13+P13 -> 0.16560967 | AE13: =AD13-Z13 -> -0.014165613
A14: 24.50.02.00 | B14: BERG GO² Mint | C14: =VLOOKUP(A14,EAN!$A:$C,3,0) -> 8715839064339 | E14: =F14/1.5 -> 59.333333 | F14: 89 | G14: 194.56 | H14: =G14/7.85 -> 24.784713 | I14: =E14/H14 -> 2.3939487 | J14: 0 | K14: 0 | L14: 0 | N14: =O14/1.5 -> 70 | O14: 105 | P14: =(Q14-G14)/(G14) -> 0.030016447 | Q14: 200.4 | R14: =Q14/7.6 -> 26.368421 | S14: =O14-F14 -> 16 | T14: =N14/R14 -> 2.6546906 | U14: =T14-I14 -> 0.26074188 | W14: 0 | X14: 0 | Y14: 0 | Z14: =S14/F14 -> 0.17977528 | AA14: =11200/AC14 -> 0.13559322 | AB14: 1180 | AC14: =N14*AB14 -> 82600 | AD14: =AA14+P14 -> 0.16560967 | AE14: =AD14-Z14 -> -0.014165613
A15: 24.50.03.00 | B15: BERG GO² SparX Red | C15: 8715839070453 | E15: =F15/1.5 -> 63.333333 | F15: 95 | G15: 201.19 | H15: =G15/7.85 -> 25.629299 | I15: =E15/H15 -> 2.4711301 | J15: 0 | K15: 0 | L15: 0 | N15: =O15/1.5 -> 76.666667 | O15: 115 | P15: =(Q15-G15)/(G15) -> 0.030021373 | Q15: 207.23 | R15: =Q15/7.6 -> 27.267105 | S15: =O15-F15 -> 20 | T15: =N15/R15 -> 2.8116907 | U15: =T15-I15 -> 0.3405606 | W15: 0 | X15: 0 | Y15: 0 | Z15: =S15/F15 -> 0.21052632 | AA15: =11200/AC15 -> 0.12380251 | AB15: 1180 | AC15: =N15*AB15 -> 90466.667 | AD15: =AA15+P15 -> 0.15382388 | AE15: =AD15-Z15 -> -0.056702437
A16: 24.50.04.00 | B16: BERG GO² SparX Yellow | C16: 8715839070460 | E16: =F16/1.5 -> 63.333333 | F16: 95 | G16: 199.6 | H16: =G16/7.85 -> 25.426752 | I16: =E16/H16 -> 2.490815 | J16: 0 | K16: 0 | L16: 0 | N16: =O16/1.5 -> 76.666667 | O16: 115 | P16: =(Q16-G16)/(G16) -> 0.03001002 | Q16: 205.59 | R16: =Q16/7.6 -> 27.051316 | S16: =O16-F16 -> 20 | T16: =N16/R16 -> 2.8341197 | U16: =T16-I16 -> 0.34330472 | W16: 0 | X16: 0 | Y16: 0 | Z16: =S16/F16 -> 0.21052632 | AA16: =11200/AC16 -> 0.12380251 | AB16: 1180 | AC16: =N16*AB16 -> 90466.667 | AD16: =AA16+P16 -> 0.15381253 | AE16: =AD16-Z16 -> -0.05671379
A17: 24.50.07.00 | B17: BERG GO² Retro Pink | C17: 8715839076028 | E17: =F17/1.5 -> 59.333333 | F17: 89 | G17: 199.07 | H17: =G17/7.85 -> 25.359236 | I17: =E17/H17 -> 2.339713 | N17: =O17/1.5 -> 70 | O17: 105 | P17: =(Q17-G17)/(G17) -> 0.029989451 | Q17: 205.04 | R17: =Q17/7.6 -> 26.978947 | S17: =O17-F17 -> 16 | T17: =N17/R17 -> 2.5946157 | U17: =T17-I17 -> 0.25490269 | Z17: =S17/F17 -> 0.17977528 | AA17: =11200/AC17 -> 0.15503876 | AB17: 1032 | AC17: =N17*AB17 -> 72240 | AD17: =AA17+P17 -> 0.18502821 | AE17: =AD17-Z17 -> 0.0052529297
A18: 24.50.08.00 | B18: BERG GO² Retro Green | C18: 8715839076035 | E18: =F18/1.5 -> 59.333333 | F18: 89 | G18: 199.07 | H18: =G18/7.85 -> 25.359236 | I18: =E18/H18 -> 2.339713 | N18: =O18/1.5 -> 70 | O18: 105 | P18: =(Q18-G18)/(G18) -> 0.029989451 | Q18: 205.04 | R18: =Q18/7.6 -> 26.978947 | S18: =O18-F18 -> 16 | T18: =N18/R18 -> 2.5946157 | U18: =T18-I18 -> 0.25490269 | Z18: =S18/F18 -> 0.17977528 | AA18: =11200/AC18 -> 0.15503876 | AB18: 1032 | AC18: =N18*AB18 -> 72240 | AD18: =AA18+P18 -> 0.18502821 | AE18: =AD18-Z18 -> 0.0052529297
B19: BERG Biky
A20: 24.75.10.00 | B20: BERG Biky Mini Green | C20: 8715839077735 | E20: =F20/1.5 -> 59.333333 | F20: 89 | G20: 187.9 | H20: =G20/7.85 -> 23.936306 | I20: =E20/H20 -> 2.4788008 | J20: =VLOOKUP(A20,Mastersheet!$A:$AK,30,0) -> #N/A | K20: =VLOOKUP(A20,Mastersheet!$A:$AK,32,0) -> #N/A | L20: =VLOOKUP(A20,Mastersheet!$A:$AK,34,0) -> #N/A | N20: =O20/1.5 -> 72.666667 | O20: 109 | P20: =(Q20-G20)/(G20) -> 0.11335817 | Q20: 209.2 | R20: =Q20/7.6 -> 27.526316 | S20: =O20-F20 -> 20 | T20: =N20/R20 -> 2.639898 | U20: =T20-I20 -> 0.16109724 | W20: 0 | X20: 0 | Y20: 0 | Z20: =S20/F20 -> 0.2247191 | AA20: =11200/AC20 -> 0.099437703 | AB20: 1550 | AC20: =N20*AB20 -> 112633.33 | AD20: =AA20+P20 -> 0.21279587 | AE20: =AD20-Z20 -> -0.011923228
A21: 24.75.11.00 | B21: BERG Biky Mini Red | C21: 8715839077742 | E21: =F21/1.5 -> 59.333333 | F21: 89 | G21: 187.9 | H21: =G21/7.85 -> 23.936306 | I21: =E21/H21 -> 2.4788008 | J21: =VLOOKUP(A21,Mastersheet!$A:$AK,30,0) -> #N/A | K21: =VLOOKUP(A21,Mastersheet!$A:$AK,32,0) -> #N/A | L21: =VLOOKUP(A21,Mastersheet!$A:$AK,34,0) -> #N/A | N21: =O21/1.5 -> 72.666667 | O21: 109 | P21: =(Q21-G21)/(G21) -> 0.11335817 | Q21: 209.2 | R21: =Q21/7.6 -> 27.526316 | S21: =O21-F21 -> 20 | T21: =N21/R21 -> 2.639898 | U21: =T21-I21 -> 0.16109724 | W21: 0 | X21: 0 | Y21: 0 | Z21: =S21/F21 -> 0.2247191 | AA21: =11200/AC21 -> 0.099437703 | AB21: 1550 | AC21: =N21*AB21 -> 112633.33 | AD21: =AA21+P21 -> 0.21279587 | AE21: =AD21-Z21 -> -0.011923228
A22: 24.75.30.00 | B22: BERG Biky City Green | C22: 8715839077759 | E22: =F22/1.5 -> 66 | F22: 99 | G22: 221.4 | H22: =G22/7.85 -> 28.203822 | I22: =E22/H22 -> 2.3401084 | J22: =VLOOKUP(A22,Mastersheet!$A:$AK,30,0) -> #N/A | K22: =VLOOKUP(A22,Mastersheet!$A:$AK,32,0) -> #N/A | L22: =VLOOKUP(A22,Mastersheet!$A:$AK,34,0) -> #N/A | N22: =O22/1.5 -> 79.333333 | O22: 119 | P22: =(Q22-G22)/(G22) -> 0.12059621 | Q22: 248.1 | R22: =Q22/7.6 -> 32.644737 | S22: =O22-F22 -> 20 | T22: =N22/R22 -> 2.4302029 | U22: =T22-I22 -> 0.090094474 | W22: 0 | X22: 0 | Y22: 0 | Z22: =S22/F22 -> 0.2020202 | AA22: =11200/AC22 -> 0.091081594 | AB22: 1550 | AC22: =N22*AB22 -> 122966.67 | AD22: =AA22+P22 -> 0.2116778 | AE22: =AD22-Z22 -> 0.0096575979
A23: 24.75.31.00 | B23: BERG Biky City Red | C23: 8715839077766 | E23: =F23/1.5 -> 66 | F23: 99 | G23: 221.4 | H23: =G23/7.85 -> 28.203822 | I23: =E23/H23 -> 2.3401084 | J23: =VLOOKUP(A23,Mastersheet!$A:$AK,30,0) -> #N/A | K23: =VLOOKUP(A23,Mastersheet!$A:$AK,32,0) -> #N/A | L23: =VLOOKUP(A23,Mastersheet!$A:$AK,34,0) -> #N/A | N23: =O23/1.5 -> 79.333333 | O23: 119 | P23: =(Q23-G23)/(G23) -> 0.12059621 | Q23: 248.1 | R23: =Q23/7.6 -> 32.644737 | S23: =O23-F23 -> 20 | T23: =N23/R23 -> 2.4302029 | U23: =T23-I23 -> 0.090094474 | W23: 0 | X23: 0 | Y23: 0 | Z23: =S23/F23 -> 0.2020202 | AA23: =11200/AC23 -> 0.091081594 | AB23: 1550 | AC23: =N23*AB23 -> 122966.67 | AD23: =AA23+P23 -> 0.2116778 | AE23: =AD23-Z23 -> 0.0096575979
A24: 24.75.50.00 | B24: BERG Biky Retro Green | C24: 8715839077773 | E24: =F24/1.5 -> 86 | F24: 129 | G24: 257.7 | H24: =G24/7.85 -> 32.828025 | I24: =E24/H24 -> 2.6197128 | J24: =VLOOKUP(A24,Mastersheet!$A:$AK,30,0) -> #N/A | K24: =VLOOKUP(A24,Mastersheet!$A:$AK,32,0) -> #N/A | L24: =VLOOKUP(A24,Mastersheet!$A:$AK,34,0) -> #N/A | N24: =O24/1.5 -> 103.33333 | O24: 155 | P24: =(Q24-G24)/(G24) -> 0.10865347 | Q24: 285.7 | R24: =Q24/7.6 -> 37.592105 | S24: =O24-F24 -> 26 | T24: =N24/R24 -> 2.7488041 | U24: =T24-I24 -> 0.12909126 | W24: 0 | X24: 0 | Y24: 0 | Z24: =S24/F24 -> 0.20155039 | AA24: =11200/AC24 -> 0.069927159 | AB24: 1550 | AC24: =N24*AB24 -> 160166.67 | AD24: =AA24+P24 -> 0.17858063 | AE24: =AD24-Z24 -> -0.022969755
A25: 24.75.51.00 | B25: BERG Biky Retro Pink | C25: 8715839077780 | E25: =F25/1.5 -> 86 | F25: 129 | G25: 257.7 | H25: =G25/7.85 -> 32.828025 | I25: =E25/H25 -> 2.6197128 | J25: =VLOOKUP(A25,Mastersheet!$A:$AK,30,0) -> #N/A | K25: =VLOOKUP(A25,Mastersheet!$A:$AK,32,0) -> #N/A | L25: =VLOOKUP(A25,Mastersheet!$A:$AK,34,0) -> #N/A | N25: =O25/1.5 -> 103.33333 | O25: 155 | P25: =(Q25-G25)/(G25) -> 0.10865347 | Q25: 285.7 | R25: =Q25/7.6 -> 37.592105 | S25: =O25-F25 -> 26 | T25: =N25/R25 -> 2.7488041 | U25: =T25-I25 -> 0.12909126 | W25: 0 | X25: 0 | Y25: 0 | Z25: =S25/F25 -> 0.20155039 | AA25: =11200/AC25 -> 0.069927159 | AB25: 1550 | AC25: =N25*AB25 -> 160166.67 | AD25: =AA25+P25 -> 0.17858063 | AE25: =AD25-Z25 -> -0.022969755
A26: 24.75.70.00 | B26: BERG Biky Cross Green | C26: 8715839077797 | E26: =F26/1.5 -> 79.333333 | F26: 119 | G26: 250.8 | H26: =G26/7.85 -> 31.949045 | I26: =E26/H26 -> 2.4831207 | N26: =O26/1.5 -> 96.666667 | O26: 145 | P26: =(Q26-G26)/(G26) -> 0.14354067 | Q26: 286.8 | R26: =Q26/7.6 -> 37.736842 | S26: =O26-F26 -> 26 | T26: =N26/R26 -> 2.5615993 | U26: =T26-I26 -> 0.078478576 | Z26: =S26/F26 -> 0.21848739 | AA26: =11200/AC26 -> 0.074749722 | AB26: 1550 | AC26: =N26*AB26 -> 149833.33 | AD26: =AA26+P26 -> 0.21829039 | AE26: =AD26-Z26 -> -0.00019700319
A27: 24.75.71.00 | B27: BERG Biky Cross Red | C27: 8715839077803 | E27: =F27/1.5 -> 79.333333 | F27: 119 | G27: 250.8 | H27: =G27/7.85 -> 31.949045 | I27: =E27/H27 -> 2.4831207 | N27: =O27/1.5 -> 96.666667 | O27: 145 | P27: =(Q27-G27)/(G27) -> 0.14354067 | Q27: 286.8 | R27: =Q27/7.6 -> 37.736842 | S27: =O27-F27 -> 26 | T27: =N27/R27 -> 2.5615993 | U27: =T27-I27 -> 0.078478576 | Z27: =S27/F27 -> 0.21848739 | AA27: =11200/AC27 -> 0.074749722 | AB27: 1550 | AC27: =N27*AB27 -> 149833.33 | AD27: =AA27+P27 -> 0.21829039 | AE27: =AD27-Z27 -> -0.00019700319
A28: 24.75.72.00 | B28: BERG Biky Cross Grey | C28: 8715839077810 | E28: =F28/1.5 -> 79.333333 | F28: 119 | G28: 250.8 | H28: =G28/7.85 -> 31.949045 | I28: =E28/H28 -> 2.4831207 | J28: =VLOOKUP(A28,Mastersheet!$A:$AK,30,0) -> #N/A | K28: =VLOOKUP(A28,Mastersheet!$A:$AK,32,0) -> #N/A | L28: =VLOOKUP(A28,Mastersheet!$A:$AK,34,0) -> #N/A | N28: =O28/1.5 -> 96.666667 | O28: 145 | P28: =(Q28-G28)/(G28) -> 0.14354067 | Q28: 286.8 | R28: =Q28/7.6 -> 37.736842 | S28: =O28-F28 -> 26 | T28: =N28/R28 -> 2.5615993 | U28: =T28-I28 -> 0.078478576 | W28: 0 | X28: 0 | Y28: 0 | Z28: =S28/F28 -> 0.21848739 | AA28: =11200/AC28 -> 0.074749722 | AB28: 1550 | AC28: =N28*AB28 -> 149833.33 | AD28: =AA28+P28 -> 0.21829039 | AE28: =AD28-Z28 -> -0.00019700319
A29: 24.74.30.00 | B29: BERG Biky City Blue Handbrake | C29: 8715839085372 | E29: NVT | F29: NVT | G29: NVT | H29: NVT | I29: NVT | N29: =O29/1.5 -> 86 | O29: 129 | P29: NVT | Q29: =Q23+30 -> 278.1 | R29: =Q29/7.6 -> 36.592105 | S29: NVT | T29: =N29/R29 -> 2.3502337 | U29: NVT | Z29: NVT | AA29: NVT | AB29: 1550 | AC29: =N29*AB29 -> 133300 | AD29: NVT | AE29: NVT
A30: 24.74.70.00 | B30: BERG Biky Cross Blue Handbrake | C30: 8715839085358 | E30: NVT | F30: NVT | G30: NVT | H30: NVT | I30: NVT | N30: =O30/1.5 -> 103.33333 | O30: 155 | P30: NVT | Q30: =Q28+25 -> 311.8 | R30: =Q30/7.6 -> 41.026316 | S30: NVT | T30: =N30/R30 -> 2.5187086 | U30: NVT | Z30: NVT | AA30: NVT | AB30: 1550 | AC30: =N30*AB30 -> 160166.67 | AD30: NVT | AE30: NVT
A31: 24.74.71.00 | B31: BERG Biky Cross Grey Handbrake | C31: 8715839085365 | E31: NVT | F31: NVT | G31: NVT | H31: NVT | I31: NVT | N31: =O31/1.5 -> 103.33333 | O31: 155 | P31: NVT | Q31: =Q28+30 -> 316.8 | R31: =Q31/7.6 -> 41.684211 | S31: NVT | T31: =N31/R31 -> 2.4789562 | U31: NVT | Z31: NVT | AA31: NVT | AB31: 1550 | AC31: =N31*AB31 -> 160166.67 | AD31: NVT | AE31: NVT
B32: BERG BeachWagon
A33: 18.07.10.01 | B33: BERG Beach Wagon L | C33: 8715839045222 | E33: =F33/1.5 -> 159.33333 | F33: 239 | H33: =35.74+37 -> 72.74 | I33: =E33/H33 -> 2.19045 | J33: =VLOOKUP(A33,Mastersheet!$A:$AK,30,0) -> 183.2 | K33: =VLOOKUP(A33,Mastersheet!$A:$AK,32,0) -> 151.83 | L33: =VLOOKUP(A33,Mastersheet!$A:$AK,34,0) -> 121.92 | N33: =O33/1.5 -> 190 | O33: 285 | P33: =(R33-H33)/(H33) -> 0.11850426 | R33: =40.36+41 -> 81.36 | S33: =O33-F33 -> 46 | T33: =N33/R33 -> 2.3352999 | U33: =T33-I33 -> 0.1448499 | W33: 0 | X33: 0 | Y33: 0 | Z33: =S33/F33 -> 0.19246862 | AA33: =11200/AC33 -> 0.03803056 | AB33: 1550 | AC33: =N33*AB33 -> 294500
A34: 18.07.17.01 | B34: BERG Beach Wagon XL | C34: 8715839045208 | E34: =F34/1.5 -> 179.33333 | F34: 269 | H34: =35.74+47 -> 82.74 | I34: =E34/H34 -> 2.1674321 | J34: =VLOOKUP(A34,Mastersheet!$A:$AK,30,0) -> 207.2 | K34: =VLOOKUP(A34,Mastersheet!$A:$AK,32,0) -> 170.12 | L34: =VLOOKUP(A34,Mastersheet!$A:$AK,34,0) -> 139.42 | N34: =O34/1.5 -> 216.66667 | O34: 325 | P34: =(R34-H34)/(H34) -> 0.11626783 | R34: =40.36+52 -> 92.36 | S34: =O34-F34 -> 56 | T34: =N34/R34 -> 2.3458929 | U34: =T34-I34 -> 0.17846077 | W34: 0 | X34: 0 | Y34: 0 | Z34: =S34/F34 -> 0.20817844 | AA34: =11200/AC34 -> 0.033349876 | AB34: 1550 | AC34: =N34*AB34 -> 335833.33
B35: BERG Accessoires
A36: 16.00.01.00 | B36: BERG Carrying Strap | C36: 8715839065749 | E36: =F36/1.5 -> 6.6666667 | F36: 10 | G36: 18 | H36: =G36/7.85 -> 2.2929936 | I36: =E36/H36 -> 2.9074074 | J36: =VLOOKUP(A36,Mastersheet!$A:$AK,30,0) -> #N/A | K36: =VLOOKUP(A36,Mastersheet!$A:$AK,32,0) -> #N/A | L36: =VLOOKUP(A36,Mastersheet!$A:$AK,34,0) -> #N/A | N36: =O36/1.5 -> 9.3333333 | O36: 14 | P36: =(Q36-G36)/(G36) -> 0 | Q36: 18 | R36: =Q36/7.6 -> 2.3684211 | S36: =O36-F36 -> 4 | T36: =N36/R36 -> 3.9407407 | U36: =T36-I36 -> 1.0333333 | W36: 0 | X36: 0 | Y36: 0 | Z36: =S36/F36 -> 0.4 | AA36: =11200/AC36 -> 0.77419355 | AB36: 1550 | AC36: =N36*AB36 -> 14466.667
A37: 16.50.00.00 | B37: BERG Push Handle XS | C37: 8715839065725 | E37: =F37/1.5 -> 16.666667 | F37: 25 | G37: 50 | H37: =G37/7.85 -> 6.3694268 | I37: =E37/H37 -> 2.6166667 | J37: =VLOOKUP(A37,Mastersheet!$A:$AK,30,0) -> #N/A | K37: =VLOOKUP(A37,Mastersheet!$A:$AK,32,0) -> #N/A | L37: =VLOOKUP(A37,Mastersheet!$A:$AK,34,0) -> #N/A | N37: =O37/1.5 -> 19.333333 | O37: 29 | P37: =(Q37-G37)/(G37) -> 0.1 | Q37: 55 | R37: =Q37/7.6 -> 7.2368421 | S37: =O37-F37 -> 4 | T37: =N37/R37 -> 2.6715152 | U37: =T37-I37 -> 0.054848485 | W37: 0 | X37: 0 | Y37: 0 | Z37: =S37/F37 -> 0.16 | AA37: =11200/AC37 -> 0.37374861 | AB37: 1550 | AC37: =N37*AB37 -> 29966.667
A38: 16.00.00.00 | B38: BERG Safety Flag XS | C38: 8715839065732 | E38: =F38/1.5 -> 8.3333333 | F38: 12.5 | G38: 17.6 | H38: =G38/7.85 -> 2.2420382 | I38: =E38/H38 -> 3.7168561 | J38: =VLOOKUP(A38,Mastersheet!$A:$AK,30,0) -> #N/A | K38: =VLOOKUP(A38,Mastersheet!$A:$AK,32,0) -> #N/A | L38: =VLOOKUP(A38,Mastersheet!$A:$AK,34,0) -> #N/A | N38: =O38/1.5 -> 10.666667 | O38: 16 | P38: =(Q38-G38)/(G38) -> 0.1 | Q38: 19.36 | R38: =Q38/7.6 -> 2.5473684 | S38: =O38-F38 -> 3.5 | T38: =N38/R38 -> 4.1873278 | U38: =T38-I38 -> 0.47047176 | W38: 0 | X38: 0 | Y38: 0 | Z38: =S38/F38 -> 0.28 | AA38: =11200/AC38 -> 0.67741935 | AB38: 1550 | AC38: =N38*AB38 -> 16533.333
A39: 16.00.04.00 | B39: BERG Helmet S | C39: 8715839078909 | E39: =F39/1.5 -> 12.666667 | F39: 19 | G39: 45 | H39: =G39/7.85 -> 5.7324841 | I39: =E39/H39 -> 2.2096296 | N39: =O39/1.5 -> 18.333333 | O39: 27.5 | P39: =(Q39-G39)/(G39) -> 0 | Q39: 45 | R39: =Q39/7.6 -> 5.9210526 | S39: =O39-F39 -> 8.5 | T39: =N39/R39 -> 3.0962963 | U39: =T39-I39 -> 0.88666667 | Z39: =S39/F39 -> 0.44736842 | AA39: =11200/AC39 -> 0.3941349 | AB39: 1550 | AC39: =N39*AB39 -> 28416.667
A40: 16.00.05.00 | B40: BERG Biky Protection Cushion | C40: 8715839078916 | E40: =F40/1.5 -> 3.3333333 | F40: 5 | G40: 7.4 | H40: =G40/7.85 -> 0.94267516 | I40: =E40/H40 -> 3.536036 | N40: =O40/1.5 -> 7.3333333 | O40: 11 | P40: =(Q40-G40)/(G40) -> 0.13513514 | Q40: 8.4 | R40: =Q40/7.6 -> 1.1052632 | S40: =O40-F40 -> 6 | T40: =N40/R40 -> 6.6349206 | U40: =T40-I40 -> 3.0988846 | Z40: =S40/F40 -> 1.2 | AA40: =11200/AC40 -> 0.98533724 | AB40: 1550 | AC40: =N40*AB40 -> 11366.667
A41: 16.00.06.00 | B41: BERG Biky Kickstand | C41: 8715839078923 | E41: =F41/1.5 -> 8.3333333 | F41: 12.5 | G41: 24.5 | H41: =G41/7.85 -> 3.1210191 | I41: =E41/H41 -> 2.670068 | N41: =O41/1.5 -> 10.666667 | O41: 16 | P41: =(Q41-G41)/(G41) -> 0 | Q41: 24.5 | R41: =Q41/7.6 -> 3.2236842 | S41: =O41-F41 -> 3.5 | T41: =N41/R41 -> 3.3088435 | U41: =T41-I41 -> 0.63877551 | Z41: =S41/F41 -> 0.28 | AA41: =11200/AC41 -> 0.67741935 | AB41: 1550 | AC41: =N41*AB41 -> 16533.333
A42: 16.00.07.00 | B42: BERG Biky Safety Flag | C42: 8715839078930 | E42: =F42/1.5 -> 8.3333333 | F42: 12.5 | G42: 20 | H42: =G42/7.85 -> 2.5477707 | I42: =E42/H42 -> 3.2708333 | N42: =O42/1.5 -> 10.666667 | O42: 16 | P42: =(Q42-G42)/(G42) -> 0.1 | Q42: 22 | R42: =Q42/7.6 -> 2.8947368 | S42: =O42-F42 -> 3.5 | T42: =N42/R42 -> 3.6848485 | U42: =T42-I42 -> 0.41401515 | Z42: =S42/F42 -> 0.28 | AA42: =11200/AC42 -> 0.67741935 | AB42: 1550 | AC42: =N42*AB42 -> 16533.333
A43: 25.17.00.02 | B43: BERG Dempy | C43: 8715839045413 | E43: =F43/1.5 -> 52.666667 | F43: 79 | G43: 175.78 | H43: =G43/7.85 -> 22.392357 | I43: =E43/H43 -> 2.351993 | J43: =VLOOKUP(A43,Mastersheet!$A:$AK,30,0) -> 59.33 | K43: =VLOOKUP(A43,Mastersheet!$A:$AK,32,0) -> 48.17 | L43: =VLOOKUP(A43,Mastersheet!$A:$AK,34,0) -> 40.25 | N43: =O43/1.5 -> 63.333333 | O43: 95 | P43: =(Q43-G43)/(G43) -> 0.036522926 | Q43: 182.2 | R43: =Q43/7.6 -> 23.973684 | S43: =O43-F43 -> 16 | T43: =N43/R43 -> 2.6417856 | U43: =T43-I43 -> 0.28979256 | W43: 0 | X43: 0 | Y43: 0 | Z43: =S43/F43 -> 0.20253165 | AA43: =11200/AC43 -> 0.11409168 | AB43: 1550 | AC43: =N43*AB43 -> 98166.667

Sheet $15.000 Container
O1: Aangepaste prijs | Q1: Geel gemarkeerd prijzen nog niet 100% final
A2: Pagina 1/1 | E2: 2021 | J2: 2017 | N2: 2022 | W2: 2018 | Z2: $15.000 container price
E5: Dealerprijs | F5: Verkoopadviesprijs | N5: inkoopprijs | O5: verkoopprijs | P5: Verschil in kostprijs % | Q5: Nieuwe kostprijs RMB | R5: Nieuwe kostprijs € | S5: Verschil in prijs | T5: Bruto TF | U5: Diff | Z5: Totaal verhoging MRSP | AA5: Upcharge vrachtkosten | AB5: QTY per container | AC5: Container waarde | AD5: Benodigde upcharge | AE5: Resultaat
A6: Art. nr. | B6: Omschrijving | C6: EAN-code | E6: excl. Btw | F6: incl. Btw | G6: Kostp. RMB | H6: Kostprijs | I6: Bruto TF | N6: excl. BTW | O6: incl. BTW
E7: EP | F7: Consument | J7: EP USD | K7: EP Ireland | L7: EP UK | N7: EP | O7: Consument | S7: Consument | W7: EP USD | X7: EP Ireland | Y7: EP UK
B8: BERG GO
A9: 24.52.00.00 | B9: BERG GO Twirl Turquoise | C9: 8715839085334 | E9: NVT | F9: NVT | G9: NVT | H9: NVT | I9: NVT | N9: =O9/1.5 -> 56.666667 | O9: 85 | P9: NVT | Q9: 168 | R9: =Q9/7.6 -> 22.105263 | S9: NVT | T9: =N9/R9 -> 2.5634921 | U9: NVT | W9: 0 | X9: 0 | Y9: 0 | Z9: NVT | AA9: NVT | AB9: 1032 | AC9: =N9*AB9 -> 58480 | AD9: NVT | AE9: NVT
A10: 24.52.01.00 | B10: BERG GO Twirl Multicolor | C10: 8715839085341 | E10: NVT | F10: NVT | G10: NVT | H10: NVT | I10: NVT | N10: =O10/1.5 -> 56.666667 | O10: 85 | P10: NVT | Q10: 168 | R10: =Q10/7.6 -> 22.105263 | S10: NVT | T10: =N10/R10 -> 2.5634921 | U10: NVT | W10: 0 | X10: 0 | Y10: 0 | Z10: NVT | AA10: NVT | AB10: 1032 | AC10: =N10*AB10 -> 58480 | AD10: NVT | AE10: NVT
B11: BERG GO²
A12: 24.50.00.00 | B12: BERG GO² Blue | C12: 8715839065404 | E12: =F12/1.5 -> 59.333333 | F12: 89 | G12: 194.56 | H12: =G12/7.85 -> 24.784713 | I12: =E12/H12 -> 2.3939487 | J12: 0 | K12: 0 | L12: 0 | N12: =O12/1.5 -> 70 | O12: 105 | P12: =(Q12-G12)/(G12) -> 0.030016447 | Q12: 200.4 | R12: =Q12/7.6 -> 26.368421 | S12: =O12-F12 -> 16 | T12: =N12/R12 -> 2.6546906 | U12: =T12-I12 -> 0.26074188 | W12: 0 | X12: 0 | Y12: 0 | Z12: =S12/F12 -> 0.17977528 | AA12: =13000/AC12 -> 0.15738499 | AB12: 1180 | AC12: =N12*AB12 -> 82600 | AD12: =AA12+P12 -> 0.18740144 | AE12: =AD12-Z12 -> 0.0076261544
A13: 24.50.01.00 | B13: BERG GO² Pink | C13: =VLOOKUP(A13,EAN!$A:$C,3,0) -> 8715839064322 | E13: =F13/1.5 -> 59.333333 | F13: 89 | G13: 194.56 | H13: =G13/7.85 -> 24.784713 | I13: =E13/H13 -> 2.3939487 | J13: 0 | K13: 0 | L13: 0 | N13: =O13/1.5 -> 70 | O13: 105 | P13: =(Q13-G13)/(G13) -> 0.030016447 | Q13: 200.4 | R13: =Q13/7.6 -> 26.368421 | S13: =O13-F13 -> 16 | T13: =N13/R13 -> 2.6546906 | U13: =T13-I13 -> 0.26074188 | W13: 0 | X13: 0 | Y13: 0 | Z13: =S13/F13 -> 0.17977528 | AA13: =13000/AC13 -> 0.15738499 | AB13: 1180 | AC13: =N13*AB13 -> 82600 | AD13: =AA13+P13 -> 0.18740144 | AE13: =AD13-Z13 -> 0.0076261544
A14: 24.50.02.00 | B14: BERG GO² Mint | C14: =VLOOKUP(A14,EAN!$A:$C,3,0) -> 8715839064339 | E14: =F14/1.5 -> 59.333333 | F14: 89 | G14: 194.56 | H14: =G14/7.85 -> 24.784713 | I14: =E14/H14 -> 2.3939487 | J14: 0 | K14: 0 | L14: 0 | N14: =O14/1.5 -> 70 | O14: 105 | P14: =(Q14-G14)/(G14) -> 0.030016447 | Q14: 200.4 | R14: =Q14/7.6 -> 26.368421 | S14: =O14-F14 -> 16 | T14: =N14/R14 -> 2.6546906 | U14: =T14-I14 -> 0.26074188 | W14: 0 | X14: 0 | Y14: 0 | Z14: =S14/F14 -> 0.17977528 | AA14: =13000/AC14 -> 0.15738499 | AB14: 1180 | AC14: =N14*AB14 -> 82600 | AD14: =AA14+P14 -> 0.18740144 | AE14: =AD14-Z14 -> 0.0076261544
A15: 24.50.03.00 | B15: BERG GO² SparX Red | C15: 8715839070453 | E15: =F15/1.5 -> 63.333333 | F15: 95 | G15: 201.19 | H15: =G15/7.85 -> 25.629299 | I15: =E15/H15 -> 2.4711301 | J15: 0 | K15: 0 | L15: 0 | N15: =O15/1.5 -> 76.666667 | O15: 115 | P15: =(Q15-G15)/(G15) -> 0.030021373 | Q15: 207.23 | R15: =Q15/7.6 -> 27.267105 | S15: =O15-F15 -> 20 | T15: =N15/R15 -> 2.8116907 | U15: =T15-I15 -> 0.3405606 | W15: 0 | X15: 0 | Y15: 0 | Z15: =S15/F15 -> 0.21052632 | AA15: =13000/AC15 -> 0.14369934 | AB15: 1180 | AC15: =N15*AB15 -> 90466.667 | AD15: =AA15+P15 -> 0.17372071 | AE15: =AD15-Z15 -> -0.036805606
A16: 24.50.04.00 | B16: BERG GO² SparX Yellow | C16: 8715839070460 | E16: =F16/1.5 -> 63.333333 | F16: 95 | G16: 199.6 | H16: =G16/7.85 -> 25.426752 | I16: =E16/H16 -> 2.490815 | J16: 0 | K16: 0 | L16: 0 | N16: =O16/1.5 -> 76.666667 | O16: 115 | P16: =(Q16-G16)/(G16) -> 0.03001002 | Q16: 205.59 | R16: =Q16/7.6 -> 27.051316 | S16: =O16-F16 -> 20 | T16: =N16/R16 -> 2.8341197 | U16: =T16-I16 -> 0.34330472 | W16: 0 | X16: 0 | Y16: 0 | Z16: =S16/F16 -> 0.21052632 | AA16: =13000/AC16 -> 0.14369934 | AB16: 1180 | AC16: =N16*AB16 -> 90466.667 | AD16: =AA16+P16 -> 0.17370936 | AE16: =AD16-Z16 -> -0.036816959
A17: 24.50.07.00 | B17: BERG GO² Retro Pink | C17: 8715839076028 | E17: =F17/1.5 -> 59.333333 | F17: 89 | G17: 199.07 | H17: =G17/7.85 -> 25.359236 | I17: =E17/H17 -> 2.339713 | N17: =O17/1.5 -> 72.666667 | O17: 109 | P17: =(Q17-G17)/(G17) -> 0.029989451 | Q17: 205.04 | R17: =Q17/7.6 -> 26.978947 | S17: =O17-F17 -> 20 | T17: =N17/R17 -> 2.6934582 | U17: =T17-I17 -> 0.35374519 | Z17: =S17/F17 -> 0.2247191 | AA17: =13000/AC17 -> 0.17335182 | AB17: 1032 | AC17: =N17*AB17 -> 74992 | AD17: =AA17+P17 -> 0.20334128 | AE17: =AD17-Z17 -> -0.021377826
A18: 24.50.08.00 | B18: BERG GO² Retro Green | C18: 8715839076035 | E18: =F18/1.5 -> 59.333333 | F18: 89 | G18: 199.07 | H18: =G18/7.85 -> 25.359236 | I18: =E18/H18 -> 2.339713 | N18: =O18/1.5 -> 72.666667 | O18: 109 | P18: =(Q18-G18)/(G18) -> 0.029989451 | Q18: 205.04 | R18: =Q18/7.6 -> 26.978947 | S18: =O18-F18 -> 20 | T18: =N18/R18 -> 2.6934582 | U18: =T18-I18 -> 0.35374519 | Z18: =S18/F18 -> 0.2247191 | AA18: =13000/AC18 -> 0.17335182 | AB18: 1032 | AC18: =N18*AB18 -> 74992 | AD18: =AA18+P18 -> 0.20334128 | AE18: =AD18-Z18 -> -0.021377826
B19: BERG Biky
A20: 24.75.10.00 | B20: BERG Biky Mini Green | C20: 8715839077735 | E20: =F20/1.5 -> 59.333333 | F20: 89 | G20: 187.9 | H20: =G20/7.85 -> 23.936306 | I20: =E20/H20 -> 2.4788008 | J20: =VLOOKUP(A20,Mastersheet!$A:$AK,30,0) -> #N/A | K20: =VLOOKUP(A20,Mastersheet!$A:$AK,32,0) -> #N/A | L20: =VLOOKUP(A20,Mastersheet!$A:$AK,34,0) -> #N/A | N20: =O20/1.5 -> 76.666667 | O20: 115 | P20: =(Q20-G20)/(G20) -> 0.11335817 | Q20: 209.2 | R20: =Q20/7.6 -> 27.526316 | S20: =O20-F20 -> 26 | T20: =N20/R20 -> 2.7852135 | U20: =T20-I20 -> 0.30641273 | W20: 0 | X20: 0 | Y20: 0 | Z20: =S20/F20 -> 0.29213483 | AA20: =13000/AC20 -> 0.10939691 | AB20: 1550 | AC20: =N20*AB20 -> 118833.33 | AD20: =AA20+P20 -> 0.22275508 | AE20: =AD20-Z20 -> -0.069379748
A21: 24.75.11.00 | B21: BERG Biky Mini Red | C21: 8715839077742 | E21: =F21/1.5 -> 59.333333 | F21: 89 | G21: 187.9 | H21: =G21/7.85 -> 23.936306 | I21: =E21/H21 -> 2.4788008 | J21: =VLOOKUP(A21,Mastersheet!$A:$AK,30,0) -> #N/A | K21: =VLOOKUP(A21,Mastersheet!$A:$AK,32,0) -> #N/A | L21: =VLOOKUP(A21,Mastersheet!$A:$AK,34,0) -> #N/A | N21: =O21/1.5 -> 76.666667 | O21: 115 | P21: =(Q21-G21)/(G21) -> 0.11335817 | Q21: 209.2 | R21: =Q21/7.6 -> 27.526316 | S21: =O21-F21 -> 26 | T21: =N21/R21 -> 2.7852135 | U21: =T21-I21 -> 0.30641273 | W21: 0 | X21: 0 | Y21: 0 | Z21: =S21/F21 -> 0.29213483 | AA21: =13000/AC21 -> 0.10939691 | AB21: 1550 | AC21: =N21*AB21 -> 118833.33 | AD21: =AA21+P21 -> 0.22275508 | AE21: =AD21-Z21 -> -0.069379748
A22: 24.75.30.00 | B22: BERG Biky City Green | C22: 8715839077759 | E22: =F22/1.5 -> 66 | F22: 99 | G22: 221.4 | H22: =G22/7.85 -> 28.203822 | I22: =E22/H22 -> 2.3401084 | J22: =VLOOKUP(A22,Mastersheet!$A:$AK,30,0) -> #N/A | K22: =VLOOKUP(A22,Mastersheet!$A:$AK,32,0) -> #N/A | L22: =VLOOKUP(A22,Mastersheet!$A:$AK,34,0) -> #N/A | N22: =O22/1.5 -> 83.333333 | O22: 125 | P22: =(Q22-G22)/(G22) -> 0.12059621 | Q22: 248.1 | R22: =Q22/7.6 -> 32.644737 | S22: =O22-F22 -> 26 | T22: =N22/R22 -> 2.5527341 | U22: =T22-I22 -> 0.21262571 | W22: 0 | X22: 0 | Y22: 0 | Z22: =S22/F22 -> 0.26262626 | AA22: =13000/AC22 -> 0.10064516 | AB22: 1550 | AC22: =N22*AB22 -> 129166.67 | AD22: =AA22+P22 -> 0.22124137 | AE22: =AD22-Z22 -> -0.041384895
A23: 24.75.31.00 | B23: BERG Biky City Red | C23: 8715839077766 | E23: =F23/1.5 -> 66 | F23: 99 | G23: 221.4 | H23: =G23/7.85 -> 28.203822 | I23: =E23/H23 -> 2.3401084 | J23: =VLOOKUP(A23,Mastersheet!$A:$AK,30,0) -> #N/A | K23: =VLOOKUP(A23,Mastersheet!$A:$AK,32,0) -> #N/A | L23: =VLOOKUP(A23,Mastersheet!$A:$AK,34,0) -> #N/A | N23: =O23/1.5 -> 83.333333 | O23: 125 | P23: =(Q23-G23)/(G23) -> 0.12059621 | Q23: 248.1 | R23: =Q23/7.6 -> 32.644737 | S23: =O23-F23 -> 26 | T23: =N23/R23 -> 2.5527341 | U23: =T23-I23 -> 0.21262571 | W23: 0 | X23: 0 | Y23: 0 | Z23: =S23/F23 -> 0.26262626 | AA23: =13000/AC23 -> 0.10064516 | AB23: 1550 | AC23: =N23*AB23 -> 129166.67 | AD23: =AA23+P23 -> 0.22124137 | AE23: =AD23-Z23 -> -0.041384895
A24: 24.75.50.00 | B24: BERG Biky Retro Green | C24: 8715839077773 | E24: =F24/1.5 -> 86 | F24: 129 | G24: 257.7 | H24: =G24/7.85 -> 32.828025 | I24: =E24/H24 -> 2.6197128 | J24: =VLOOKUP(A24,Mastersheet!$A:$AK,30,0) -> #N/A | K24: =VLOOKUP(A24,Mastersheet!$A:$AK,32,0) -> #N/A | L24: =VLOOKUP(A24,Mastersheet!$A:$AK,34,0) -> #N/A | N24: =O24/1.5 -> 103.33333 | O24: 155 | P24: =(Q24-G24)/(G24) -> 0.10865347 | Q24: 285.7 | R24: =Q24/7.6 -> 37.592105 | S24: =O24-F24 -> 26 | T24: =N24/R24 -> 2.7488041 | U24: =T24-I24 -> 0.12909126 | W24: 0 | X24: 0 | Y24: 0 | Z24: =S24/F24 -> 0.20155039 | AA24: =13000/AC24 -> 0.081165453 | AB24: 1550 | AC24: =N24*AB24 -> 160166.67 | AD24: =AA24+P24 -> 0.18981893 | AE24: =AD24-Z24 -> -0.011731462
A25: 24.75.51.00 | B25: BERG Biky Retro Pink | C25: 8715839077780 | E25: =F25/1.5 -> 86 | F25: 129 | G25: 257.7 | H25: =G25/7.85 -> 32.828025 | I25: =E25/H25 -> 2.6197128 | J25: =VLOOKUP(A25,Mastersheet!$A:$AK,30,0) -> #N/A | K25: =VLOOKUP(A25,Mastersheet!$A:$AK,32,0) -> #N/A | L25: =VLOOKUP(A25,Mastersheet!$A:$AK,34,0) -> #N/A | N25: =O25/1.5 -> 103.33333 | O25: 155 | P25: =(Q25-G25)/(G25) -> 0.10865347 | Q25: 285.7 | R25: =Q25/7.6 -> 37.592105 | S25: =O25-F25 -> 26 | T25: =N25/R25 -> 2.7488041 | U25: =T25-I25 -> 0.12909126 | W25: 0 | X25: 0 | Y25: 0 | Z25: =S25/F25 -> 0.20155039 | AA25: =13000/AC25 -> 0.081165453 | AB25: 1550 | AC25: =N25*AB25 -> 160166.67 | AD25: =AA25+P25 -> 0.18981893 | AE25: =AD25-Z25 -> -0.011731462
A26: 24.75.70.00 | B26: BERG Biky Cross Green | C26: 8715839077797 | E26: =F26/1.5 -> 79.333333 | F26: 119 | G26: 250.8 | H26: =G26/7.85 -> 31.949045 | I26: =E26/H26 -> 2.4831207 | N26: =O26/1.5 -> 96.666667 | O26: 145 | P26: =(Q26-G26)/(G26) -> 0.14354067 | Q26: 286.8 | R26: =Q26/7.6 -> 37.736842 | S26: =O26-F26 -> 26 | T26: =N26/R26 -> 2.5615993 | U26: =T26-I26 -> 0.078478576 | Z26: =S26/F26 -> 0.21848739 | AA26: =13000/AC26 -> 0.08676307 | AB26: 1550 | AC26: =N26*AB26 -> 149833.33 | AD26: =AA26+P26 -> 0.23030374 | AE26: =AD26-Z26 -> 0.011816345
A27: 24.75.71.00 | B27: BERG Biky Cross Red | C27: 8715839077803 | E27: =F27/1.5 -> 79.333333 | F27: 119 | G27: 250.8 | H27: =G27/7.85 -> 31.949045 | I27: =E27/H27 -> 2.4831207 | N27: =O27/1.5 -> 96.666667 | O27: 145 | P27: =(Q27-G27)/(G27) -> 0.14354067 | Q27: 286.8 | R27: =Q27/7.6 -> 37.736842 | S27: =O27-F27 -> 26 | T27: =N27/R27 -> 2.5615993 | U27: =T27-I27 -> 0.078478576 | Z27: =S27/F27 -> 0.21848739 | AA27: =13000/AC27 -> 0.08676307 | AB27: 1550 | AC27: =N27*AB27 -> 149833.33 | AD27: =AA27+P27 -> 0.23030374 | AE27: =AD27-Z27 -> 0.011816345
A28: 24.75.72.00 | B28: BERG Biky Cross Grey | C28: 8715839077810 | E28: =F28/1.5 -> 79.333333 | F28: 119 | G28: 250.8 | H28: =G28/7.85 -> 31.949045 | I28: =E28/H28 -> 2.4831207 | J28: =VLOOKUP(A28,Mastersheet!$A:$AK,30,0) -> #N/A | K28: =VLOOKUP(A28,Mastersheet!$A:$AK,32,0) -> #N/A | L28: =VLOOKUP(A28,Mastersheet!$A:$AK,34,0) -> #N/A | N28: =O28/1.5 -> 96.666667 | O28: 145 | P28: =(Q28-G28)/(G28) -> 0.14354067 | Q28: 286.8 | R28: =Q28/7.6 -> 37.736842 | S28: =O28-F28 -> 26 | T28: =N28/R28 -> 2.5615993 | U28: =T28-I28 -> 0.078478576 | W28: 0 | X28: 0 | Y28: 0 | Z28: =S28/F28 -> 0.21848739 | AA28: =13000/AC28 -> 0.08676307 | AB28: 1550 | AC28: =N28*AB28 -> 149833.33 | AD28: =AA28+P28 -> 0.23030374 | AE28: =AD28-Z28 -> 0.011816345
A29: 24.74.30.00 | B29: BERG Biky City Blue Handbrake | C29: 8715839085372 | E29: NVT | F29: NVT | G29: NVT | H29: NVT | I29: NVT | N29: =O29/1.5 -> 90 | O29: 135 | P29: NVT | Q29: =Q23+30 -> 278.1 | R29: =Q29/7.6 -> 36.592105 | S29: NVT | T29: =N29/R29 -> 2.4595469 | U29: NVT | Z29: NVT | AA29: NVT | AB29: 1550 | AC29: =N29*AB29 -> 139500 | AD29: NVT | AE29: NVT
A30: 24.74.70.00 | B30: BERG Biky Cross Blue Handbrake | C30: 8715839085358 | E30: NVT | F30: NVT | G30: NVT | H30: NVT | I30: NVT | N30: =O30/1.5 -> 103.33333 | O30: 155 | P30: NVT | Q30: =Q28+25 -> 311.8 | R30: =Q30/7.6 -> 41.026316 | S30: NVT | T30: =N30/R30 -> 2.5187086 | U30: NVT | Z30: NVT | AA30: NVT | AB30: 1550 | AC30: =N30*AB30 -> 160166.67 | AD30: NVT | AE30: NVT
A31: 24.74.71.00 | B31: BERG Biky Cross Grey Handbrake | C31: 8715839085365 | E31: NVT | F31: NVT | G31: NVT | H31: NVT | I31: NVT | N31: =O31/1.5 -> 103.33333 | O31: 155 | P31: NVT | Q31: =Q28+30 -> 316.8 | R31: =Q31/7.6 -> 41.684211 | S31: NVT | T31: =N31/R31 -> 2.4789562 | U31: NVT | Z31: NVT | AA31: NVT | AB31: 1550 | AC31: =N31*AB31 -> 160166.67 | AD31: NVT | AE31: NVT
B32: BERG BeachWagon
A33: 18.07.10.01 | B33: BERG Beach Wagon L | C33: 8715839045222 | E33: =F33/1.5 -> 159.33333 | F33: 239 | H33: =35.74+37 -> 72.74 | I33: =E33/H33 -> 2.19045 | J33: =VLOOKUP(A33,Mastersheet!$A:$AK,30,0) -> 183.2 | K33: =VLOOKUP(A33,Mastersheet!$A:$AK,32,0) -> 151.83 | L33: =VLOOKUP(A33,Mastersheet!$A:$AK,34,0) -> 121.92 | N33: =O33/1.5 -> 190 | O33: 285 | P33: =(R33-H33)/(H33) -> 0.11850426 | R33: =40.36+41 -> 81.36 | S33: =O33-F33 -> 46 | T33: =N33/R33 -> 2.3352999 | U33: =T33-I33 -> 0.1448499 | W33: 0 | X33: 0 | Y33: 0 | Z33: =S33/F33 -> 0.19246862 | AA33: =13000/AC33 -> 0.044142615 | AB33: 1550 | AC33: =N33*AB33 -> 294500
A34: 18.07.17.01 | B34: BERG Beach Wagon XL | C34: 8715839045208 | E34: =F34/1.5 -> 179.33333 | F34: 269 | H34: =35.74+47 -> 82.74 | I34: =E34/H34 -> 2.1674321 | J34: =VLOOKUP(A34,Mastersheet!$A:$AK,30,0) -> 207.2 | K34: =VLOOKUP(A34,Mastersheet!$A:$AK,32,0) -> 170.12 | L34: =VLOOKUP(A34,Mastersheet!$A:$AK,34,0) -> 139.42 | N34: =O34/1.5 -> 216.66667 | O34: 325 | P34: =(R34-H34)/(H34) -> 0.11626783 | R34: =40.36+52 -> 92.36 | S34: =O34-F34 -> 56 | T34: =N34/R34 -> 2.3458929 | U34: =T34-I34 -> 0.17846077 | W34: 0 | X34: 0 | Y34: 0 | Z34: =S34/F34 -> 0.20817844 | AA34: =13000/AC34 -> 0.038709677 | AB34: 1550 | AC34: =N34*AB34 -> 335833.33
B35: BERG Accessoires
A36: 16.00.01.00 | B36: BERG Carrying Strap | C36: 8715839065749 | E36: =F36/1.5 -> 6.6666667 | F36: 10 | G36: 18 | H36: =G36/7.85 -> 2.2929936 | I36: =E36/H36 -> 2.9074074 | J36: =VLOOKUP(A36,Mastersheet!$A:$AK,30,0) -> #N/A | K36: =VLOOKUP(A36,Mastersheet!$A:$AK,32,0) -> #N/A | L36: =VLOOKUP(A36,Mastersheet!$A:$AK,34,0) -> #N/A | N36: =O36/1.5 -> 9.3333333 | O36: 14 | P36: =(Q36-G36)/(G36) -> 0 | Q36: 18 | R36: =Q36/7.6 -> 2.3684211 | S36: =O36-F36 -> 4 | T36: =N36/R36 -> 3.9407407 | U36: =T36-I36 -> 1.0333333 | W36: 0 | X36: 0 | Y36: 0 | Z36: =S36/F36 -> 0.4 | AA36: =13000/AC36 -> 0.89861751 | AB36: 1550 | AC36: =N36*AB36 -> 14466.667
A37: 16.50.00.00 | B37: BERG Push Handle XS | C37: 8715839065725 | E37: =F37/1.5 -> 16.666667 | F37: 25 | G37: 50 | H37: =G37/7.85 -> 6.3694268 | I37: =E37/H37 -> 2.6166667 | J37: =VLOOKUP(A37,Mastersheet!$A:$AK,30,0) -> #N/A | K37: =VLOOKUP(A37,Mastersheet!$A:$AK,32,0) -> #N/A | L37: =VLOOKUP(A37,Mastersheet!$A:$AK,34,0) -> #N/A | N37: =O37/1.5 -> 19.333333 | O37: 29 | P37: =(Q37-G37)/(G37) -> 0.1 | Q37: 55 | R37: =Q37/7.6 -> 7.2368421 | S37: =O37-F37 -> 4 | T37: =N37/R37 -> 2.6715152 | U37: =T37-I37 -> 0.054848485 | W37: 0 | X37: 0 | Y37: 0 | Z37: =S37/F37 -> 0.16 | AA37: =13000/AC37 -> 0.43381535 | AB37: 1550 | AC37: =N37*AB37 -> 29966.667
A38: 16.00.00.00 | B38: BERG Safety Flag XS | C38: 8715839065732 | E38: =F38/1.5 -> 8.3333333 | F38: 12.5 | G38: 17.6 | H38: =G38/7.85 -> 2.2420382 | I38: =E38/H38 -> 3.7168561 | J38: =VLOOKUP(A38,Mastersheet!$A:$AK,30,0) -> #N/A | K38: =VLOOKUP(A38,Mastersheet!$A:$AK,32,0) -> #N/A | L38: =VLOOKUP(A38,Mastersheet!$A:$AK,34,0) -> #N/A | N38: =O38/1.5 -> 10.666667 | O38: 16 | P38: =(Q38-G38)/(G38) -> 0.1 | Q38: 19.36 | R38: =Q38/7.6 -> 2.5473684 | S38: =O38-F38 -> 3.5 | T38: =N38/R38 -> 4.1873278 | U38: =T38-I38 -> 0.47047176 | W38: 0 | X38: 0 | Y38: 0 | Z38: =S38/F38 -> 0.28 | AA38: =13000/AC38 -> 0.78629032 | AB38: 1550 | AC38: =N38*AB38 -> 16533.333
A39: 16.00.04.00 | B39: BERG Helmet S | C39: 8715839078909 | E39: =F39/1.5 -> 12.666667 | F39: 19 | G39: 45 | H39: =G39/7.85 -> 5.7324841 | I39: =E39/H39 -> 2.2096296 | N39: =O39/1.5 -> 18.333333 | O39: 27.5 | P39: =(Q39-G39)/(G39) -> 0 | Q39: 45 | R39: =Q39/7.6 -> 5.9210526 | S39: =O39-F39 -> 8.5 | T39: =N39/R39 -> 3.0962963 | U39: =T39-I39 -> 0.88666667 | Z39: =S39/F39 -> 0.44736842 | AA39: =13000/AC39 -> 0.45747801 | AB39: 1550 | AC39: =N39*AB39 -> 28416.667
A40: 16.00.05.00 | B40: BERG Biky Protection Cushion | C40: 8715839078916 | E40: =F40/1.5 -> 3.3333333 | F40: 5 | G40: 7.4 | H40: =G40/7.85 -> 0.94267516 | I40: =E40/H40 -> 3.536036 | N40: =O40/1.5 -> 7.3333333 | O40: 11 | P40: =(Q40-G40)/(G40) -> 0.13513514 | Q40: 8.4 | R40: =Q40/7.6 -> 1.1052632 | S40: =O40-F40 -> 6 | T40: =N40/R40 -> 6.6349206 | U40: =T40-I40 -> 3.0988846 | Z40: =S40/F40 -> 1.2 | AA40: =13000/AC40 -> 1.143695 | AB40: 1550 | AC40: =N40*AB40 -> 11366.667
A41: 16.00.06.00 | B41: BERG Biky Kickstand | C41: 8715839078923 | E41: =F41/1.5 -> 8.3333333 | F41: 12.5 | G41: 24.5 | H41: =G41/7.85 -> 3.1210191 | I41: =E41/H41 -> 2.670068 | N41: =O41/1.5 -> 10.666667 | O41: 16 | P41: =(Q41-G41)/(G41) -> 0 | Q41: 24.5 | R41: =Q41/7.6 -> 3.2236842 | S41: =O41-F41 -> 3.5 | T41: =N41/R41 -> 3.3088435 | U41: =T41-I41 -> 0.63877551 | Z41: =S41/F41 -> 0.28 | AA41: =13000/AC41 -> 0.78629032 | AB41: 1550 | AC41: =N41*AB41 -> 16533.333
A42: 16.00.07.00 | B42: BERG Biky Safety Flag | C42: 8715839078930 | E42: =F42/1.5 -> 8.3333333 | F42: 12.5 | G42: 20 | H42: =G42/7.85 -> 2.5477707 | I42: =E42/H42 -> 3.2708333 | N42: =O42/1.5 -> 10.666667 | O42: 16 | P42: =(Q42-G42)/(G42) -> 0.1 | Q42: 22 | R42: =Q42/7.6 -> 2.8947368 | S42: =O42-F42 -> 3.5 | T42: =N42/R42 -> 3.6848485 | U42: =T42-I42 -> 0.41401515 | Z42: =S42/F42 -> 0.28 | AA42: =13000/AC42 -> 0.78629032 | AB42: 1550 | AC42: =N42*AB42 -> 16533.333
A43: 25.17.00.02 | B43: BERG Dempy | C43: 8715839045413 | E43: =F43/1.5 -> 52.666667 | F43: 79 | G43: 175.78 | H43: =G43/7.85 -> 22.392357 | I43: =E43/H43 -> 2.351993 | J43: =VLOOKUP(A43,Mastersheet!$A:$AK,30,0) -> 59.33 | K43: =VLOOKUP(A43,Mastersheet!$A:$AK,32,0) -> 48.17 | L43: =VLOOKUP(A43,Mastersheet!$A:$AK,34,0) -> 40.25 | N43: =O43/1.5 -> 63.333333 | O43: 95 | P43: =(Q43-G43)/(G43) -> 0.036522926 | Q43: 182.2 | R43: =Q43/7.6 -> 23.973684 | S43: =O43-F43 -> 16 | T43: =N43/R43 -> 2.6417856 | U43: =T43-I43 -> 0.28979256 | W43: 0 | X43: 0 | Y43: 0 | Z43: =S43/F43 -> 0.20253165 | AA43: =13000/AC43 -> 0.13242784 | AB43: 1550 | AC43: =N43*AB43 -> 98166.667

Sheet Nieuw AX
A1: Item number | B1: Product name | C1: Vendor | D1: Freight allocation group | E1: Visible in webshop | F1: Commission item group | G1: Alternative item number | H1: When to use | I1: Kit | J1: Item rebate group | K1: Coverage group | L1: Country/region | M1: Pallet quantity | N1: E-commerce | O1: Volume | P1: Net weight | Q1: Tare weight | R1: Gross width | S1: Gross depth | T1: Gross height | U1: Commodity | V1: Danger class | W1: Search name | X1: Total weight | Y1: Extended fieldcheck RT-WMS | Z1: Product type | AA1: Product subtype | AB1: Product dimension group | AC1: Production type
A2: 35.09.01.02 | B2: BERG Favorit 270 (9 ft) + Safety Net Comfort | D2: UNDER_CON | E2: No | H2: Never | I2: Yes | J2: IMPOSSIBLE | K2: TRAMPO | M2: 1 | N2: No | O2: 1 | P2: 0.01 | Q2: 0 | R2: 1 | S2: 1 | T2: 1 | W2: 35090102 | Y2: Enabled | Z2: Item | AA2: Product | AC2: BOM
A3: 35.09.05.01 | B3: BERG InGround Favorit 270 (9 ft) + Safety Net Comfort | D3: UNDER_CON | E3: No | H3: Never | I3: Yes | J3: IMPOSSIBLE | K3: TRAMPO | M3: 1 | N3: No | O3: 1 | P3: 0.01 | Q3: 0 | R3: 1 | S3: 1 | T3: 1 | W3: 35090501 | Y3: Enabled | Z3: Item | AA3: Product | AC3: BOM
A4: 35.11.01.02 | B4: BERG Favorit 330 (11 ft) + Safety Net Comfort | D4: UNDER_CON | E4: No | H4: Never | I4: Yes | J4: IMPOSSIBLE | K4: TRAMPO | M4: 1 | N4: No | O4: 1 | P4: 0.01 | Q4: 0 | R4: 1 | S4: 1 | T4: 1 | W4: 35110102 | Y4: Enabled | Z4: Item | AA4: Product | AC4: BOM
A5: 35.11.04.01 | B5: BERG InGround Favorit 330 (11 ft) + Safety Net Comfort | D5: UNDER_CON | E5: No | H5: Never | I5: Yes | J5: IMPOSSIBLE | K5: TRAMPO | M5: 1 | N5: No | O5: 1 | P5: 0.01 | Q5: 0 | R5: 1 | S5: 1 | T5: 1 | W5: 35110401 | Y5: Enabled | Z5: Item | AA5: Product | AC5: BOM
A6: 35.11.92.00 | B6: BERG InGround Favorit Grey 330 + Safety Net Comfort | D6: UNDER_CON | E6: No | H6: Never | I6: Yes | J6: PENDING | K6: TRAMPO | M6: 1 | N6: No | O6: 1 | P6: 0.01 | Q6: 0 | R6: 1 | S6: 1 | T6: 1 | W6: 35119200 | Y6: Enabled | Z6: Item | AA6: Product | AC6: BOM
A7: 35.11.94.00 | B7: BERG Favorit Grey 330 + Safety Net Comfort | D7: UNDER_CON | E7: No | H7: Never | I7: Yes | J7: PENDING | K7: TRAMPO | M7: 1 | N7: No | O7: 1 | P7: 0.01 | Q7: 0 | R7: 1 | S7: 1 | T7: 1 | W7: 35119400 | Y7: Enabled | Z7: Item | AA7: Product | AC7: BOM
A8: 35.12.01.02 | B8: BERG Favorit 380 (12,5 ft) + Safety Net Comfort | D8: UNDER_CON | E8: No | H8: Never | I8: Yes | J8: IMPOSSIBLE | K8: TRAMPO | M8: 1 | N8: No | O8: 1 | P8: 0.01 | Q8: 0 | R8: 1 | S8: 1 | T8: 1 | W8: 35120102 | Y8: Enabled | Z8: Item | AA8: Product | AC8: BOM
A9: 35.12.04.01 | B9: BERG InGround Favorit 380 (12,5 ft) + Safety Net Comfort | D9: UNDER_CON | E9: No | H9: Never | I9: Yes | J9: IMPOSSIBLE | K9: TRAMPO | M9: 1 | N9: No | O9: 1 | P9: 0.01 | Q9: 0 | R9: 1 | S9: 1 | T9: 1 | W9: 35120401 | Y9: Enabled | Z9: Item | AA9: Product | AC9: BOM
A10: 35.12.92.00 | B10: BERG InGround Favorit Grey 380 + Safety Net Comfort | D10: UNDER_CON | E10: No | H10: Never | I10: Yes | J10: PENDING | K10: TRAMPO | M10: 1 | N10: No | O10: 1 | P10: 0.01 | Q10: 0 | R10: 1 | S10: 1 | T10: 1 | W10: 35129200 | Y10: Enabled | Z10: Item | AA10: Product | AC10: BOM
A11: 35.12.94.00 | B11: BERG Favorit Grey 380 + Safety Net Comfort | D11: UNDER_CON | E11: No | H11: Never | I11: Yes | J11: PENDING | K11: TRAMPO | M11: 1 | N11: No | O11: 1 | P11: 0.01 | Q11: 0 | R11: 1 | S11: 1 | T11: 1 | W11: 35129400 | Y11: Enabled | Z11: Item | AA11: Product | AC11: BOM
A12: 35.14.02.02 | B12: BERG Favorit 430 (14 ft) + Safety Net Comfort | D12: UNDER_CON | E12: No | H12: Never | I12: Yes | J12: IMPOSSIBLE | K12: TRAMPO | M12: 1 | N12: No | O12: 1 | P12: 0.01 | Q12: 0 | R12: 1 | S12: 1 | T12: 1 | W12: 35140202 | Y12: Enabled | Z12: Item | AA12: Product | AC12: BOM
A13: 35.14.03.02 | B13: BERG Favorit 430 (14 ft) Tattoo + Safety Net Comfort | D13: UNDER_CON | E13: No | H13: Never | I13: Yes | J13: IMPOSSIBLE | K13: TRAMPO | M13: 1 | N13: No | O13: 1 | P13: 0.01 | Q13: 0 | R13: 1 | S13: 1 | T13: 1 | W13: 35140302 | Y13: Enabled | Z13: Item | AA13: Product | AC13: BOM
... A16: 35.14.94.00 | B16: BERG Favorit Grey 430 + Safety Net Comfort | D16: UNDER_CON | E16: No | H16: Never | I16: Yes | J16: PENDING | K16: TRAMPO | M16: 1 | N16: No | O16: 1 | P16: 0.01 | Q16: 0 | R16: 1 | S16: 1 | T16: 1 | W16: 35149400 | Y16: Enabled | Z16: Item | AA16: Product | AC16: BOM
A17: 35.39.01.02 | B17: BERG Champion 270 + Safety Net Deluxe | D17: UNDER_CON | E17: No | H17: Never | I17: Yes | J17: IMPOSSIBLE | K17: TRAMPO | L17: CHN | M17: 6 | N17: No | O17: 1 | P17: 76.3 | Q17: 0 | R17: 1 | S17: 1 | T17: 1 | U17: 95069190 | W17: 35390102 | Y17: Enabled | Z17: Item | AA17: Product | AC17: BOM
A18: 35.39.04.01 | B18: BERG Champion 270 + Safety Net Comfort | D18: UNDER_CON | E18: No | H18: Never | I18: Yes | J18: IMPOSSIBLE | K18: TRAMPO | L18: CHN | M18: 6 | N18: No | O18: 1 | P18: 69.3 | Q18: 0 | R18: 1 | S18: 1 | T18: 1 | U18: 95069190 | W18: 35390401 | Y18: Enabled | Z18: Item | AA18: Product | AC18: BOM
A19: 35.39.05.01 | B19: BERG InGround Champion 270 + Safety Net Deluxe | D19: UNDER_CON | E19: No | H19: Never | I19: Yes | J19: IMPOSSIBLE | K19: TRAMPO | L19: CHN | M19: 6 | N19: No | O19: 1 | P19: 73.6 | Q19: 0 | R19: 1 | S19: 1 | T19: 1 | U19: 95069190 | W19: 35390501 | Y19: Enabled | Z19: Item | AA19: Product | AC19: BOM
A20: 35.39.06.01 | B20: BERG InGround Champion 270 + Safety Net Comfort | D20: UNDER_CON | E20: No | H20: Never | I20: Yes | J20: IMPOSSIBLE | K20: TRAMPO | L20: CHN | M20: 6 | N20: No | O20: 1 | P20: 66.7 | Q20: 0 | R20: 1 | S20: 1 | T20: 1 | U20: 95069190 | W20: 35390601 | Y20: Enabled | Z20: Item | AA20: Product | AC20: BOM
A21: 35.41.01.02 | B21: BERG Champion 330 + Safety Net Deluxe | D21: UNDER_CON | E21: No | H21: Never | I21: Yes | J21: IMPOSSIBLE | K21: TRAMPO | L21: CHN | M21: 6 | N21: No | O21: 1 | P21: 113.7 | Q21: 0 | R21: 1 | S21: 1 | T21: 1 | U21: 95069190 | W21: 35410102 | Y21: Enabled | Z21: Item | AA21: Product | AC21: BOM
A22: 35.41.04.01 | B22: BERG Champion 330 + Safety Net Comfort | D22: UNDER_CON | E22: No | H22: Never | I22: Yes | J22: IMPOSSIBLE | K22: TRAMPO | L22: CHN | M22: 6 | N22: No | O22: 1 | P22: 101.1 | Q22: 0 | R22: 1 | S22: 1 | T22: 1 | U22: 95069190 | W22: 35410401 | Y22: Enabled | Z22: Item | AA22: Product | AC22: BOM
A23: 35.41.05.01 | B23: BERG InGround Champion 330 + Safety Net Deluxe | D23: UNDER_CON | E23: No | H23: Never | I23: Yes | J23: IMPOSSIBLE | K23: TRAMPO | L23: CHN | M23: 6 | N23: No | O23: 1 | P23: 98.8 | Q23: 0 | R23: 1 | S23: 1 | T23: 1 | U23: 95069190 | W23: 35410501 | Y23: Enabled | Z23: Item | AA23: Product | AC23: BOM
A24: 35.41.06.01 | B24: BERG InGround Champion 330 + Safety Net Comfort | D24: UNDER_CON | E24: No | H24: Never | I24: Yes | J24: IMPOSSIBLE | K24: TRAMPO | L24: CHN | M24: 6 | N24: No | O24: 1 | P24: 86.5 | Q24: 0 | R24: 1 | S24: 1 | T24: 1 | U24: 95069190 | W24: 35410601 | Y24: Enabled | Z24: Item | AA24: Product | AC24: BOM
A25: 35.41.80.00 | B25: BERG Champion USA 11ft + BERG Safety Net Deluxe USA | D25: UNDER_CON | E25: No | H25: Never | I25: Yes | J25: IMPOSSIBLE | K25: TRAMPO | M25: 1 | N25: No | O25: 1 | P25: 0.01 | Q25: 0 | R25: 1 | S25: 1 | T25: 1 | W25: 35418000 | Y25: Enabled | Z25: Item | AA25: Product | AC25: BOM
A26: 35.41.81.00 | B26: BERG InGround Champion USA 11ft + BERG Safety Net Deluxe USA | D26: UNDER_CON | E26: No | H26: Never | I26: Yes | J26: IMPOSSIBLE | K26: STD | M26: 1 | N26: No | O26: 1 | P26: 0.01 | Q26: 0 | R26: 1 | S26: 1 | T26: 1 | W26: 35418100 | Y26: Enabled | Z26: Item | AA26: Product | AC26: BOM
A27: 35.41.91.01 | B27: BERG InGround Champion Grey 330 + Safety Net Deluxe | D27: UNDER_CON | E27: No | H27: Never | I27: Yes | J27: IMPOSSIBLE | K27: TRAMPO | L27: CHN | M27: 6 | N27: No | O27: 1 | P27: 98.8 | Q27: 0 | R27: 1 | S27: 1 | T27: 1 | U27: 95069190 | W27: 35419101 | Y27: Enabled | Z27: Item | AA27: Product | AC27: BOM
A28: 35.41.92.01 | B28: BERG InGround Champion Grey 330 + Safety Net Comfort | D28: UNDER_CON | E28: No | H28: Never | I28: Yes | J28: IMPOSSIBLE | K28: TRAMPO | L28: CHN | M28: 6 | N28: No | O28: 1 | P28: 86.5 | Q28: 0 | R28: 1 | S28: 1 | T28: 1 | U28: 95069190 | W28: 35419201 | Y28: Enabled | Z28: Item | AA28: Product | AC28: BOM
A29: 35.41.93.01 | B29: BERG Champion Grey 330 + Safety Net Deluxe | D29: UNDER_CON | E29: No | H29: Never | I29: Yes | J29: IMPOSSIBLE | K29: TRAMPO | L29: CHN | M29: 6 | N29: No | O29: 1 | P29: 113.7 | Q29: 0 | R29: 1 | S29: 1 | T29: 1 | U29: 95069190 | W29: 35419301 | Y29: Enabled | Z29: Item | AA29: Product | AC29: BOM
A30: 35.41.94.01 | B30: BERG Champion Grey 330 + Safety Net Comfort | D30: UNDER_CON | E30: No | H30: Never | I30: Yes | J30: IMPOSSIBLE | K30: TRAMPO | L30: CHN | M30: 6 | N30: No | O30: 1 | P30: 101.1 | Q30: 0 | R30: 1 | S30: 1 | T30: 1 | U30: 95069190 | W30: 35419401 | Y30: Enabled | Z30: Item | AA30: Product | AC30: BOM
A31: 35.42.01.02 | B31: BERG Champion 380 + Safety Net Deluxe | D31: UNDER_CON | E31: No | H31: Never | I31: Yes | J31: IMPOSSIBLE | K31: TRAMPO | L31: CHN | M31: 6 | N31: No | O31: 1 | P31: 113.7 | Q31: 0 | R31: 1 | S31: 1 | T31: 1 | U31: 95069190 | W31: 35420102 | Y31: Enabled | Z31: Item | AA31: Product | AC31: BOM
A32: 35.42.04.01 | B32: BERG Champion 380 + Safety Net Comfort | D32: UNDER_CON | E32: No | H32: Never | I32: Yes | J32: IMPOSSIBLE | K32: TRAMPO | L32: CHN | M32: 6 | N32: No | O32: 1 | P32: 111.9 | Q32: 0 | R32: 1 | S32: 1 | T32: 1 | U32: 95069190 | W32: 35420401 | Y32: Enabled | Z32: Item | AA32: Product | AC32: BOM
A33: 35.42.05.01 | B33: BERG InGround Champion 380 + Safety Net Deluxe | D33: UNDER_CON | E33: No | H33: Never | I33: Yes | J33: IMPOSSIBLE | K33: TRAMPO | L33: CHN | M33: 6 | N33: No | O33: 1 | P33: 108.2 | Q33: 0 | R33: 1 | S33: 1 | T33: 1 | U33: 95069190 | W33: 35420501 | Y33: Enabled | Z33: Item | AA33: Product | AC33: BOM
A34: 35.42.06.01 | B34: BERG InGround Champion 380 + Safety Net Comfort | D34: UNDER_CON | E34: No | H34: Never | I34: Yes | J34: IMPOSSIBLE | K34: TRAMPO | L34: CHN | M34: 6 | N34: No | O34: 1 | P34: 95.1 | Q34: 0 | R34: 1 | S34: 1 | T34: 1 | U34: 95069190 | W34: 35420601 | Y34: Enabled | Z34: Item | AA34: Product | AC34: BOM
A35: 35.42.91.01 | B35: BERG InGround Champion Grey 380 + Safety Net Deluxe | D35: UNDER_CON | E35: No | H35: Never | I35: Yes | J35: IMPOSSIBLE | K35: TRAMPO | L35: CHN | M35: 6 | N35: No | O35: 1 | P35: 108.2 | Q35: 0 | R35: 1 | S35: 1 | T35: 1 | U35: 95069190 | W35: 35429101 | Y35: Enabled | Z35: Item | AA35: Product | AC35: BOM
A36: 35.42.92.01 | B36: BERG InGround Champion Grey 380 + Safety Net Comfort | D36: UNDER_CON | E36: No | H36: Never | I36: Yes | J36: IMPOSSIBLE | K36: TRAMPO | L36: CHN | M36: 6 | N36: No | O36: 1 | P36: 95.1 | Q36: 0 | R36: 1 | S36: 1 | T36: 1 | U36: 95069190 | W36: 35429201 | Y36: Enabled | Z36: Item | AA36: Product | AC36: BOM
A37: 35.42.93.01 | B37: BERG Champion Grey 380 + Safety Net Deluxe | D37: UNDER_CON | E37: No | H37: Never | I37: Yes | J37: IMPOSSIBLE | K37: TRAMPO | L37: CHN | M37: 6 | N37: No | O37: 1 | P37: 113.7 | Q37: 0 | R37: 1 | S37: 1 | T37: 1 | U37: 95069190 | W37: 35429301 | Y37: Enabled | Z37: Item | AA37: Product | AC37: BOM
A38: 35.42.94.01 | B38: BERG Champion Grey 380 + Safety Net Comfort | D38: UNDER_CON | E38: No | H38: Never | I38: Yes | J38: IMPOSSIBLE | K38: TRAMPO | L38: CHN | M38: 6 | N38: No | O38: 1 | P38: 111.9 | Q38: 0 | R38: 1 | S38: 1 | T38: 1 | U38: 95069190 | W38: 35429401 | Y38: Enabled | Z38: Item | AA38: Product | AC38: BOM
... A44: 35.44.09.01 | B44: BERG InGround Champion 430 + Safety Net Comfort | D44: UNDER_CON | E44: No | H44: Never | I44: Yes | J44: IMPOSSIBLE | K44: TRAMPO | L44: CHN | M44: 6 | N44: No | O44: 1 | P44: 102.5 | Q44: 0 | R44: 1 | S44: 1 | T44: 1 | U44: 95069190 | W44: 35440901 | Y44: Enabled | Z44: Item | AA44: Product | AC44: BOM
A45: 35.44.80.00 | B45: BERG Champion USA 14ft + BERG Safety Net Deluxe USA | D45: UNDER_CON | E45: No | H45: Never | I45: Yes | J45: IMPOSSIBLE | K45: TRAMPO | M45: 1 | N45: No | O45: 1 | P45: 0.01 | Q45: 0 | R45: 1 | S45: 1 | T45: 1 | W45: 35448000 | Y45: Enabled | Z45: Item | AA45: Product | AC45: BOM
A46: 35.44.81.00 | B46: BERG InGround Champion USA 14ft + BERG Safety Net Deluxe USA | D46: UNDER_CON | E46: No | H46: Never | I46: Yes | J46: IMPOSSIBLE | K46: STD | M46: 1 | N46: No | O46: 1 | P46: 0.01 | Q46: 0 | R46: 1 | S46: 1 | T46: 1 | W46: 35448100 | Y46: Enabled | Z46: Item | AA46: Product | AC46: BOM
A47: 35.44.91.01 | B47: BERG InGround Champion Grey 430 + Safety Net Deluxe | D47: UNDER_CON | E47: No | H47: Never | I47: Yes | J47: IMPOSSIBLE | K47: TRAMPO | L47: CHN | M47: 6 | N47: No | O47: 1 | P47: 115.9 | Q47: 0 | R47: 1 | S47: 1 | T47: 1 | U47: 95069190 | W47: 35449101 | Y47: Enabled | Z47: Item | AA47: Product | AC47: BOM
A48: 35.44.92.01 | B48: BERG InGround Champion Grey 430 + Safety Net Comfort | D48: UNDER_CON | E48: No | H48: Never | I48: Yes | J48: IMPOSSIBLE | K48: TRAMPO | L48: CHN | M48: 6 | N48: No | O48: 1 | P48: 102.5 | Q48: 0 | R48: 1 | S48: 1 | T48: 1 | U48: 95069190 | W48: 35449201 | Y48: Enabled | Z48: Item | AA48: Product | AC48: BOM
A49: 35.44.93.01 | B49: BERG Champion Grey 430 + Safety Net Deluxe | D49: UNDER_CON | E49: No | H49: Never | I49: Yes | J49: IMPOSSIBLE | K49: TRAMPO | L49: CHN | M49: 6 | N49: No | O49: 1 | P49: 135.8 | Q49: 0 | R49: 1 | S49: 1 | T49: 1 | U49: 95069190 | W49: 35449301 | Y49: Enabled | Z49: Item | AA49: Product | AC49: BOM
A50: 35.44.94.01 | B50: BERG Champion Grey 430 + Safety Net Comfort | D50: UNDER_CON | E50: No | H50: Never | I50: Yes | J50: IMPOSSIBLE | K50: TRAMPO | L50: CHN | M50: 6 | N50: No | O50: 1 | P50: 122.2 | Q50: 0 | R50: 1 | S50: 1 | T50: 1 | U50: 95069190 | W50: 35449401 | Y50: Enabled | Z50: Item | AA50: Product | AC50: BOM
A51: 35.62.00.01 | B51: BERG EazyFit (Regular) + Safety Net Deluxe EazyFit | D51: UNDER_CON | E51: No | H51: Never | I51: Yes | J51: IMPOSSIBLE | K51: TRAMPO | L51: CHN | M51: 6 | N51: No | O51: 1 | P51: 116.6 | Q51: 0 | R51: 1 | S51: 1 | T51: 1 | U51: 95069190 | W51: 35620001 | Y51: Enabled | Z51: Item | AA51: Product | AC51: BOM
A52: 35.62.01.01 | B52: BERG InGround EazyFit + Safety Net Deluxe EazyFit | D52: UNDER_CON | E52: No | H52: Never | I52: Yes | J52: IMPOSSIBLE | K52: TRAMPO | L52: CHN | M52: 6 | N52: No | O52: 1 | P52: 95.65 | Q52: 0 | R52: 1 | S52: 1 | T52: 1 | U52: 95069190 | W52: 35620101 | Y52: Enabled | Z52: Item | AA52: Product | AC52: BOM
A53: 35.62.90.01 | B53: BERG EazyFit (Regular) Grey + Safety Net Deluxe EazyFit | D53: UNDER_CON | E53: No | H53: Never | I53: Yes | J53: IMPOSSIBLE | K53: TRAMPO | L53: CHN | M53: 6 | N53: No | O53: 1 | P53: 116.6 | Q53: 0 | R53: 1 | S53: 1 | T53: 1 | U53: 95069190 | W53: 35629001 | Y53: Enabled | Z53: Item | AA53: Product | AC53: BOM
A54: 35.62.91.01 | B54: BERG InGround EazyFit Grey + Safety Net Deluxe EazyFit | D54: UNDER_CON | E54: No | H54: Never | I54: Yes | J54: IMPOSSIBLE | K54: TRAMPO | L54: CHN | M54: 6 | N54: No | O54: 1 | P54: 99.65 | Q54: 0 | R54: 1 | S54: 1 | T54: 1 | U54: 95069190 | W54: 35629101 | Y54: Enabled | Z54: Item | AA54: Product | AC54: BOM
A55: 35.63.00.01 | B55: BERG InGround Grand Champion | D55: UNDER_CON | E55: No | H55: Never | I55: Yes | J55: IMPOSSIBLE | K55: TRAMPO | L55: CHN | M55: 6 | N55: No | O55: 1 | P55: 84.3 | Q55: 0 | R55: 1 | S55: 1 | T55: 1 | U55: 95069190 | W55: 35630001 | Y55: Enabled | Z55: Item | AA55: Product | AC55: BOM
A56: 35.63.01.01 | B56: BERG InGround Grand Champion + Safety Net Deluxe | D56: UNDER_CON | E56: No | H56: Never | I56: Yes | J56: IMPOSSIBLE | K56: TRAMPO | L56: CHN | M56: 6 | N56: No | O56: 1 | P56: 123.8 | Q56: 0 | R56: 1 | S56: 1 | T56: 1 | U56: 95069190 | W56: 35630101 | Y56: Enabled | Z56: Item | AA56: Product | AC56: BOM
A57: 35.63.02.01 | B57: BERG Grand Champion + Safety Net Deluxe | D57: UNDER_CON | E57: No | H57: Never | I57: Yes | J57: IMPOSSIBLE | K57: TRAMPO | L57: CHN | M57: 6 | N57: No | O57: 1 | P57: 144.6 | Q57: 0 | R57: 1 | S57: 1 | T57: 1 | U57: 95069190 | W57: 35630201 | Y57: Enabled | Z57: Item | AA57: Product | AC57: BOM
A58: 35.63.30.01 | B58: BERG InGround Grand Champion Grey | D58: UNDER_CON | E58: No | H58: Never | I58: Yes | J58: IMPOSSIBLE | K58: TRAMPO | L58: CHN | M58: 6 | N58: No | O58: 1 | P58: 84.3 | Q58: 0 | R58: 1 | S58: 1 | T58: 1 | U58: 95069190 | W58: 35633001 | Y58: Enabled | Z58: Item | AA58: Product | AC58: BOM
... A60: 35.63.32.01 | B60: BERG Grand Champion Grey + Safety Net Deluxe | D60: UNDER_CON | E60: No | H60: Never | I60: Yes | J60: IMPOSSIBLE | K60: TRAMPO | L60: CHN | M60: 6 | N60: No | O60: 1 | P60: 144.6 | Q60: 0 | R60: 1 | S60: 1 | T60: 1 | U60: 95069190 | W60: 35633201 | Y60: Enabled | Z60: Item | AA60: Product | AC60: BOM
A62: 35.11.43.00 | B62: BERG InGround Favorit Grey 330 (11 ft) | D62: UNDER_CON | E62: No | H62: Never | I62: No | J62: PENDING | K62: TRAMPO | M62: 1 | N62: No | O62: 1 | P62: 0.01 | Q62: 0 | R62: 1 | S62: 1 | T62: 1 | W62: 35114300 | Y62: Enabled | Z62: Item | AA62: Product | AC62: BOM
A63: 35.12.43.00 | B63: BERG InGround Favorit Grey 380 (12,5 ft) | D63: UNDER_CON | E63: No | H63: Never | I63: No | J63: PENDING | K63: TRAMPO | M63: 1 | N63: No | O63: 1 | P63: 0.01 | Q63: 0 | R63: 1 | S63: 1 | T63: 1 | W63: 35124300 | Y63: Enabled | Z63: Item | AA63: Product | AC63: BOM
A64: 35.14.43.00 | B64: BERG InGround Favorit Grey 430 (14 ft) | D64: UNDER_CON | E64: No | H64: Never | I64: No | J64: PENDING | K64: TRAMPO | M64: 1 | N64: No | O64: 1 | P64: 0.01 | Q64: 0 | R64: 1 | S64: 1 | T64: 1 | W64: 35144300 | Y64: Enabled | Z64: Item | AA64: Product | AC64: BOM
A65: 35.39.57.01 | B65: BERG InGround Champion 270 (9ft) | C65: 350446 | D65: UNDER_CON | E65: No | H65: Never | I65: No | J65: PENDING | K65: TRAMPO | L65: CHN | M65: 6 | N65: No | O65: 196168 | P65: 42.6 | Q65: 3.6 | R65: 31 | S65: 56 | T65: 113 | U65: 95069190 | W65: 35395701 | Y65: Enabled | Z65: Item | AA65: Product | AC65: BOM
A66: 35.41.53.01 | B66: BERG InGround Champion Grey 330 (11ft) | C66: 350446 | D66: UNDER_CON | E66: No | H66: Never | I66: No | J66: PENDING | K66: TRAMPO | L66: CHN | M66: 6 | N66: No | O66: 233585 | P66: 61.9 | Q66: 5.8 | R66: 31 | S66: 55 | T66: 137 | U66: 95069190 | W66: 35415301 | Y66: Enabled | Z66: Item | AA66: Product | AC66: BOM
A67: 35.41.57.01 | B67: BERG InGround Champion 330 (11ft) | C67: 350446 | D67: UNDER_CON | E67: No | H67: Never | I67: No | J67: PENDING | K67: TRAMPO | L67: CHN | M67: 6 | N67: No | O67: 233585 | P67: 61.9 | Q67: 5.8 | R67: 31 | S67: 55 | T67: 137 | U67: 95069190 | W67: 35415701 | Y67: Enabled | Z67: Item | AA67: Product | AC67: BOM
A68: 35.42.53.01 | B68: BERG InGround Champion Grey 380 (12,5ft) | C68: 350446 | D68: UNDER_CON | E68: No | H68: Never | I68: No | J68: PENDING | K68: TRAMPO | L68: CHN | M68: 6 | N68: No | O68: 269080 | P68: 70.3 | Q68: 8.9 | R68: 31 | S68: 56 | T68: 155 | U68: 95069190 | W68: 35425301 | Y68: Enabled | Z68: Item | AA68: Product | AC68: BOM
A69: 35.42.57.01 | B69: BERG InGround Champion 380 (12,5ft) | C69: 350446 | D69: UNDER_CON | E69: No | H69: Never | I69: No | J69: PENDING | K69: TRAMPO | L69: CHN | M69: 6 | N69: No | O69: 269080 | P69: 70.3 | Q69: 8.9 | R69: 31 | S69: 56 | T69: 155 | U69: 95069190 | W69: 35425701 | Y69: Enabled | Z69: Item | AA69: Product | AC69: BOM
A70: 35.44.53.01 | B70: BERG InGround Champion Grey 430 (14ft) | C70: 350446 | D70: UNDER_CON | E70: No | H70: Never | I70: No | J70: PENDING | K70: TRAMPO | L70: CHN | M70: 6 | N70: No | O70: 291555 | P70: 77.3 | Q70: 9 | R70: 31 | S70: 55 | T70: 171 | U70: 95069190 | W70: 35445301 | Y70: Enabled | Z70: Item | AA70: Product | AC70: BOM
A71: 35.44.57.01 | B71: BERG InGround Champion 430 (14ft) | C71: 350446 | D71: UNDER_CON | E71: No | H71: Never | I71: No | J71: PENDING | K71: TRAMPO | L71: CHN | M71: 6 | N71: No | O71: 291555 | P71: 77.3 | Q71: 9 | R71: 31 | S71: 55 | T71: 171 | U71: 95069190 | W71: 35445701 | Y71: Enabled | Z71: Item | AA71: Product | AC71: BOM
A72: 35.62.53.01 | B72: BERG InGround EazyFit Grey | C72: 350446 | D72: UNDER_CON | E72: No | H72: Never | I72: No | J72: PENDING | K72: TRAMPO | L72: CHN | M72: 6 | N72: No | O72: 304325 | P72: 63.05 | Q72: 9.55 | R72: 35 | S72: 47 | T72: 185 | U72: 95069190 | W72: 35625301 | Y72: Enabled | Z72: Item | AA72: Product | AC72: BOM
A73: 35.62.57.01 | B73: BERG InGround EazyFit | C73: 350446 | D73: UNDER_CON | E73: No | H73: Never | I73: No | J73: PENDING | K73: TRAMPO | L73: CHN | M73: 6 | N73: No | O73: 304325 | P73: 63.05 | Q73: 9.55 | R73: 35 | S73: 47 | T73: 185 | U73: 95069190 | W73: 35625701 | Y73: Enabled | Z73: Item | AA73: Product | AC73: BOM
A74: 35.63.83.00 | B74: BERG Grand Champion Grey (InGround) (Box 2/2) | C74: 351840 | D74: UNDER_CON | E74: No | H74: Never | I74: No | J74: PENDING | K74: TRAMPO | L74: CHN | M74: 6 | N74: No | O74: 288768 | P74: 20.1 | Q74: 8.1 | R74: 24 | S74: 64 | T74: 188 | U74: 95069190 | W74: 35638300 | Y74: Enabled | Z74: Item | AA74: Product | AC74: BOM

Sheet EAN
A1: Item number | B1: Description | C1: Bar code
A2: 01.95.14.00 | B2: BERG Buster BF prof | C2: 8715839034868
A3: 02.41.82.00 | B3: GK 1505 - KRAMP Midi AF | C3: 8716106025404
A4: 02.66.02.00 | B4: BERG Donald AF | C4: 8715839010831
A5: 02.66.02.01 | B5: BERG Donald F Blue | C5: 8715839029345
A6: 02.66.02.02 | B6: BERG Donald F Red | C6: 8715839029352
A7: 02.79.52.01 | B7: BERG Delta AF | C7: 8715839020373
A8: 03.11.50.00 | B8: BERG Basic Rood + Duostoel | C8: 8715839014785
A9: 03.11.52.00 | B9: BERG Basic AF Rood + Duostoel | C9: 8715839014389
A10: 03.15.00.00 | B10: BERG Basic | C10: 8715839020953
A11: 03.15.02.00 | B11: BERG Basic AF blauw | C11: 8715839020960
A12: 03.15.80.00 | B12: BERG Basic zilver | C12: 8715839022544
... A4433: 99.99.99.99 | B4433: Tekstregel - MAX 30 tekens!! | C4433: 8715839040975

Sheet Mastersheet
A1: 07.10.00.00 | C1: TRUE | D1: TRUE | E1: 0 | F1: 0 | G1: 0 | H1: 95030010 | I1: 6 | J1: 40.5 | K1: 5.9 | M1: ACTIVE | O1: STD | P1: BERG Extra BFR | Q1: BERG Extra BFR | R1: BERG Extra BFR | S1: BERG Extra BFR | T1: 8715839050936 | U1: 0 | V1: TRUE | W1: FALSE | X1: FALSE | Y1: Purchase order | Z1: 371.07 | AA1: EUR | AB1: 299.33 | AC1: EUR | AD1: 359.2 | AE1: USD | AF1: 304.27 | AG1: EUR | AH1: 232.75 | AI1: GBP | AJ1: 449 | AK1: EUR
A2: 07.10.01.00 | C2: TRUE | D2: TRUE | E2: 0 | F2: 0 | G2: 0 | H2: 95030010 | I2: 6 | J2: 42.5 | K2: 8.5 | M2: ACTIVE | O2: STD | P2: BERG Extra Sport BFR | Q2: BERG Extra Sport BFR | R2: BERG Extra Sport BFR | S2: BERG Extra Sport BFR | T2: 8715839050943 | U2: 0 | V2: FALSE | W2: FALSE | X2: FALSE | Y2: Purchase order | Z2: 412.4 | AA2: EUR | AB2: 332.67 | AC2: EUR | AD2: 399.2 | AE2: USD | AF2: 334.76 | AG2: EUR | AH2: 261.92 | AI2: GBP | AJ2: 499 | AK2: EUR
A3: 07.10.02.00 | C3: TRUE | D3: TRUE | E3: 0 | F3: 0 | G3: 0 | H3: 95030010 | I3: 6 | J3: 48 | K3: 8.6 | M3: ACTIVE | O3: STD | P3: BERG Race BFR | Q3: BERG Race BFR | R3: BERG Race BFR | S3: BERG Race BFR | T3: 8715839050950 | U3: 0 | V3: TRUE | W3: FALSE | X3: FALSE | Y3: Purchase order | Z3: 519.83 | AA3: EUR | AB3: 419.33 | AC3: EUR | AD3: 503.2 | AE3: USD | AF3: 401.83 | AG3: EUR | AH3: 320.25 | AI3: GBP | AJ3: 629 | AK3: EUR
A4: 07.10.03.00 | C4: TRUE | D4: TRUE | E4: 0 | F4: 0 | G4: 0 | H4: 95030010 | I4: 6 | J4: 45 | K4: 8.6 | M4: ACTIVE | O4: STD | P4: BERG X-Plore BFR | Q4: BERG X-Plore BFR | R4: BERG X-Plore BFR | S4: BERG X-Plore BFR | T4: 8715839050967 | U4: 0 | V4: TRUE | W4: FALSE | X4: FALSE | Y4: Purchase order | Z4: 503.31 | AA4: EUR | AB4: 406 | AC4: EUR | AD4: 487.2 | AE4: USD | AF4: 395.73 | AG4: EUR | AH4: 308.58 | AI4: GBP | AJ4: 609 | AK4: EUR
A5: 07.10.04.00 | C5: TRUE | D5: TRUE | E5: 0 | F5: 0 | G5: 0 | H5: 95030010 | I5: 6 | J5: 40 | K5: 0 | M5: ACTIVE | O5: STD | P5: BERG Route 66 BFR | Q5: BERG Route 66 BFR | R5: BERG Route 66 BFR | S5: BERG Route 66 BFR | T5: 8715839050974 | U5: 0 | V5: TRUE | W5: FALSE | X5: FALSE | Y5: Purchase order | Z5: 453.72 | AA5: EUR | AB5: 366 | AC5: EUR | AD5: 423.2 | AE5: USD | AF5: 365.24 | AG5: EUR | AH5: 279.42 | AI5: GBP | AJ5: 549 | AK5: EUR
A6: 07.10.05.00 | C6: TRUE | D6: TRUE | E6: 0 | F6: 0 | G6: 0 | H6: 95030010 | I6: 6 | J6: 43.6 | K6: 8.6 | M6: ACTIVE | O6: STD | P6: BERG Black Edition BFR | Q6: BERG Black Edition BFR | R6: BERG Black Edition BFR | S6: BERG Black Edition BFR | T6: 8715839050981 | U6: 0 | V6: FALSE | W6: FALSE | X6: FALSE | Y6: Purchase order | Z6: 470.25 | AA6: EUR | AB6: 379.33 | AC6: EUR | AD6: 455.2 | AE6: USD | AF6: 377.44 | AG6: EUR | AH6: 291.08 | AI6: GBP | AJ6: 569 | AK6: EUR
A7: 07.10.06.00 | C7: TRUE | D7: TRUE | E7: 0 | F7: 0 | G7: 0 | H7: 95030010 | I7: 6 | J7: 39 | K7: 5.9 | M7: ACTIVE | O7: STD | P7: BERG Basic BFR | Q7: BERG Basic BFR | R7: BERG Basic BFR | S7: BERG Basic BFR | T7: 8715839050998 | U7: 0 | V7: TRUE | W7: FALSE | X7: FALSE | Y7: Purchase order | Z7: 346.28 | AA7: EUR | AB7: 279.33 | AC7: EUR | AD7: 335.2 | AE7: USD | AF7: 279.6 | AG7: EUR | AH7: 215.25 | AI7: GBP | AJ7: 419 | AK7: EUR
A8: 07.10.07.00 | C8: TRUE | D8: TRUE | E8: 0 | F8: 0 | G8: 0 | H8: 95030010 | I8: 6 | J8: 50.5 | K8: 9.1 | M8: ACTIVE | O8: STD | P8: BERG Safari BFR | Q8: BERG Safari BFR | R8: BERG Safari BFR | S8: BERG Safari BFR | T8: 8715839051001 | U8: 0 | V8: FALSE | W8: FALSE | X8: FALSE | Y8: Purchase order | Z8: 544.63 | AA8: EUR | AB8: 439.33 | AC8: EUR | AD8: 527.2 | AE8: USD | AF8: 444.51 | AG8: EUR | AH8: 337.75 | AI8: GBP | AJ8: 659 | AK8: EUR
A9: 07.10.08.00 | C9: TRUE | D9: TRUE | E9: 0 | F9: 0 | G9: 0 | H9: 95030010 | I9: 6 | J9: 43.1 | K9: 8.6 | M9: ACTIVE | O9: STD | P9: BERG X-Cross BFR | Q9: BERG X-Cross BFR | R9: BERG X-Cross BFR | S9: BERG X-Cross BFR | T9: 8715839051018 | U9: 0 | V9: FALSE | W9: FALSE | X9: FALSE | Y9: Purchase order | Z9: 437.19 | AA9: EUR | AB9: 352.67 | AC9: EUR | AD9: 423.2 | AE9: USD | AF9: 353.05 | AG9: EUR | AH9: 267.75 | AI9: GBP | AJ9: 529 | AK9: EUR
A10: 07.10.09.00 | C10: TRUE | D10: FALSE | E10: 1 | F10: 1 | G10: 1 | H10: 95030010 | I10: 1 | J10: 42.5 | K10: 8.5 | M10: ACTIVE | O10: STD | P10: BERG Extra Sport Red BFR | Q10: BERG Extra Sport Red BFR | R10: BERG Extra Sport Red BFR | S10: BERG Extra Sport Red BFR | T10: 8715839060034 | U10: 0 | V10: TRUE | W10: FALSE | X10: FALSE | Y10: Purchase order | Z10: 412.4 | AA10: EUR | AB10: 332.67 | AC10: EUR | AD10: 399.2 | AE10: USD | AF10: 334.76 | AG10: EUR | AH10: 261.92 | AI10: GBP | AJ10: 499 | AK10: EUR
A11: 07.10.10.00 | C11: FALSE | D11: FALSE | E11: 1 | F11: 1 | G11: 1 | H11: 95030010 | I11: 1 | J11: 0.01 | K11: 0 | M11: UNDER_CON | O11: STD | P11: BERG Basic Red BFR | Q11: BERG Basic Red BFR | R11: BERG Basic Red BFR | S11: BERG Basic Red BFR | T11: 8715839063462 | U11: 0 | V11: TRUE | W11: TRUE | X11: FALSE | Y11: Purchase order
A12: 07.10.11.00 | C12: FALSE | D12: FALSE | E12: 1 | F12: 1 | G12: 1 | H12: 95030010 | I12: 1 | J12: 0.01 | K12: 0 | M12: UNDER_CON | O12: STD | P12: BERG Extra Red BFR | Q12: BERG Extra Red BFR | R12: BERG Extra Red BFR | S12: BERG Extra Red BFR | T12: 8715839063479 | U12: 0 | V12: TRUE | W12: TRUE | X12: FALSE | Y12: Purchase order
A13: 07.10.12.00 | C13: FALSE | D13: FALSE | E13: 1 | F13: 1 | G13: 1 | H13: 95030010 | I13: 1 | J13: 0.01 | K13: 0 | M13: UNDER_CON | O13: STD | P13: BERG Extra Sport Red BFR | Q13: BERG Extra Sport Red BFR | R13: BERG Extra Sport Red BFR | S13: BERG Extra Sport Red BFR | T13: 8715839063486 | U13: 0 | V13: TRUE | W13: TRUE | X13: FALSE | Y13: Purchase order
A14: 07.10.13.00 | C14: FALSE | D14: FALSE | E14: 1 | F14: 1 | G14: 1 | H14: 95030010 | I14: 1 | J14: 0.01 | K14: 0 | M14: UNDER_CON | O14: STD | P14: BERG Special christmas 2017 BFR | Q14: BERG Special christmas 2017 BFR | R14: BERG Special christmas 2017 BFR | S14: BERG Special christmas 2017 BFR | T14: 8715839063509 | U14: 0 | V14: TRUE | W14: TRUE | X14: FALSE | Y14: Purchase order
A15: 07.11.00.00 | C15: TRUE | D15: TRUE | E15: 100 | F15: 80 | G15: 58 | H15: 95030010 | I15: 4 | J15: 51 | K15: 9.1 | M15: ACTIVE | O15: STD | P15: BERG John Deere BFR | Q15: BERG John Deere BFR | R15: BERG John Deere BFR | S15: BERG John Deere BFR | T15: 8715839051025 | U15: 0 | V15: TRUE | W15: FALSE | X15: FALSE | Y15: Purchase order | Z15: 561.16 | AA15: EUR | AB15: 452.67 | AC15: EUR | AD15: 543.2 | AE15: USD | AF15: 481.1 | AG15: EUR | AH15: 349.42 | AI15: GBP | AJ15: 679 | AK15: EUR
A16: 07.11.01.00 | C16: TRUE | D16: TRUE | E16: 0 | F16: 0 | G16: 0 | H16: 95030010 | I16: 6 | J16: 51 | K16: 9.1 | M16: ACTIVE | O16: STD | P16: BERG CLAAS BFR | Q16: BERG CLAAS BFR | R16: BERG CLAAS BFR | S16: BERG CLAAS BFR | T16: 8715839051032 | U16: 0 | V16: TRUE | W16: FALSE | X16: FALSE | Y16: Purchase order | Z16: 561.16 | AA16: EUR | AB16: 452.67 | AC16: EUR | AD16: 543.2 | AE16: USD | AF16: 481.1 | AG16: EUR | AH16: 349.42 | AI16: GBP | AJ16: 679 | AK16: EUR
A17: 07.11.02.00 | C17: TRUE | D17: TRUE | E17: 0 | F17: 0 | G17: 0 | H17: 95030010 | I17: 6 | J17: 51 | K17: 9.1 | M17: ACTIVE | O17: STD | P17: BERG Case IH BFR | Q17: BERG Case IH BFR | R17: BERG Case IH BFR | S17: BERG Case IH BFR | T17: 8715839051049 | U17: 0 | V17: TRUE | W17: FALSE | X17: FALSE | Y17: Purchase order | Z17: 561.16 | AA17: EUR | AB17: 452.67 | AC17: EUR | AD17: 543.2 | AE17: USD | AF17: 481.1 | AG17: EUR | AH17: 349.42 | AI17: GBP | AJ17: 679 | AK17: EUR
A18: 07.11.03.00 | C18: TRUE | D18: TRUE | E18: 0 | F18: 0 | G18: 0 | H18: 95030010 | I18: 6 | J18: 51 | K18: 9.1 | M18: ACTIVE | O18: STD | P18: BERG New Holland BFR | Q18: BERG New Holland BFR | R18: BERG New Holland BFR | S18: BERG New Holland BFR | T18: 8715839051056 | U18: 0 | V18: TRUE | W18: FALSE | X18: FALSE | Y18: Purchase order | Z18: 561.16 | AA18: EUR | AB18: 452.67 | AC18: EUR | AD18: 543.2 | AE18: USD | AF18: 481.1 | AG18: EUR | AH18: 349.42 | AI18: GBP | AJ18: 679 | AK18: EUR
A19: 07.11.04.00 | C19: TRUE | D19: TRUE | E19: 0 | F19: 0 | G19: 0 | H19: 95030010 | I19: 6 | J19: 51 | K19: 9.1 | M19: ACTIVE | O19: STD | P19: BERG Fendt BFR | Q19: BERG Fendt BFR | R19: BERG Fendt BFR | S19: BERG Fendt BFR | T19: 8715839051063 | U19: 0 | V19: TRUE | W19: FALSE | X19: FALSE | Y19: Purchase order | Z19: 561.16 | AA19: EUR | AB19: 452.67 | AC19: EUR | AD19: 543.2 | AE19: USD | AF19: 481.1 | AG19: EUR | AH19: 349.42 | AI19: GBP | AJ19: 679 | AK19: EUR
A20: 07.11.05.00 | C20: TRUE | D20: TRUE | E20: 0 | F20: 0 | G20: 0 | H20: 95030010 | I20: 6 | J20: 51 | K20: 9.1 | M20: ACTIVE | O20: STD | P20: BERG DEUTZ-FAHR BFR | Q20: BERG DEUTZ-FAHR BFR | R20: BERG DEUTZ-FAHR BFR | S20: BERG DEUTZ-FAHR BFR | T20: 8715839051070 | U20: 0 | V20: TRUE | W20: FALSE | X20: FALSE | Y20: Purchase order | Z20: 561.16 | AA20: EUR | AB20: 452.67 | AC20: EUR | AD20: 543.2 | AE20: USD | AF20: 481.1 | AG20: EUR | AH20: 349.42 | AI20: GBP | AJ20: 679 | AK20: EUR
A21: 07.11.06.00 | C21: TRUE | D21: TRUE | E21: 0 | F21: 0 | G21: 0 | H21: 95030010 | I21: 6 | J21: 51 | K21: 8.6 | M21: ACTIVE | O21: STD | P21: Jeep® Revolution pedal go-kart BFR | Q21: Jeep® Revolution pedal go-kart BFR | R21: Jeep® Revolution pedal go-kart BFR | S21: Jeep® Revolution pedal go-kart BFR | T21: 8715839051087 | U21: 0 | V21: FALSE | W21: FALSE | X21: FALSE | Y21: Purchase order | Z21: 544.63 | AA21: EUR | AB21: 439.33 | AC21: EUR | AD21: 527.2 | AE21: USD | AF21: 450.61 | AG21: EUR | AH21: 343.58 | AI21: GBP | AJ21: 659 | AK21: EUR
A22: 07.12.00.00 | C22: TRUE | D22: TRUE | E22: 1 | F22: 1 | G22: 1 | H22: 95030010 | I22: 1 | J22: 58.6 | K22: 10.3 | M22: UNDER_CON | O22: STD | P22: BERG Duo Chopper BF | Q22: BERG Duo Chopper BF | R22: BERG Duo Chopper BF | S22: BERG Duo Chopper BF | T22: 8715839058598 | U22: 0 | V22: TRUE | W22: FALSE | X22: FALSE | Y22: Purchase order | Z22: 577.69 | AA22: EUR | AB22: 466 | AC22: EUR | AD22: 532.67 | AE22: USD | AF22: 426.22 | AG22: EUR | AH22: 355.25 | AI22: GBP | AJ22: 699 | AK22: EUR
A23: 07.15.01.00 | C23: FALSE | D23: FALSE | E23: 1 | F23: 1 | G23: 1 | H23: 95030010 | I23: 1 | J23: 0.01 | K23: 0 | M23: UNDER_CON | O23: STD | P23: BERG XXL Extra Sport BFR | Q23: BERG XXL Extra Sport BFR | R23: BERG XXL Extra Sport BFR | S23: BERG XXL Extra Sport BFR | T23: 8715839063189 | U23: 0 | V23: TRUE | W23: TRUE | X23: FALSE | Y23: Purchase order
A24: 07.15.02.00 | C24: FALSE | D24: FALSE | E24: 1 | F24: 1 | G24: 1 | H24: 95030010 | I24: 1 | J24: 0.01 | K24: 0 | M24: UNDER_CON | O24: STD | P24: BERG XXL Race BFR | Q24: BERG XXL Race BFR | R24: BERG XXL Race BFR | S24: BERG XXL Race BFR | T24: 8715839063196 | U24: 0 | V24: TRUE | W24: TRUE | X24: FALSE | Y24: Purchase order
A25: 07.15.03.00 | C25: FALSE | D25: FALSE | E25: 1 | F25: 1 | G25: 1 | H25: 95030010 | I25: 1 | J25: 0.01 | K25: 0 | M25: UNDER_CON | O25: STD | P25: BERG XXL X-Plore BFR | Q25: BERG XXL X-Plore BFR | R25: BERG XXL X-Plore BFR | S25: BERG XXL X-Plore BFR | T25: 8715839063202 | U25: 0 | V25: TRUE | W25: TRUE | X25: FALSE | Y25: Purchase order
A26: 07.15.05.00 | C26: FALSE | D26: FALSE | E26: 1 | F26: 1 | G26: 1 | H26: 95030010 | I26: 1 | J26: 0.01 | K26: 0 | M26: UNDER_CON | O26: STD | P26: BERG XXL Black Edition BFR | Q26: BERG XXL Black Edition BFR | R26: BERG XXL Black Edition BFR | S26: BERG XXL Black Edition BFR | T26: 8715839063219 | U26: 0 | V26: TRUE | W26: TRUE | X26: FALSE | Y26: Purchase order
A27: 07.15.07.00 | C27: FALSE | D27: FALSE | E27: 1 | F27: 1 | G27: 1 | H27: 95030010 | I27: 1 | J27: 0.01 | K27: 0 | M27: UNDER_CON | O27: STD | P27: BERG XXL Safari BFR | Q27: BERG XXL Safari BFR | R27: BERG XXL Safari BFR | S27: BERG XXL Safari BFR | T27: 8715839063226 | U27: 0 | V27: TRUE | W27: TRUE | X27: FALSE | Y27: Purchase order
A28: 07.15.08.00 | C28: FALSE | D28: FALSE | E28: 1 | F28: 1 | G28: 1 | H28: 95030010 | I28: 1 | J28: 0.01 | K28: 0 | M28: UNDER_CON | O28: STD | P28: BERG XXL X-Cross BFR | Q28: BERG XXL X-Cross BFR | R28: BERG XXL X-Cross BFR | S28: BERG XXL X-Cross BFR | T28: 8715839063233 | U28: 0 | V28: TRUE | W28: TRUE | X28: FALSE | Y28: Purchase order
A29: 07.15.12.00 | C29: FALSE | D29: FALSE | E29: 1 | F29: 1 | G29: 1 | H29: 95030010 | I29: 1 | J29: 0.01 | K29: 0 | M29: UNDER_CON | O29: STD | P29: BERG XXL Extra Sport Red BFR | Q29: BERG XXL Extra Sport Red BFR | R29: BERG XXL Extra Sport Red BFR | S29: BERG XXL Extra Sport Red BFR | T29: 8715839063455 | U29: 0 | V29: TRUE | W29: TRUE | X29: FALSE | Y29: Purchase order
A30: 07.16.00.00 | C30: FALSE | D30: FALSE | E30: 1 | F30: 1 | G30: 1 | H30: 95030010 | I30: 1 | J30: 0.01 | K30: 0 | M30: UNDER_CON | O30: STD | P30: BERG XXL John Deere BFR | Q30: BERG XXL John Deere BFR | R30: BERG XXL John Deere BFR | S30: BERG XXL John Deere BFR | T30: 8715839063240 | U30: 0 | V30: TRUE | W30: TRUE | X30: FALSE | Y30: Purchase order
A31: 07.16.01.00 | C31: FALSE | D31: FALSE | E31: 1 | F31: 1 | G31: 1 | H31: 95030010 | I31: 1 | J31: 0.01 | K31: 0 | M31: UNDER_CON | O31: STD | P31: BERG XXL CLAAS BFR | Q31: BERG XXL CLAAS BFR | R31: BERG XXL CLAAS BFR | S31: BERG XXL CLAAS BFR | T31: 8715839063257 | U31: 0 | V31: TRUE | W31: TRUE | X31: FALSE | Y31: Purchase order
A32: 07.16.02.00 | C32: FALSE | D32: FALSE | E32: 1 | F32: 1 | G32: 1 | H32: 95030010 | I32: 1 | J32: 0.01 | K32: 0 | M32: UNDER_CON | O32: STD | P32: BERG XXL Case IH BFR | Q32: BERG XXL Case IH BFR | R32: BERG XXL Case IH BFR | S32: BERG XXL Case IH BFR | T32: 8715839063264 | U32: 0 | V32: TRUE | W32: TRUE | X32: FALSE | Y32: Purchase order
A33: 07.16.03.00 | C33: FALSE | D33: FALSE | E33: 1 | F33: 1 | G33: 1 | H33: 95030010 | I33: 1 | J33: 0.01 | K33: 0 | M33: UNDER_CON | O33: STD | P33: BERG XXL New Holland BFR | Q33: BERG XXL New Holland BFR | R33: BERG XXL New Holland BFR | S33: BERG XXL New Holland BFR | T33: 8715839063271 | U33: 0 | V33: TRUE | W33: TRUE | X33: FALSE | Y33: Purchase order
A34: 07.16.04.00 | C34: FALSE | D34: FALSE | E34: 1 | F34: 1 | G34: 1 | H34: 95030010 | I34: 1 | J34: 0.01 | K34: 0 | M34: UNDER_CON | O34: STD | P34: BERG XXL Fendt BFR | Q34: BERG XXL Fendt BFR | R34: BERG XXL Fendt BFR | S34: BERG XXL Fendt BFR | T34: 8715839063288 | U34: 0 | V34: TRUE | W34: TRUE | X34: FALSE | Y34: Purchase order
... A36: 07.16.06.00 | C36: FALSE | D36: FALSE | E36: 1 | F36: 1 | G36: 1 | H36: 95030010 | I36: 1 | J36: 0.01 | K36: 0 | M36: UNDER_CON | O36: STD | P36: Jeep® Revolution pedal go-kart XXL BFR | Q36: Jeep® Revolution pedal go-kart XXL BFR | R36: Jeep® Revolution pedal go-kart XXL BFR | S36: Jeep® Revolution pedal go-kart XXL BFR | T36: 8715839063301 | U36: 0 | V36: TRUE | W36: TRUE | X36: FALSE | Y36: Purchase order
A37: 07.20.01.00 | C37: TRUE | D37: TRUE | E37: 0 | F37: 0 | G37: 0 | H37: 95030010 | I37: 6 | J37: 44.5 | K37: 8.5 | M37: ACTIVE | O37: STD | P37: BERG Extra Sport BFR-3 | Q37: BERG Extra Sport BFR-3 | R37: BERG Extra Sport BFR-3 | S37: BERG Extra Sport BFR-3 | T37: 8715839051094 | U37: 0 | V37: TRUE | W37: FALSE | X37: FALSE | Y37: Purchase order | Z37: 577.69 | AA37: EUR | AB37: 466 | AC37: EUR | AD37: 559.2 | AE37: USD | AF37: 456.71 | AG37: EUR | AH37: 361.08 | AI37: GBP | AJ37: 699 | AK37: EUR
A38: 07.20.02.00 | C38: TRUE | D38: TRUE | E38: 0 | F38: 0 | G38: 0 | H38: 95030010 | I38: 6 | J38: 50 | K38: 8.6 | M38: ACTIVE | O38: STD | P38: BERG Race BFR-3 | Q38: BERG Race BFR-3 | R38: BERG Race BFR-3 | S38: BERG Race BFR-3 | T38: 8715839051100 | U38: 0 | V38: TRUE | W38: FALSE | X38: FALSE | Y38: Purchase order | Z38: 685.12 | AA38: EUR | AB38: 552.67 | AC38: EUR | AD38: 663.2 | AE38: USD | AF38: 535.98 | AG38: EUR | AH38: 425.25 | AI38: GBP | AJ38: 829 | AK38: EUR
A39: 07.20.03.00 | C39: TRUE | D39: TRUE | E39: 0 | F39: 0 | G39: 0 | H39: 95030010 | I39: 6 | J39: 47 | K39: 8.6 | M39: ACTIVE | O39: STD | P39: BERG X-Plore BFR-3 | Q39: BERG X-Plore BFR-3 | R39: BERG X-Plore BFR-3 | S39: BERG X-Plore BFR-3 | T39: 8715839051117 | U39: 0 | V39: TRUE | W39: FALSE | X39: FALSE | Y39: Purchase order | Z39: 668.6 | AA39: EUR | AB39: 539.33 | AC39: EUR | AD39: 647.2 | AE39: USD | AF39: 523.78 | AG39: EUR | AH39: 425.25 | AI39: GBP | AJ39: 809 | AK39: EUR
A40: 07.20.05.00 | C40: TRUE | D40: TRUE | E40: 0 | F40: 0 | G40: 0 | H40: 95030010 | I40: 6 | J40: 45.6 | K40: 8.6 | M40: ACTIVE | O40: STD | P40: BERG Black Edition BFR-3 | Q40: BERG Black Edition BFR-3 | R40: BERG Black Edition BFR-3 | S40: BERG Black Edition BFR-3 | T40: 8715839051124 | U40: 0 | V40: TRUE | W40: FALSE | X40: FALSE | Y40: Purchase order | Z40: 635.54 | AA40: EUR | AB40: 512.67 | AC40: EUR | AD40: 615.2 | AE40: USD | AF40: 499.39 | AG40: EUR | AH40: 396.08 | AI40: GBP | AJ40: 769 | AK40: EUR
A41: 07.20.07.00 | C41: TRUE | D41: TRUE | E41: 0 | F41: 0 | G41: 0 | H41: 95030010 | I41: 6 | J41: 52.5 | K41: 9.1 | M41: ACTIVE | O41: STD | P41: BERG Safari BFR-3 | Q41: BERG Safari BFR-3 | R41: BERG Safari BFR-3 | S41: BERG Safari BFR-3 | T41: 8715839051131 | U41: 0 | V41: TRUE | W41: FALSE | X41: FALSE | Y41: Purchase order | Z41: 709.92 | AA41: EUR | AB41: 572.67 | AC41: EUR | AD41: 687.2 | AE41: USD | AF41: 548.17 | AG41: EUR | AH41: 442.75 | AI41: GBP | AJ41: 859 | AK41: EUR
A42: 07.20.08.00 | C42: TRUE | D42: TRUE | E42: 0 | F42: 0 | G42: 0 | H42: 95030010 | I42: 6 | J42: 45.1 | K42: 8.6 | M42: ACTIVE | O42: STD | P42: BERG X-Cross BFR-3 | Q42: BERG X-Cross BFR-3 | R42: BERG X-Cross BFR-3 | S42: BERG X-Cross BFR-3 | T42: 8715839051148 | U42: 0 | V42: FALSE | W42: FALSE | X42: FALSE | Y42: Purchase order | Z42: 602.48 | AA42: EUR | AB42: 486 | AC42: EUR | AD42: 583.2 | AE42: USD | AF42: 475 | AG42: EUR | AH42: 372.75 | AI42: GBP | AJ42: 729 | AK42: EUR
A43: 07.20.12.00 | C43: FALSE | D43: FALSE | E43: 1 | F43: 1 | G43: 1 | H43: 95030010 | I43: 1 | J43: 0.01 | K43: 0 | M43: UNDER_CON | O43: STD | P43: BERG Extra Sport Red BFR-3 | Q43: BERG Extra Sport Red BFR-3 | R43: BERG Extra Sport Red BFR-3 | S43: BERG Extra Sport Red BFR-3 | T43: 8715839063493 | U43: 0 | V43: TRUE | W43: TRUE | X43: FALSE | Y43: Purchase order
A44: 07.21.00.00 | C44: TRUE | D44: TRUE | E44: 100 | F44: 80 | G44: 58 | H44: 95030010 | I44: 4 | J44: 53 | K44: 9.1 | M44: ACTIVE | O44: STD | P44: BERG John Deere BFR-3 | Q44: BERG John Deere BFR-3 | R44: BERG John Deere BFR-3 | S44: BERG John Deere BFR-3 | T44: 8715839051155 | U44: 0 | V44: TRUE | W44: FALSE | X44: FALSE | Y44: Purchase order | Z44: 726.45 | AA44: EUR | AB44: 586 | AC44: EUR | AD44: 703.2 | AE44: USD | AF44: 596.95 | AG44: EUR | AH44: 448.58 | AI44: GBP | AJ44: 879 | AK44: EUR
A45: 07.21.01.00 | C45: TRUE | D45: TRUE | E45: 0 | F45: 0 | G45: 0 | H45: 95030010 | I45: 6 | J45: 53 | K45: 9.1 | M45: ACTIVE | O45: STD | P45: BERG CLAAS BFR-3 | Q45: BERG CLAAS BFR-3 | R45: BERG CLAAS BFR-3 | S45: BERG CLAAS BFR-3 | T45: 8715839051162 | U45: 0 | V45: TRUE | W45: FALSE | X45: FALSE | Y45: Purchase order | Z45: 726.45 | AA45: EUR | AB45: 586 | AC45: EUR | AD45: 703.2 | AE45: USD | AF45: 596.95 | AG45: EUR | AH45: 448.58 | AI45: GBP | AJ45: 879 | AK45: EUR
A46: 07.21.02.00 | C46: TRUE | D46: TRUE | E46: 0 | F46: 0 | G46: 0 | H46: 95030010 | I46: 6 | J46: 53 | K46: 9.1 | M46: ACTIVE | O46: STD | P46: BERG Case IH BFR-3 | Q46: BERG Case IH BFR-3 | R46: BERG Case IH BFR-3 | S46: BERG Case IH BFR-3 | T46: 8715839051179 | U46: 0 | V46: TRUE | W46: FALSE | X46: FALSE | Y46: Purchase order | Z46: 726.45 | AA46: EUR | AB46: 586 | AC46: EUR | AD46: 703.2 | AE46: USD | AF46: 596.95 | AG46: EUR | AH46: 448.58 | AI46: GBP | AJ46: 879 | AK46: EUR
A47: 07.21.03.00 | C47: TRUE | D47: TRUE | E47: 0 | F47: 0 | G47: 0 | H47: 95030010 | I47: 6 | J47: 53 | K47: 9.1 | M47: ACTIVE | O47: STD | P47: BERG New Holland BFR-3 | Q47: BERG New Holland BFR-3 | R47: BERG New Holland BFR-3 | S47: BERG New Holland BFR-3 | T47: 8715839051186 | U47: 0 | V47: TRUE | W47: FALSE | X47: FALSE | Y47: Purchase order | Z47: 726.45 | AA47: EUR | AB47: 586 | AC47: EUR | AD47: 703.2 | AE47: USD | AF47: 596.95 | AG47: EUR | AH47: 448.58 | AI47: GBP | AJ47: 879 | AK47: EUR
A48: 07.21.04.00 | C48: TRUE | D48: TRUE | E48: 0 | F48: 0 | G48: 0 | H48: 95030010 | I48: 6 | J48: 53 | K48: 9.1 | M48: ACTIVE | O48: STD | P48: BERG Fendt BFR-3 | Q48: BERG Fendt BFR-3 | R48: BERG Fendt BFR-3 | S48: BERG Fendt BFR-3 | T48: 8715839051193 | U48: 0 | V48: TRUE | W48: FALSE | X48: FALSE | Y48: Purchase order | Z48: 726.45 | AA48: EUR | AB48: 586 | AC48: EUR | AD48: 703.2 | AE48: USD | AF48: 596.95 | AG48: EUR | AH48: 448.58 | AI48: GBP | AJ48: 879 | AK48: EUR
A49: 07.21.05.00 | C49: TRUE | D49: TRUE | E49: 0 | F49: 0 | G49: 0 | H49: 95030010 | I49: 6 | J49: 53 | K49: 9.1 | M49: ACTIVE | O49: STD | P49: BERG DEUTZ-FAHR BFR-3 | Q49: BERG DEUTZ-FAHR BFR-3 | R49: BERG DEUTZ-FAHR BFR-3 | S49: BERG DEUTZ-FAHR BFR-3 | T49: 8715839051209 | U49: 0 | V49: TRUE | W49: FALSE | X49: FALSE | Y49: Purchase order | Z49: 726.45 | AA49: EUR | AB49: 586 | AC49: EUR | AD49: 703.2 | AE49: USD | AF49: 596.95 | AG49: EUR | AH49: 448.58 | AI49: GBP | AJ49: 879 | AK49: EUR
A50: 07.21.06.00 | C50: TRUE | D50: TRUE | E50: 0 | F50: 0 | G50: 0 | H50: 95030010 | I50: 6 | J50: 46.5 | K50: 8.6 | M50: ACTIVE | O50: STD | P50: Jeep® Revolution pedal go-kart BFR-3 | Q50: Jeep® Revolution pedal go-kart BFR-3 | R50: Jeep® Revolution pedal go-kart BFR-3 | S50: Jeep® Revolution pedal go-kart BFR-3 | T50: 8715839051216 | U50: 0 | V50: TRUE | W50: FALSE | X50: FALSE | Y50: Purchase order | Z50: 709.92 | AA50: EUR | AB50: 572.67 | AC50: EUR | AD50: 687.2 | AE50: USD | AF50: 584.76 | AG50: EUR | AH50: 442.75 | AI50: GBP | AJ50: 859 | AK50: EUR
A51: 07.30.01.01 | C51: TRUE | D51: TRUE | E51: 1 | F51: 1 | G51: 1 | H51: 95030010 | I51: 1 | J51: 38.11 | K51: 6.89 | L51: NLD | M51: ACTIVE | O51: STD | P51: BERG Compact Sport BFR | Q51: BERG Compact Sport BFR | R51: BERG Compact Sport BFR | S51: BERG Compact Sport BFR | T51: 8715839054170 | U51: 0 | V51: TRUE | W51: FALSE | X51: FALSE | Y51: Purchase order | Z51: 362.81 | AA51: EUR | AB51: 292.67 | AC51: EUR | AD51: 335.33 | AE51: USD | AF51: 273.78 | AG51: EUR | AH51: 226.92 | AI51: GBP | AJ51: 439 | AK51: EUR
A52: 07.30.02.01 | C52: TRUE | D52: TRUE | E52: 1 | F52: 1 | G52: 1 | H52: 95030010 | I52: 1 | J52: 38.11 | K52: 6.89 | L52: NLD | M52: ACTIVE | O52: STD | P52: BERG Compact Pink BFR | Q52: BERG Compact Pink BFR | R52: BERG Compact Pink BFR | S52: BERG Compact Pink BFR | T52: 8715839054187 | U52: 0 | V52: TRUE | W52: FALSE | X52: FALSE | Y52: Purchase order | Z52: 362.81 | AA52: EUR | AB52: 292.67 | AC52: EUR | AD52: 335.33 | AE52: USD | AF52: 273.78 | AG52: EUR | AH52: 226.92 | AI52: GBP | AJ52: 439 | AK52: EUR
A53: 07.45.01.00 | C53: FALSE | D53: FALSE | E53: 1 | F53: 1 | G53: 1 | H53: 95030010 | I53: 1 | J53: 0.01 | K53: 0 | M53: UNDER_CON | O53: STD | P53: BERG E-Extra Sport BFR | Q53: BERG E-Extra Sport BFR | R53: BERG E-Extra Sport BFR | S53: BERG E-Extra Sport BFR | T53: 8715839063318 | U53: 0 | V53: TRUE | W53: TRUE | X53: FALSE | Y53: Purchase order
A54: 07.45.02.00 | C54: FALSE | D54: FALSE | E54: 1 | F54: 1 | G54: 1 | H54: 95030010 | I54: 1 | J54: 0.01 | K54: 0 | M54: UNDER_CON | O54: STD | P54: BERG E-Race BFR | Q54: BERG E-Race BFR | R54: BERG E-Race BFR | S54: BERG E-Race BFR | T54: 8715839063325 | U54: 0 | V54: TRUE | W54: TRUE | X54: FALSE | Y54: Purchase order
A55: 07.45.03.00 | C55: FALSE | D55: FALSE | E55: 1 | F55: 1 | G55: 1 | H55: 95030010 | I55: 1 | J55: 0.01 | K55: 0 | M55: UNDER_CON | O55: STD | P55: BERG E-X-Plore BFR | Q55: BERG E-X-Plore BFR | R55: BERG E-X-Plore BFR | S55: BERG E-X-Plore BFR | T55: 8715839063332 | U55: 0 | V55: TRUE | W55: TRUE | X55: FALSE | Y55: Purchase order
A56: 07.45.05.00 | C56: FALSE | D56: FALSE | E56: 1 | F56: 1 | G56: 1 | H56: 95030010 | I56: 1 | J56: 0.01 | K56: 0 | M56: UNDER_CON | O56: STD | P56: BERG E-Black Edition BFR | Q56: BERG E-Black Edition BFR | R56: BERG E-Black Edition BFR | S56: BERG E-Black Edition BFR | T56: 8715839063349 | U56: 0 | V56: TRUE | W56: TRUE | X56: FALSE | Y56: Purchase order
A57: 07.45.07.00 | C57: FALSE | D57: FALSE | E57: 1 | F57: 1 | G57: 1 | H57: 95030010 | I57: 1 | J57: 0.01 | K57: 0 | M57: UNDER_CON | O57: STD | P57: BERG E-Safari BFR | Q57: BERG E-Safari BFR | R57: BERG E-Safari BFR | S57: BERG E-Safari BFR | T57: 8715839063356 | U57: 0 | V57: TRUE | W57: TRUE | X57: FALSE | Y57: Purchase order
A58: 07.45.08.00 | C58: FALSE | D58: FALSE | E58: 1 | F58: 1 | G58: 1 | H58: 95030010 | I58: 1 | J58: 0.01 | K58: 0 | M58: UNDER_CON | O58: STD | P58: BERG E-X-Cross BFR | Q58: BERG E-X-Cross BFR | R58: BERG E-X-Cross BFR | S58: BERG E-X-Cross BFR | T58: 8715839063363 | U58: 0 | V58: TRUE | W58: TRUE | X58: FALSE | Y58: Purchase order
A59: 07.45.12.00 | C59: FALSE | D59: FALSE | E59: 1 | F59: 1 | G59: 1 | H59: 95030010 | I59: 1 | J59: 0.01 | K59: 0 | M59: UNDER_CON | O59: STD | P59: BERG E-Extra Sport Red BFR | Q59: BERG E-Extra Sport Red BFR | R59: BERG E-Extra Sport Red BFR | S59: BERG E-Extra Sport Red BFR | T59: 8715839063448 | U59: 0 | V59: TRUE | W59: TRUE | X59: FALSE | Y59: Purchase order
A60: 07.46.00.00 | C60: FALSE | D60: FALSE | E60: 1 | F60: 1 | G60: 1 | H60: 95030010 | I60: 1 | J60: 0.01 | K60: 0 | M60: UNDER_CON | O60: STD | P60: BERG E-John Deere BFR | Q60: BERG E-John Deere BFR | R60: BERG E-John Deere BFR | S60: BERG E-John Deere BFR | T60: 8715839063370 | U60: 0 | V60: TRUE | W60: TRUE | X60: FALSE | Y60: Purchase order
A61: 07.46.01.00 | C61: FALSE | D61: FALSE | E61: 1 | F61: 1 | G61: 1 | H61: 95030010 | I61: 1 | J61: 0.01 | K61: 0 | M61: UNDER_CON | O61: STD | P61: BERG E-CLAAS BFR | Q61: BERG E-CLAAS BFR | R61: BERG E-CLAAS BFR | S61: BERG E-CLAAS BFR | T61: 8715839063387 | U61: 0 | V61: TRUE | W61: TRUE | X61: FALSE | Y61: Purchase order
A62: 07.46.02.00 | C62: FALSE | D62: FALSE | E62: 1 | F62: 1 | G62: 1 | H62: 95030010 | I62: 1 | J62: 0.01 | K62: 0 | M62: UNDER_CON | O62: STD | P62: BERG E-Case IH BFR | Q62: BERG E-Case IH BFR | R62: BERG E-Case IH BFR | S62: BERG E-Case IH BFR | T62: 8715839063394 | U62: 0 | V62: TRUE | W62: TRUE | X62: FALSE | Y62: Purchase order
A63: 07.46.03.00 | C63: FALSE | D63: FALSE | E63: 1 | F63: 1 | G63: 1 | H63: 95030010 | I63: 1 | J63: 0.01 | K63: 0 | M63: UNDER_CON | O63: STD | P63: BERG E-New Holland BFR | Q63: BERG E-New Holland BFR | R63: BERG E-New Holland BFR | S63: BERG E-New Holland BFR | T63: 8715839063400 | U63: 0 | V63: TRUE | W63: TRUE | X63: FALSE | Y63: Purchase order
A64: 07.46.04.00 | C64: FALSE | D64: FALSE | E64: 1 | F64: 1 | G64: 1 | H64: 95030010 | I64: 1 | J64: 0.01 | K64: 0 | M64: UNDER_CON | O64: STD | P64: BERG E-Fendt BFR | Q64: BERG E-Fendt BFR | R64: BERG E-Fendt BFR | S64: BERG E-Fendt BFR | T64: 8715839063417 | U64: 0 | V64: TRUE | W64: TRUE | X64: FALSE | Y64: Purchase order
... A66: 07.46.06.00 | C66: FALSE | D66: FALSE | E66: 1 | F66: 1 | G66: 1 | H66: 95030010 | I66: 1 | J66: 0.01 | K66: 0 | M66: UNDER_CON | O66: STD | P66: Jeep® Revolution pedal go-kart E-BFR | Q66: Jeep® Revolution pedal go-kart E-BFR | R66: Jeep® Revolution pedal go-kart E-BFR | S66: Jeep® Revolution pedal go-kart E-BFR | T66: 8715839063431 | U66: 0 | V66: TRUE | W66: TRUE | X66: FALSE | Y66: Purchase order
A67: 07.50.00.00 | B67: 07.50.00.01 | C67: FALSE | D67: FALSE | E67: 100 | F67: 40 | G67: 58.5 | H67: 95030010 | I67: 10 | J67: 27.65 | K67: 4.35 | L67: CHN | M67: ENDING | N67: 350653 | O67: STD | P67: BERG XL Rahmen BFR | Q67: BERG Cadre XL BFR | R67: BERG XL Frame BFR | S67: BERG XL Frame BFR | T67: 8715839050417 | U67: 296 | V67: TRUE | W67: FALSE | X67: FALSE | Y67: Purchase order | Z67: 227.27 | AA67: EUR | AB67: 183.33 | AC67: EUR | AD67: 220 | AE67: USD | AF67: 192.5 | AG67: EUR | AH67: 152.16 | AI67: GBP | AJ67: 275 | AK67: EUR
A68: 07.50.00.01 | C68: TRUE | D68: TRUE | E68: 100 | F68: 40 | G68: 58.5 | H68: 95030010 | I68: 10 | J68: 27.64 | K68: 3.86 | L68: CHN | M68: UNDER_CON | N68: 350653 | O68: STD | P68: BERG XL Rahmen BFR | Q68: BERG Cadre XL BFR | R68: BERG XL Frame BFR | S68: BERG XL Frame BFR | T68: 8715839061338 | U68: 296 | V68: FALSE | W68: FALSE | X68: FALSE | Y68: Purchase order | Z68: 227.27 | AA68: EUR | AB68: 183.33 | AC68: EUR | AD68: 220 | AE68: USD | AF68: 192.5 | AG68: EUR | AH68: 152.16 | AI68: GBP | AJ68: 275 | AK68: EUR
A69: 07.50.01.00 | B69: 07.50.01.01 | C69: TRUE | D69: TRUE | E69: 100 | F69: 40 | G69: 60 | H69: 95030010 | I69: 10 | J69: 28.14 | K69: 4.16 | L69: CHN | M69: ENDING | N69: 350653 | O69: STD | P69: BERG Chopper Rahmen BFR | Q69: BERG Chopper Cadre BFR | R69: BERG Chopper Frame BFR | S69: BERG Chopper Frame BFR | T69: 8715839051223 | U69: 296 | V69: TRUE | W69: FALSE | X69: FALSE | Y69: Purchase order | Z69: 227.27 | AA69: EUR | AB69: 183.33 | AC69: EUR | AD69: 220 | AE69: USD | AF69: 192.5 | AG69: EUR | AH69: 152.16 | AI69: GBP | AJ69: 275 | AK69: EUR
A70: 07.50.01.01 | C70: FALSE | D70: FALSE | E70: 100 | F70: 40 | G70: 58.5 | H70: 95030010 | I70: 10 | J70: 0.01 | K70: 0 | L70: CHN | M70: UNDER_CON | N70: 350653 | O70: STD | P70: BERG Chopper Rahmen BFR | Q70: BERG Chopper Cadre BFR | R70: BERG Chopper Frame BFR | S70: BERG Chopper Frame BFR | T70: 8715839061468 | U70: 296 | V70: TRUE | W70: TRUE | X70: FALSE | Y70: Purchase order
A71: 07.50.02.00 | C71: TRUE | D71: TRUE | E71: 58 | F71: 40 | G71: 100 | H71: 95030010 | I71: 10 | J71: 26.6 | K71: 5.2 | L71: CHN | M71: UNDER_CON | N71: 350653 | O71: STD | P71: BERG Duo Chopper Frame BF | Q71: BERG Duo Chopper Frame BF | R71: BERG Duo Chopper Frame BF | S71: BERG Duo Chopper Frame BF | T71: 8715839058574 | U71: 175 | V71: FALSE | W71: FALSE | X71: FALSE | Y71: Purchase order | Z71: 326.45 | AA71: EUR | AB71: 263.34 | AC71: EUR | AD71: 301.01 | AE71: USD | AF71: 263.34 | AG71: EUR | AH71: 229.43 | AI71: GBP | AJ71: 395.01 | AK71: EUR
A72: 07.50.03.00 | C72: TRUE | D72: TRUE | E72: 75 | F72: 75 | G72: 29.5 | H72: 95030010 | I72: 10 | J72: 17.8 | K72: 3.1 | L72: CHN | M72: UNDER_CON | N72: 350653 | O72: STD | P72: BERG Duo Chopper Sidecar | Q72: BERG Duo Chopper Sidecar | R72: BERG Duo Chopper Sidecar | S72: BERG Duo Chopper Sidecar | T72: 8715839061345 | U72: 175 | V72: FALSE | W72: FALSE | X72: FALSE | Y72: Purchase order | Z72: 168.48 | AA72: EUR | AB72: 135.91 | AC72: EUR | AD72: 155.35 | AE72: USD | AF72: 135.91 | AG72: EUR | AH72: 118.41 | AI72: GBP | AJ72: 203.86 | AK72: EUR
A73: 07.51.00.01 | B73: 07.51.00.02 | C73: TRUE | D73: TRUE | E73: 60 | F73: 40 | G73: 100 | H73: 95030010 | I73: 8 | J73: 23.63 | K73: 3.77 | L73: CHN | M73: ENDING | N73: 350653 | O73: STD | P73: BERG Compact Rahmen BFR | Q73: BERG Compact Cadre BFR | R73: BERG Compact Frame BFR | S73: BERG Compact Frame BFR | T73: 8715839052398 | U73: 195 | V73: TRUE | W73: FALSE | X73: FALSE | Y73: Purchase order | Z73: 198.35 | AA73: EUR | AB73: 160 | AC73: EUR | AD73: 192 | AE73: USD | AF73: 168 | AG73: EUR | AH73: 132.8 | AI73: GBP | AJ73: 240 | AK73: EUR
A74: 07.51.00.02 | C74: FALSE | D74: FALSE | E74: 100 | F74: 40 | G74: 58.5 | H74: 95030010 | I74: 10 | J74: 0.01 | K74: 0 | L74: CHN | M74: UNDER_CON | N74: 350653 | O74: STD | P74: BERG Compact Rahmen BFR | Q74: BERG Compact Cadre BFR | R74: BERG Compact Frame BFR | S74: BERG Compact Frame BFR | T74: 8715839061475 | U74: 0 | V74: FALSE | W74: FALSE | X74: FALSE | Y74: Purchase order
A75: 07.52.00.00 | B75: 07.52.00.01 | C75: FALSE | D75: FALSE | E75: 100 | F75: 40 | G75: 58.5 | H75: 95030010 | I75: 10 | J75: 28.45 | K75: 4.35 | L75: CHN | M75: ENDING | N75: 350653 | O75: STD | P75: BERG XL Rahmen BFR-3 | Q75: BERG Cadre XL BFR-3 | R75: BERG XL Frame BFR-3 | S75: BERG XL Frame BFR-3 | T75: 8715839051230 | U75: 296 | V75: TRUE | W75: FALSE | X75: FALSE | Y75: Purchase order | Z75: 409.09 | AA75: EUR | AB75: 330 | AC75: EUR | AD75: 396 | AE75: USD | AF75: 346.5 | AG75: EUR | AH75: 273.9 | AI75: GBP | AJ75: 495 | AK75: EUR
A76: 07.52.00.01 | C76: TRUE | D76: TRUE | E76: 100 | F76: 40 | G76: 58.5 | H76: 95030010 | I76: 10 | J76: 28.45 | K76: 4.15 | L76: CHN | M76: UNDER_CON | N76: 350653 | O76: STD | P76: BERG XL Rahmen BFR-3 | Q76: BERG Cadre XL BFR-3 | R76: BERG XL Frame BFR-3 | S76: BERG XL Frame BFR-3 | T76: 8715839061451 | U76: 296 | V76: FALSE | W76: FALSE | X76: FALSE | Y76: Purchase order | Z76: 409.09 | AA76: EUR | AB76: 330 | AC76: EUR | AD76: 396 | AE76: USD | AF76: 346.5 | AG76: EUR | AH76: 273.9 | AI76: GBP | AJ76: 495 | AK76: EUR
A77: 07.55.00.00 | C77: TRUE | D77: TRUE | E77: 41 | F77: 50 | G77: 58 | H77: 95030010 | I77: 20 | J77: 14.9 | K77: 2 | L77: NLD | M77: ACTIVE | N77: 310001 | O77: STD | P77: BERG Extra Theme (excl. XL Frame) | Q77: BERG Extra Theme (excl. XL Frame) | R77: BERG Extra Theme (excl. XL Frame) | S77: BERG Extra Theme (excl. XL Frame) | T77: 8715839050356 | U77: 0 | V77: FALSE | W77: FALSE | X77: FALSE | Y77: Production | Z77: 180.91 | AA77: EUR | AB77: 145.93 | AC77: EUR | AD77: 175.12 | AE77: USD | AF77: 153.23 | AG77: EUR | AH77: 103.86 | AI77: GBP | AJ77: 218.9 | AK77: EUR
A78: 07.55.00.01 | C78: TRUE | D78: TRUE | E78: 58 | F78: 31.5 | G78: 100 | H78: 95030010 | I78: 12 | J78: 16 | K78: 4.6 | L78: NLD | M78: ACTIVE | N78: 310001 | O78: STD | P78: BERG Extra Sport Theme (excl. XL Frame) | Q78: BERG Extra Sport Theme (excl. XL Frame) | R78: BERG Extra Sport Theme (excl. XL Frame) | S78: BERG Extra Sport Theme (excl. XL Frame) | T78: 8715839051247 | U78: 0 | V78: FALSE | W78: FALSE | X78: FALSE | Y78: Production | Z78: 226.36 | AA78: EUR | AB78: 182.6 | AC78: EUR | AD78: 219.12 | AE78: USD | AF78: 191.73 | AG78: EUR | AH78: 135.95 | AI78: GBP | AJ78: 273.9 | AK78: EUR
A79: 07.55.00.02 | C79: TRUE | D79: TRUE | E79: 58 | F79: 31.5 | G79: 100 | H79: 95030010 | I79: 12 | J79: 17.8 | K79: 4.7 | L79: NLD | M79: ACTIVE | N79: 310001 | O79: STD | P79: BERG Black edition Theme (excl. XL Frame) | Q79: BERG Black edition Theme (excl. XL Frame) | R79: BERG Black edition Theme (excl. XL Frame) | S79: BERG Black edition Theme (excl. XL Frame) | T79: 8715839051254 | U79: 0 | V79: FALSE | W79: FALSE | X79: FALSE | Y79: Production | Z79: 290 | AA79: EUR | AB79: 233.93 | AC79: EUR | AD79: 280.72 | AE79: USD | AF79: 245.63 | AG79: EUR | AH79: 148.78 | AI79: GBP | AJ79: 350.9 | AK79: EUR
A80: 07.55.00.04 | C80: TRUE | D80: TRUE | E80: 58 | F80: 41.5 | G80: 100 | H80: 95030010 | I80: 10 | J80: 18.9 | K80: 4.7 | L80: NLD | M80: ACTIVE | N80: 310001 | O80: STD | P80: Jeep® Revolution Theme (excl. XL Frame) | Q80: Jeep® Revolution Theme (excl. XL Frame) | R80: Jeep® Revolution Theme (excl. XL Frame) | S80: Jeep® Revolution Theme (excl. XL Frame) | T80: 8715839051261 | U80: 0 | V80: FALSE | W80: FALSE | X80: FALSE | Y80: Production | Z80: 371.82 | AA80: EUR | AB80: 299.93 | AC80: EUR | AD80: 359.92 | AE80: USD | AF80: 314.93 | AG80: EUR | AH80: 225.78 | AI80: GBP | AJ80: 449.9 | AK80: EUR
A81: 07.55.00.05 | C81: TRUE | D81: TRUE | E81: 58 | F81: 41 | G81: 100 | H81: 95030010 | I81: 10 | J81: 25.4 | K81: 5.2 | L81: NLD | M81: ACTIVE | N81: 310001 | O81: STD | P81: BERG John Deere Theme (excl. XL Frame) | Q81: BERG John Deere Theme (excl. XL Frame) | R81: BERG John Deere Theme (excl. XL Frame) | S81: BERG John Deere Theme (excl. XL Frame) | T81: 8715839051278 | U81: 0 | V81: FALSE | W81: FALSE | X81: FALSE | Y81: Production | Z81: 390 | AA81: EUR | AB81: 314.6 | AC81: EUR | AD81: 377.52 | AE81: USD | AF81: 330.33 | AG81: EUR | AH81: 232.2 | AI81: GBP | AJ81: 471.9 | AK81: EUR
A82: 07.55.00.06 | C82: TRUE | D82: TRUE | E82: 58 | F82: 41.5 | G82: 100 | H82: 95030010 | I82: 10 | J82: 25.4 | K82: 5.2 | L82: NLD | M82: ACTIVE | N82: 310001 | O82: STD | P82: BERG CLAAS Theme (excl. XL Frame) | Q82: BERG CLAAS Theme (excl. XL Frame) | R82: BERG CLAAS Theme (excl. XL Frame) | S82: BERG CLAAS Theme (excl. XL Frame) | T82: 8715839051285 | U82: 0 | V82: FALSE | W82: FALSE | X82: FALSE | Y82: Production | Z82: 390 | AA82: EUR | AB82: 314.6 | AC82: EUR | AD82: 377.52 | AE82: USD | AF82: 330.33 | AG82: EUR | AH82: 232.2 | AI82: GBP | AJ82: 471.9 | AK82: EUR
A83: 07.55.00.07 | C83: TRUE | D83: TRUE | E83: 58 | F83: 41.5 | G83: 100 | H83: 95030010 | I83: 10 | J83: 25.4 | K83: 5.2 | L83: NLD | M83: ACTIVE | N83: 310001 | O83: STD | P83: BERG Case IH Theme (excl. XL Frame) | Q83: BERG Case IH Theme (excl. XL Frame) | R83: BERG Case IH Theme (excl. XL Frame) | S83: BERG Case IH Theme (excl. XL Frame) | T83: 8715839051292 | U83: 0 | V83: FALSE | W83: FALSE | X83: FALSE | Y83: Production | Z83: 390 | AA83: EUR | AB83: 314.6 | AC83: EUR | AD83: 377.52 | AE83: USD | AF83: 330.33 | AG83: EUR | AH83: 232.2 | AI83: GBP | AJ83: 471.9 | AK83: EUR
A84: 07.55.00.08 | C84: TRUE | D84: TRUE | E84: 58 | F84: 41.5 | G84: 100 | H84: 95030010 | I84: 10 | J84: 25.2 | K84: 5.2 | L84: NLD | M84: ACTIVE | N84: 310001 | O84: STD | P84: BERG New Holland Theme (excl. XL Frame) | Q84: BERG New Holland Theme (excl. XL Frame) | R84: BERG New Holland Theme (excl. XL Frame) | S84: BERG New Holland Theme (excl. XL Frame) | T84: 8715839051308 | U84: 0 | V84: FALSE | W84: FALSE | X84: FALSE | Y84: Production | Z84: 390 | AA84: EUR | AB84: 314.6 | AC84: EUR | AD84: 377.52 | AE84: USD | AF84: 330.33 | AG84: EUR | AH84: 232.2 | AI84: GBP | AJ84: 471.9 | AK84: EUR
A85: 07.55.00.09 | C85: TRUE | D85: TRUE | E85: 58 | F85: 41.5 | G85: 100 | H85: 95030010 | I85: 10 | J85: 25.4 | K85: 5.2 | L85: NLD | M85: ACTIVE | N85: 310001 | O85: STD | P85: BERG Fendt Theme (excl. XL Frame) | Q85: BERG Fendt Theme (excl. XL Frame) | R85: BERG Fendt Theme (excl. XL Frame) | S85: BERG Fendt Theme (excl. XL Frame) | T85: 8715839051315 | U85: 0 | V85: FALSE | W85: FALSE | X85: FALSE | Y85: Production | Z85: 390 | AA85: EUR | AB85: 314.6 | AC85: EUR | AD85: 377.52 | AE85: USD | AF85: 330.33 | AG85: EUR | AH85: 232.2 | AI85: GBP | AJ85: 471.9 | AK85: EUR
A86: 07.55.00.10 | C86: TRUE | D86: TRUE | E86: 58 | F86: 41.5 | G86: 100 | H86: 95030010 | I86: 10 | J86: 25.4 | K86: 5.2 | L86: NLD | M86: ACTIVE | N86: 310001 | O86: STD | P86: BERG DEUTZ-FAHR Theme (excl. XL Frame) | Q86: BERG DEUTZ-FAHR Theme (excl. XL Frame) | R86: BERG DEUTZ-FAHR Theme (excl. XL Frame) | S86: BERG DEUTZ-FAHR Theme (excl. XL Frame) | T86: 8715839051322 | U86: 0 | V86: FALSE | W86: FALSE | X86: FALSE | Y86: Production | Z86: 390 | AA86: EUR | AB86: 314.6 | AC86: EUR | AD86: 377.52 | AE86: USD | AF86: 330.33 | AG86: EUR | AH86: 232.2 | AI86: GBP | AJ86: 471.9 | AK86: EUR
A87: 07.55.00.11 | C87: TRUE | D87: TRUE | E87: 58 | F87: 41.5 | G87: 100 | H87: 95030010 | I87: 10 | J87: 22.4 | K87: 4.7 | L87: NLD | M87: ACTIVE | N87: 310001 | O87: STD | P87: BERG Race Theme (excl. XL Frame) | Q87: BERG Race Theme (excl. XL Frame) | R87: BERG Race Theme (excl. XL Frame) | S87: BERG Race Theme (excl. XL Frame) | T87: 8715839051339 | U87: 0 | V87: FALSE | W87: FALSE | X87: FALSE | Y87: Production | Z87: 344.55 | AA87: EUR | AB87: 277.93 | AC87: EUR | AD87: 333.52 | AE87: USD | AF87: 291.83 | AG87: EUR | AH87: 289.95 | AI87: GBP | AJ87: 416.9 | AK87: EUR
... A93: 07.55.17.00 | C93: TRUE | D93: TRUE | E93: 41 | F93: 50 | G93: 58 | H93: 95030010 | I93: 20 | J93: 14.5 | K93: 2 | L93: NLD | M93: UNDER_CON | N93: 310001 | O93: STD | P93: BERG Duo Chopper Theme | Q93: BERG Duo Chopper Theme | R93: BERG Duo Chopper Theme | S93: BERG Duo Chopper Theme | T93: 8715839058581 | U93: 0 | V93: TRUE | W93: FALSE | X93: FALSE | Y93: Production | Z93: 140.52 | AA93: EUR | AB93: 113.35 | AC93: EUR | AD93: 129.57 | AE93: USD | AF93: 113.35 | AG93: EUR | AH93: 98.76 | AI93: GBP | AJ93: 170.03 | AK93: EUR
A94: 07.55.20.00 | C94: FALSE | D94: FALSE | E94: 41 | F94: 50 | G94: 58 | H94: 95030010 | I94: 20 | J94: 14.9 | K94: 2 | M94: UNDER_CON | O94: STD | P94: BERG Extra Red Theme (excl. XL Frame) | Q94: BERG Extra Red Theme (excl. XL Frame) | R94: BERG Extra Red Theme (excl. XL Frame) | S94: BERG Extra Red Theme (excl. XL Frame) | T94: 8715839063516 | U94: 0 | V94: TRUE | W94: TRUE | X94: FALSE | Y94: Production | Z94: 180.91 | AA94: EUR | AB94: 145.93 | AC94: EUR | AD94: 175.12 | AE94: USD | AF94: 153.23 | AG94: EUR | AH94: 103.86 | AI94: GBP | AJ94: 218.9 | AK94: EUR
A95: 07.55.21.00 | C95: FALSE | D95: FALSE | E95: 58 | F95: 31.5 | G95: 100 | H95: 95030010 | I95: 6 | J95: 16 | K95: 4.6 | M95: UNDER_CON | O95: STD | P95: BERG Extra Sport Red Theme (excl. XL Frame) | Q95: BERG Extra Sport Red Theme (excl. XL Frame) | R95: BERG Extra Sport Red Theme (excl. XL Frame) | S95: BERG Extra Sport Red Theme (excl. XL Frame) | T95: 8715839063523 | U95: 0 | V95: TRUE | W95: TRUE | X95: FALSE | Y95: Production | Z95: 226.36 | AA95: EUR | AB95: 182.6 | AC95: EUR | AD95: 219.12 | AE95: USD | AF95: 191.73 | AG95: EUR | AH95: 135.95 | AI95: GBP | AJ95: 273.9 | AK95: EUR
A96: 07.55.22.00 | C96: FALSE | D96: FALSE | E96: 41 | F96: 50 | G96: 58 | H96: 95030010 | I96: 20 | J96: 13.2 | K96: 2 | M96: UNDER_CON | O96: STD | P96: BERG Basic Red Theme (excl. XL Frame) | Q96: BERG Basic Red Theme (excl. XL Frame) | R96: BERG Basic Red Theme (excl. XL Frame) | S96: BERG Basic Red Theme (excl. XL Frame) | T96: 8715839063530 | U96: 0 | V96: TRUE | W96: TRUE | X96: FALSE | Y96: Production | Z96: 153.64 | AA96: EUR | AB96: 123.93 | AC96: EUR | AD96: 148.72 | AE96: USD | AF96: 130.13 | AG96: EUR | AH96: 71.78 | AI96: GBP | AJ96: 185.9 | AK96: EUR
A97: 07.55.23.00 | C97: FALSE | D97: FALSE | E97: 58 | F97: 31.5 | G97: 100 | H97: 95030010 | I97: 6 | J97: 0.01 | K97: 0 | M97: UNDER_CON | O97: STD | P97: BERG Special christmas 2017 (excl. XL Frame) | Q97: BERG Special christmas 2017 (excl. XL Frame) | R97: BERG Special christmas 2017 (excl. XL Frame) | S97: BERG Special christmas 2017 (excl. XL Frame) | U97: 0 | V97: TRUE | W97: TRUE | X97: FALSE | Y97: Production
A98: 07.60.00.01 | C98: TRUE | D98: TRUE | E98: 60 | F98: 50 | G98: 40 | H98: 95030010 | I98: 20 | J98: 14.48 | K98: 3.12 | L98: CHN | M98: ACTIVE | N98: 350653 | O98: STD | P98: BERG Compact Sport theme (excl. Compact frame) | Q98: BERG Compact Sport theme (excl. Compact frame) | R98: BERG Compact Sport theme (excl. Compact frame) | S98: BERG Compact Sport theme (excl. Compact frame) | T98: 8715839052404 | U98: 195 | V98: FALSE | W98: FALSE | X98: FALSE | Y98: Purchase order | Z98: 198.35 | AA98: EUR | AB98: 160 | AC98: EUR | AD98: 192 | AE98: USD | AF98: 168 | AG98: EUR | AH98: 132.8 | AI98: GBP | AJ98: 240 | AK98: EUR
A99: 07.60.01.01 | C99: TRUE | D99: TRUE | E99: 60 | F99: 50 | G99: 40 | H99: 95030010 | I99: 20 | J99: 14.48 | K99: 3.12 | L99: CHN | M99: ACTIVE | N99: 350653 | O99: STD | P99: BERG Compact Pink theme (excl. Compact frame) | Q99: BERG Compact Pink theme (excl. Compact frame) | R99: BERG Compact Pink theme (excl. Compact frame) | S99: BERG Compact Pink theme (excl. Compact frame) | T99: 8715839052411 | U99: 195 | V99: FALSE | W99: FALSE | X99: FALSE | Y99: Purchase order | Z99: 198.35 | AA99: EUR | AB99: 160 | AC99: EUR | AD99: 192 | AE99: USD | AF99: 168 | AG99: EUR | AH99: 132.8 | AI99: GBP | AJ99: 240 | AK99: EUR
A100: 15.03.32.00 | C100: TRUE | D100: TRUE | E100: 32 | F100: 11 | G100: 18 | H100: 95030010 | I100: 120 | J100: 1 | K100: 0.01 | L100: DEU | M100: ACTIVE | N100: 350017 | O100: RiOn spare | P100: BERG Kotflügel-Set vorne Schwarz | Q100: BERG Garde-boue avant noir | R100: BERG Voorspatborden zwart | S100: BERG Front mudguards black | T100: 8715839054712 | U100: 150 | V100: FALSE | W100: FALSE | X100: FALSE | Y100: Purchase order | Z100: 28.1 | AA100: EUR | AB100: 22.67 | AC100: EUR | AD100: 27.2 | AE100: USD | AF100: 23.78 | AG100: EUR | AH100: 19.25 | AI100: GBP | AJ100: 34 | AK100: EUR
A101: 15.08.28.01 | C101: FALSE | D101: TRUE | E101: 20 | F101: 10 | G101: 10 | H101: 95030010 | I101: 0 | J101: 3.3 | K101: 0.1 | L101: CHN | M101: ACTIVE | N101: 350653 | O101: STD | P101: BERG Rammschutz, gummiert (Für XL Frame) | Q101: BERG Pare-chocs en caoutchouc (pour Cadre XL) | R101: BERG Stootbumper (voor XL Frame) | S101: BERG Rubber Go-kart bumper (for XL Frame) | T101: 8715839053869 | U101: 250 | V101: FALSE | W101: FALSE | X101: FALSE | Y101: Purchase order | Z101: 40.5 | AA101: EUR | AB101: 32.67 | AC101: EUR | AD101: 36 | AE101: USD | AF101: 35.98 | AG101: EUR | AH101: 25.08 | AI101: GBP | AJ101: 49 | AK101: EUR
A102: 15.09.08.00 | C102: TRUE | D102: TRUE | E102: 20 | F102: 10 | G102: 10 | H102: 95030010 | I102: 200 | J102: 1.1 | K102: 0.1 | L102: CHN | M102: ACTIVE | N102: 350653 | O102: STD | P102: BERG Stützfuß | Q102: BERG Pied de soutien | R102: BERG Steunpoot | S102: BERG Support strut | T102: 8715839011630 | U102: 150 | V102: FALSE | W102: FALSE | X102: FALSE | Y102: Purchase order | Z102: 20.66 | AA102: EUR | AB102: 16.67 | AC102: EUR | AD102: 20 | AE102: USD | AF102: 17.67 | AG102: EUR | AH102: 12.83 | AI102: GBP | AJ102: 25 | AK102: EUR
A103: 15.20.01.00 | C103: TRUE | D103: TRUE | E103: 20 | F103: 10 | G103: 10 | H103: 95030010 | I103: 144 | J103: 0.29 | K103: 0.01 | L103: CHN | M103: ACTIVE | N103: 350653 | O103: STD | P103: BERG LED Vorderlicht | Q103: BERG LED phare | R103: BERG LED koplamp | S103: BERG LED headlight | T103: 8715839019476 | U103: 50 | V103: FALSE | W103: FALSE | X103: FALSE | Y103: Purchase order | Z103: 23.97 | AA103: EUR | AB103: 19.33 | AC103: EUR | AD103: 23.2 | AE103: USD | AF103: 21.32 | AG103: EUR | AH103: 18.08 | AI103: GBP | AJ103: 29 | AK103: EUR
A104: 15.20.10.00 | C104: TRUE | D104: TRUE | E104: 20 | F104: 10 | G104: 10 | H104: 95030010 | I104: 144 | J104: 0.11 | K104: 0.01 | L104: CHN | M104: ACTIVE | N104: 350653 | O104: STD | P104: BERG LED weiß | Q104: BERG LED blanc | R104: BERG LED wit | S104: BERG LED white | T104: 8715839011883 | U104: 100 | V104: FALSE | W104: FALSE | X104: FALSE | Y104: Purchase order | Z104: 12.4 | AA104: EUR | AB104: 10 | AC104: EUR | AD104: 12 | AE104: USD | AF104: 11.57 | AG104: EUR | AH104: 9.92 | AI104: GBP | AJ104: 15 | AK104: EUR
A105: 15.20.20.00 | C105: TRUE | D105: TRUE | E105: 20 | F105: 10 | G105: 10 | H105: 95030010 | I105: 144 | J105: 0.11 | K105: 0.01 | L105: CHN | M105: ACTIVE | N105: 350653 | O105: STD | P105: BERG LED rot | Q105: BERG LED rouge | R105: BERG LED rood | S105: BERG LED red | T105: 8715839011890 | U105: 100 | V105: FALSE | W105: FALSE | X105: FALSE | Y105: Purchase order | Z105: 12.4 | AA105: EUR | AB105: 10 | AC105: EUR | AD105: 12 | AE105: USD | AF105: 11.57 | AG105: EUR | AH105: 9.92 | AI105: GBP | AJ105: 15 | AK105: EUR
A106: 15.20.45.00 | C106: TRUE | D106: TRUE | E106: 20 | F106: 10 | G106: 10 | H106: 95030010 | I106: 150 | J106: 0.57 | K106: 0.01 | L106: CHN | M106: ACTIVE | N106: 350653 | O106: STD | P106: BERG Beleuchtungs-Set | Q106: BERG Set d 'éclairage | R106: BERG Verlichtingsset | S106: BERG Light set | T106: 8715839019483 | U106: 500 | V106: FALSE | W106: FALSE | X106: FALSE | Y106: Purchase order | Z106: 32.23 | AA106: EUR | AB106: 26 | AC106: EUR | AD106: 31.2 | AE106: USD | AF106: 27.41 | AG106: EUR | AH106: 22.75 | AI106: GBP | AJ106: 39 | AK106: EUR
A107: 15.21.01.00 | C107: TRUE | D107: TRUE | E107: 20 | F107: 10 | G107: 10 | H107: 95030010 | I107: 300 | J107: 0.31 | K107: 0.01 | L107: CHN | M107: ACTIVE | N107: 350653 | O107: STD | P107: BERG Spiegel-Set | Q107: BERG Set de rétroviseurs | R107: BERG Spiegelset | S107: BERG Mirror set | T107: 8715839015454 | U107: 500 | V107: FALSE | W107: FALSE | X107: FALSE | Y107: Purchase order | Z107: 20.66 | AA107: EUR | AB107: 16.67 | AC107: EUR | AD107: 15.2 | AE107: USD | AF107: 17.68 | AG107: EUR | AH107: 14 | AI107: GBP | AJ107: 25 | AK107: EUR
...

Sheet Sheet1
A1: Item number | B1: Product name nl
A2: 35.09.01.01 | B2: BERG Favorit 270 + Safety Net Comfort 270
A3: 35.09.03.00 | B3: BERG Favorit 270 + Safety Net Deluxe 270
A4: 35.09.04.00 | B4: BERG InGround Favorit 270 + Safety Net Deluxe
A5: 35.09.05.00 | B5: BERG InGround Favorit 270 + Safety Net Comfort (InGr)
A6: 35.09.07.06 | B6: BERG Favorit 270 (9ft)
A7: 35.09.47.02 | B7: BERG InGround Favorit 270 (9ft)
A8: 35.11.01.01 | B8: BERG Favorit 330 + Safety Net Comfort 330
A9: 35.11.02.00 | B9: BERG Favorit 330 + Safety Net Deluxe 330
A10: 35.11.03.00 | B10: BERG InGround Favorit 330 + Safety Net Deluxe
A11: 35.11.04.00 | B11: BERG InGround Favorit 330 + Safety Net Comfort (InGr)
A12: 35.11.07.06 | B12: BERG Favorit 330 (11ft)
... A186: 38.14.67.00 | B186: BERG Flatground Champion Padding Green 430
